{
  "type": "Feature",
  "properties": {
    "gn:admin1_code":"9.0",
    "gn:asciiname":"En Nakhle",
    "gn:country_code":"LB",
    "gn:dem":306,
    "gn:feature_class":"P",
    "gn:feature_code":"PPL",
    "gn:name":"En Nakhl\u00e9",
    "gn:population":0,
    "gn:timezone":"Asia/Beirut",
    "iso:country":"LB",
    "name:ara_x_preferred":[
        "\u0627\u0644\u0646\u062e\u0644\u0629"
    ],
    "name:und_x_variant":[
        "Enn Nakhle",
        "En Nakhlah",
        "An Nakhlah",
        "En Nakhl\u00e9"
    ],
    "wof:name":"En Nakhle",
    "wof:placetype":"locality"
},
  "geometry": {"coordinates":[35.82722000000001,34.36444],"type":"Point"}
}