{
  "type": "Feature",
  "properties": {
    "gn:admin1_code":"5.0",
    "gn:asciiname":"Khaab",
    "gn:country_code":"LB",
    "gn:dem":1112,
    "gn:feature_class":"P",
    "gn:feature_code":"PPL",
    "gn:name":"Khaab",
    "gn:population":0,
    "gn:timezone":"Asia/Beirut",
    "iso:country":"LB",
    "name:und_x_variant":[
        "Kha\u2018b",
        "Khaab"
    ],
    "wof:name":"Khaab",
    "wof:placetype":"locality"
},
  "geometry": {"coordinates":[35.75583,34.12722],"type":"Point"}
}