{
  "type": "Feature",
  "properties": {
    "gn:admin1_code":"5.0",
    "gn:asciiname":"El Bayader",
    "gn:country_code":"LB",
    "gn:dem":521,
    "gn:feature_class":"P",
    "gn:feature_code":"PPL",
    "gn:name":"El Bay\u00e2der",
    "gn:population":0,
    "gn:timezone":"Asia/Beirut",
    "iso:country":"LB",
    "name:und_x_variant":[
        "Al Bay\u0101dir",
        "El Bay\u00e2der"
    ],
    "wof:name":"El Bayader",
    "wof:placetype":"locality"
},
  "geometry": {"coordinates":[35.67111,34.03611],"type":"Point"}
}