{
  "type": "Feature",
  "properties": {
    "gn:admin1_code":"6.0",
    "gn:asciiname":"El Ouata",
    "gn:country_code":"LB",
    "gn:dem":658,
    "gn:feature_class":"P",
    "gn:feature_code":"PPL",
    "gn:name":"El Ouata",
    "gn:population":0,
    "gn:timezone":"Asia/Beirut",
    "iso:country":"LB",
    "name:ara_x_preferred":[
        "\u0627\u0644\u0648\u0627\u062a\u0629"
    ],
    "name:azb_x_preferred":[
        "\u0627\u0644\u0648\u0627\u062a\u0629"
    ],
    "name:fas_x_preferred":[
        "\u0627\u0644\u0648\u0627\u062a\u0629"
    ],
    "name:fra_x_preferred":[
        "El Ouata"
    ],
    "name:ita_x_preferred":[
        "El Ouata"
    ],
    "name:msa_x_preferred":[
        "El Ouata"
    ],
    "name:por_x_preferred":[
        "El Ouata"
    ],
    "name:ron_x_preferred":[
        "El Ouata"
    ],
    "name:spa_x_preferred":[
        "El Ouata"
    ],
    "name:vie_x_preferred":[
        "El Ouata"
    ],
    "wof:name":"El Ouata",
    "wof:placetype":"locality"
},
  "geometry": {"coordinates":[35.53333,33.53472],"type":"Point"}
}