{
  "type": "Feature",
  "properties": {
    "gn:admin1_code":"6.0",
    "gn:asciiname":"El Ouata",
    "gn:country_code":"LB",
    "gn:dem":658,
    "gn:feature_class":"P",
    "gn:feature_code":"PPL",
    "gn:name":"El Ouata",
    "gn:population":0,
    "gn:timezone":"Asia/Beirut",
    "iso:country":"LB",
    "wof:name":"El Ouata",
    "wof:placetype":"locality"
},
  "geometry": {"coordinates":[35.53333,33.53472],"type":"Point"}
}