{
  "type": "Feature",
  "properties": {
    "gn:admin1_code":"5.0",
    "gn:asciiname":"Ed Daasse",
    "gn:country_code":"LB",
    "gn:dem":618,
    "gn:feature_class":"P",
    "gn:feature_code":"PPL",
    "gn:name":"Ed Daass\u00e9",
    "gn:population":0,
    "gn:timezone":"Asia/Beirut",
    "iso:country":"LB",
    "name:und_x_variant":[
        "Ad Da\u2018sah",
        "Ed Daass\u00e9"
    ],
    "wof:name":"Ed Daasse",
    "wof:placetype":"locality"
},
  "geometry": {"coordinates":[35.68167000000001,34.03722],"type":"Point"}
}