{
  "type": "Feature",
  "properties": {
    "gn:admin1_code":"5.0",
    "gn:asciiname":"Saoufar",
    "gn:country_code":"LB",
    "gn:dem":1282,
    "gn:feature_class":"P",
    "gn:feature_code":"PPL",
    "gn:name":"Saoufar",
    "gn:population":0,
    "gn:timezone":"Asia/Beirut",
    "iso:country":"LB",
    "name:ara_x_preferred":[
        "\u0635\u0648\u0641\u0631"
    ],
    "name:heb_x_preferred":[
        "\u05e1\u05d0\u05d5\u05e4\u05e8"
    ],
    "name:nno_x_preferred":[
        "Saoufar"
    ],
    "name:und_x_variant":[
        "\u015eawfar",
        "Saoufar"
    ],
    "wof:name":"Saoufar",
    "wof:placetype":"locality"
},
  "geometry": {"coordinates":[35.69889000000001,33.80222],"type":"Point"}
}