{
  "type": "Feature",
  "properties": {
    "gn:admin1_code":"9.0",
    "gn:asciiname":"Enfe",
    "gn:country_code":"LB",
    "gn:dem":13,
    "gn:feature_class":"P",
    "gn:feature_code":"PPL",
    "gn:name":"Enf\u00e9",
    "gn:population":0,
    "gn:timezone":"Asia/Beirut",
    "iso:country":"LB",
    "name:ara_x_preferred":[
        "\u0623\u0646\u0641\u0629"
    ],
    "name:ara_x_variant":[
        "\u0627\u0646\u0641\u0647"
    ],
    "name:cat_x_preferred":[
        "Enfeh"
    ],
    "name:fra_x_preferred":[
        "Anfeh"
    ],
    "name:ita_x_preferred":[
        "Anfeh"
    ],
    "name:nno_x_preferred":[
        "Enfeh"
    ],
    "name:spa_x_preferred":[
        "Enfeh"
    ],
    "name:und_x_variant":[
        "Infah",
        "Ennf\u00e9",
        "Enfeh",
        "Anfah",
        "Enf\u00e9"
    ],
    "wof:name":"Enfe",
    "wof:placetype":"locality"
},
  "geometry": {"coordinates":[35.73083,34.3575],"type":"Point"}
}