{
  "type": "Feature",
  "properties": {
    "gn:admin1_code":"10.0",
    "gn:asciiname":"Ain Faouar",
    "gn:country_code":"LB",
    "gn:dem":57,
    "gn:feature_class":"P",
    "gn:feature_code":"PPL",
    "gn:name":"A\u00efn Faou\u00e2r",
    "gn:population":0,
    "gn:timezone":"Asia/Beirut",
    "iso:country":"LB",
    "name:und_x_variant":[
        "\u2018Ayn al Faww\u0101r",
        "A\u00efn Faou\u00e2r"
    ],
    "wof:name":"Ain Faouar",
    "wof:placetype":"locality"
},
  "geometry": {"coordinates":[35.98333,34.50278],"type":"Point"}
}