{
  "type": "Feature",
  "properties": {
    "gn:admin1_code":"5.0",
    "gn:asciiname":"Fghal",
    "gn:country_code":"LB",
    "gn:dem":278,
    "gn:feature_class":"P",
    "gn:feature_code":"PPL",
    "gn:name":"Fgh\u00e2l",
    "gn:population":0,
    "gn:timezone":"Asia/Beirut",
    "iso:country":"LB",
    "name:und_x_variant":[
        "Farel",
        "Ferhal",
        "Fgh\u00e2l"
    ],
    "wof:name":"Fghal",
    "wof:placetype":"locality"
},
  "geometry": {"coordinates":[35.67778,34.20722],"type":"Point"}
}