{
  "type": "Feature",
  "properties": {
    "gn:admin1_code":"5.0",
    "gn:asciiname":"Ez Zalqa",
    "gn:country_code":"LB",
    "gn:dem":45,
    "gn:feature_class":"P",
    "gn:feature_code":"PPL",
    "gn:name":"Ez Zalqa",
    "gn:population":0,
    "gn:timezone":"Asia/Beirut",
    "iso:country":"LB",
    "name:ara_x_preferred":[
        "\u0627\u0644\u0632\u0644\u0642\u0627"
    ],
    "name:und_x_variant":[
        "Az Zalq\u0101\u2019",
        "Ez Zalqa",
        "Az Zalq\u0101"
    ],
    "wof:name":"Ez Zalqa",
    "wof:placetype":"locality"
},
  "geometry": {"coordinates":[35.57639,33.89611],"type":"Point"}
}