{
  "type": "Feature",
  "properties": {
    "gn:admin1_code":"7.0",
    "gn:asciiname":"Baitsaniye",
    "gn:country_code":"LB",
    "gn:dem":740,
    "gn:feature_class":"P",
    "gn:feature_code":"PPL",
    "gn:name":"Ba\u00eftsan\u00eey\u00e9",
    "gn:population":0,
    "gn:timezone":"Asia/Beirut",
    "iso:country":"LB",
    "name:ara_x_preferred":[
        "\u0628\u064a\u062b\u0646\u064a\u0629"
    ],
    "name:und_x_variant":[
        "Ba\u00eftsan\u00eey\u00e9",
        "Baythan\u012byah"
    ],
    "wof:name":"Baitsaniye",
    "wof:placetype":"locality"
},
  "geometry": {"coordinates":[35.71028,33.42111],"type":"Point"}
}