{
  "type": "Feature",
  "properties": {
    "gn:admin1_code":"6.0",
    "gn:asciiname":"Mazraat Qrouh",
    "gn:country_code":"LB",
    "gn:dem":733,
    "gn:feature_class":"P",
    "gn:feature_code":"PPL",
    "gn:name":"Mazraat Qrouh",
    "gn:population":0,
    "gn:timezone":"Asia/Beirut",
    "iso:country":"LB",
    "name:ara_x_preferred":[
        "\u0645\u0632\u0631\u0639\u0629 \u0642\u0631\u0648\u062d"
    ],
    "name:und_x_variant":[
        "Mazra\u2018at Qr\u016b\u1e29",
        "Mazraat Qrouh",
        "Mazra\u2018at Qur\u016b\u1e29"
    ],
    "wof:name":"Mazraat Qrouh",
    "wof:placetype":"locality"
},
  "geometry": {"coordinates":[35.57444,33.42667],"type":"Point"}
}