{
  "type": "Feature",
  "properties": {
    "gn:admin1_code":"9.0",
    "gn:asciiname":"Deir Nbouh",
    "gn:country_code":"LB",
    "gn:dem":277,
    "gn:feature_class":"P",
    "gn:feature_code":"PPL",
    "gn:name":"De\u00efr Nbo\u00fbh",
    "gn:population":0,
    "gn:timezone":"Asia/Beirut",
    "iso:country":"LB",
    "name:ara_x_preferred":[
        "\u062f\u064a\u0631 \u0646\u0628\u0648\u062d"
    ],
    "name:und_x_variant":[
        "Dayr Nb\u016b\u1e29",
        "De\u00efr Nbouch",
        "De\u00efr Nbo\u00fbh",
        "Dayr Nab\u016b\u1e29"
    ],
    "wof:name":"Deir Nbouh",
    "wof:placetype":"locality"
},
  "geometry": {"coordinates":[35.92944,34.37306],"type":"Point"}
}