{
  "type": "Feature",
  "properties": {
    "gn:admin1_code":"5.0",
    "gn:asciiname":"Chmis Aarnbaya",
    "gn:country_code":"LB",
    "gn:dem":921,
    "gn:feature_class":"P",
    "gn:feature_code":"PPL",
    "gn:name":"Chm\u00ees Aarnbaya",
    "gn:population":0,
    "gn:timezone":"Asia/Beirut",
    "iso:country":"LB",
    "name:und_x_variant":[
        "Sham\u012bs \u2018Arnbay\u0101",
        "Chm\u00ees Aarnbaya"
    ],
    "wof:name":"Chmis Aarnbaya",
    "wof:placetype":"locality"
},
  "geometry": {"coordinates":[35.71889,34.0275],"type":"Point"}
}