{
  "type": "Feature",
  "properties": {
    "gn:admin1_code":"9.0",
    "gn:asciiname":"El Aasbe",
    "gn:country_code":"LB",
    "gn:dem":1008,
    "gn:feature_class":"P",
    "gn:feature_code":"PPL",
    "gn:name":"El Aasb\u00e9",
    "gn:population":0,
    "gn:timezone":"Asia/Beirut",
    "iso:country":"LB",
    "name:und_x_variant":[
        "Al \u2018A\u015fbah",
        "El Aasb\u00e9"
    ],
    "wof:name":"El Aasbe",
    "wof:placetype":"locality"
},
  "geometry": {"coordinates":[35.78861,34.18722],"type":"Point"}
}