{
  "type": "Feature",
  "properties": {
    "gn:admin1_code":"5.0",
    "gn:asciiname":"El Mtain",
    "gn:country_code":"LB",
    "gn:dem":1072,
    "gn:feature_class":"P",
    "gn:feature_code":"PPL",
    "gn:name":"El Mta\u00efn",
    "gn:population":0,
    "gn:timezone":"Asia/Beirut",
    "iso:country":"LB",
    "name:ara_x_preferred":[
        "\u0627\u0644\u0645\u062a\u064a\u0646"
    ],
    "name:und_x_variant":[
        "El Mta\u00efne",
        "Al Mutayn",
        "El Mta\u00efn"
    ],
    "wof:name":"El Mtain",
    "wof:placetype":"locality"
},
  "geometry": {"coordinates":[35.74278,33.89194000000001],"type":"Point"}
}