{
  "type": "Feature",
  "properties": {
    "gn:admin1_code":"6.0",
    "gn:asciiname":"Qaaqaiet es Snaoubar",
    "gn:country_code":"LB",
    "gn:dem":225,
    "gn:feature_class":"P",
    "gn:feature_code":"PPL",
    "gn:name":"Qaaqa\u00efet es Snaoubar",
    "gn:population":0,
    "gn:timezone":"Asia/Beirut",
    "iso:country":"LB",
    "name:ara_x_preferred":[
        "\u0642\u0639\u0642\u0639\u064a\u0629 \u0627\u0644\u0635\u0646\u0648\u0628\u0631"
    ],
    "name:und_x_variant":[
        "Qa\u2018qa\u2018\u012byat a\u015f \u015eanawbar",
        "Qaaqa\u00efet es Snaoubar"
    ],
    "wof:name":"Qaaqaiet es Snaoubar",
    "wof:placetype":"locality"
},
  "geometry": {"coordinates":[35.34444000000001,33.43111],"type":"Point"}
}