{
  "type": "Feature",
  "properties": {
    "gn:admin1_code":"6.0",
    "gn:asciiname":"Ed Demachqiye",
    "gn:country_code":"LB",
    "gn:dem":440,
    "gn:feature_class":"P",
    "gn:feature_code":"PPL",
    "gn:name":"Ed Demachq\u00eey\u00e9",
    "gn:population":0,
    "gn:timezone":"Asia/Beirut",
    "iso:country":"LB",
    "name:ara_x_preferred":[
        "\u0627\u0644\u062f\u0645\u0634\u0642\u064a\u0629"
    ],
    "name:und_x_variant":[
        "Ad Dimashq\u012byah",
        "D\u00e9michk\u00eey\u00e9",
        "Dimishq\u012byih",
        "Ed-Dimashqiyah",
        "Demachqiye",
        "D\u00e9michqiy\u00e9",
        "Ed Demachq\u00eey\u00e9"
    ],
    "wof:name":"Ed Demachqiye",
    "wof:placetype":"locality"
},
  "geometry": {"coordinates":[35.54694,33.375],"type":"Point"}
}