{
  "type": "Feature",
  "properties": {
    "gn:admin1_code":"9.0",
    "gn:asciiname":"Mazraat es Slafni",
    "gn:country_code":"LB",
    "gn:dem":752,
    "gn:feature_class":"P",
    "gn:feature_code":"PPL",
    "gn:name":"Mazraat es Sl\u00e2fni",
    "gn:population":0,
    "gn:timezone":"Asia/Beirut",
    "iso:country":"LB",
    "name:und_x_variant":[
        "Mazra\u2018at as Sal\u0101fin\u012b",
        "Mazraat es Sl\u00e2fni"
    ],
    "wof:name":"Mazraat es Slafni",
    "wof:placetype":"locality"
},
  "geometry": {"coordinates":[35.80806,34.23611],"type":"Point"}
}