{
  "type": "Feature",
  "properties": {
    "gn:admin1_code":"9.0",
    "gn:asciiname":"Ain el Blat",
    "gn:country_code":"LB",
    "gn:dem":1430,
    "gn:feature_class":"P",
    "gn:feature_code":"PPL",
    "gn:name":"A\u00efn el Bl\u00e2t",
    "gn:population":0,
    "gn:timezone":"Asia/Beirut",
    "iso:country":"LB",
    "name:und_x_variant":[
        "\u2018Ayn al Bal\u0101\u0163",
        "A\u00efn el Bl\u00e2t"
    ],
    "wof:name":"Ain el Blat",
    "wof:placetype":"locality"
},
  "geometry": {"coordinates":[35.88583,34.18667],"type":"Point"}
}