{
  "type": "Feature",
  "properties": {
    "gn:admin1_code":"6.0",
    "gn:asciiname":"El Biyada",
    "gn:country_code":"LB",
    "gn:dem":130,
    "gn:feature_class":"P",
    "gn:feature_code":"PPL",
    "gn:name":"El B\u00efy\u00e2da",
    "gn:population":0,
    "gn:timezone":"Asia/Beirut",
    "iso:country":"LB",
    "name:ara_x_preferred":[
        "\u0645\u0632\u0631\u0639\u0629 \u0627\u0644\u0628\u064a\u0627\u0636\u0629"
    ],
    "name:ara_x_variant":[
        "\u0627\u0644\u0628\u064a\u0651\u0627\u0636\u0629"
    ],
    "name:und_x_variant":[
        "Al Bayy\u0101\u1e11ah",
        "El B\u00efy\u00e2da",
        "Mazra\u2018at al Bayy\u0101\u1e11ah"
    ],
    "wof:name":"El Biyada",
    "wof:placetype":"locality"
},
  "geometry": {"coordinates":[35.18167,33.16278],"type":"Point"}
}