{
  "type": "Feature",
  "properties": {
    "gn:admin1_code":"7.0",
    "gn:asciiname":"Bayadat",
    "gn:country_code":"LB",
    "gn:dem":696,
    "gn:feature_class":"P",
    "gn:feature_code":"PPL",
    "gn:name":"Bayad\u00e2t",
    "gn:population":0,
    "gn:timezone":"Asia/Beirut",
    "iso:country":"LB",
    "name:ara_x_preferred":[
        "\u0628\u064a\u0627\u0636\u0627\u062a"
    ],
    "name:und_x_variant":[
        "Bayad\u00e2t",
        "Bayy\u0101\u1e11\u0101t"
    ],
    "wof:name":"Bayadat",
    "wof:placetype":"locality"
},
  "geometry": {"coordinates":[35.40361,33.17055999999999],"type":"Point"}
}