{
  "type": "Feature",
  "properties": {
    "gn:admin1_code":"5.0",
    "gn:asciiname":"Daraaoun",
    "gn:country_code":"LB",
    "gn:dem":564,
    "gn:feature_class":"P",
    "gn:feature_code":"PPL",
    "gn:name":"Daraao\u00fbn",
    "gn:population":0,
    "gn:timezone":"Asia/Beirut",
    "iso:country":"LB",
    "name:und_x_variant":[
        "Darao\u00fbn",
        "Dar\u2018awn",
        "Daraon",
        "Dar\u2018\u016bn",
        "Daraao\u00fbn"
    ],
    "wof:name":"Daraaoun",
    "wof:placetype":"locality"
},
  "geometry": {"coordinates":[35.65861,33.97722],"type":"Point"}
}