{
  "type": "Feature",
  "properties": {
    "gn:admin1_code":"8.0",
    "gn:asciiname":"Chtaura",
    "gn:country_code":"LB",
    "gn:dem":910,
    "gn:feature_class":"P",
    "gn:feature_code":"PPL",
    "gn:name":"Chtaura",
    "gn:population":0,
    "gn:timezone":"Asia/Beirut",
    "iso:country":"LB",
    "name:ara_x_preferred":[
        "\u0634\u062a\u0648\u0631\u0629"
    ],
    "name:und_x_variant":[
        "Shtawrah",
        "Chtaura",
        "Sht\u016brah"
    ],
    "wof:name":"Chtaura",
    "wof:placetype":"locality"
},
  "geometry": {"coordinates":[35.85139,33.81667],"type":"Point"}
}