{
  "type": "Feature",
  "properties": {
    "gn:admin1_code":"8.0",
    "gn:asciiname":"Chtaura",
    "gn:country_code":"LB",
    "gn:dem":910,
    "gn:feature_class":"P",
    "gn:feature_code":"PPL",
    "gn:name":"Chtaura",
    "gn:population":0,
    "gn:timezone":"Asia/Beirut",
    "iso:country":"LB",
    "name:ara_x_preferred":[
        "\u0634\u062a\u0648\u0631\u0629"
    ],
    "name:ara_x_variant":[
        "\u0634\u062a\u0648\u0631\u0627"
    ],
    "name:ceb_x_preferred":[
        "Chtaura"
    ],
    "name:deu_x_preferred":[
        "Chtoura"
    ],
    "name:fra_x_preferred":[
        "Chtaura"
    ],
    "name:heb_x_preferred":[
        "\u05e9\u05ea\u05d5\u05e8\u05d0"
    ],
    "name:ita_x_preferred":[
        "Chtaura"
    ],
    "name:nno_x_preferred":[
        "Chtaura"
    ],
    "name:swe_x_preferred":[
        "Chtaura"
    ],
    "name:und_x_variant":[
        "Shtawrah",
        "Sht\u016brah"
    ],
    "wof:name":"Chtaura",
    "wof:placetype":"locality"
},
  "geometry": {"coordinates":[35.85139,33.81667],"type":"Point"}
}