{
  "type": "Feature",
  "properties": {
    "iso:country":"LB",
    "qs:gn_pop":0,
    "qs:name":"\u0627\u0644\u0628\u0627\u0631\u0648\u0643",
    "qs:name_adm0":"\u0644\u0628\u0646\u0627\u0646",
    "qs:name_adm1":"\u062c\u0628\u0644 \u0644\u0628\u0646\u0627\u0646",
    "qs:photos":81,
    "qs:photos_1k":16,
    "qs:photos_9k":1,
    "qs:photos_9r":3,
    "qs:photos_all":81,
    "qs:photos_sr":3,
    "qs:placetype":"Town",
    "qs:pop_sr":"0",
    "qs:woe_adm0":23424873,
    "wof:name":"\u0627\u0644\u0628\u0627\u0631\u0648\u0643",
    "wof:placetype":"locality"
},
  "geometry": {"coordinates":[35.681388,33.692495],"type":"Point"}
}