{
  "type": "Feature",
  "properties": {
    "gn:admin1_code":"11.0",
    "gn:asciiname":"Mrah el Hariqa",
    "gn:country_code":"LB",
    "gn:dem":1213,
    "gn:feature_class":"P",
    "gn:feature_code":"PPL",
    "gn:name":"Mr\u00e2h el Har\u00eeqa",
    "gn:population":0,
    "gn:timezone":"Asia/Beirut",
    "iso:country":"LB",
    "name:und_x_variant":[
        "Mar\u0101\u1e29 al \u1e28ar\u012bqah",
        "Mr\u00e2h el Har\u00eeqa"
    ],
    "wof:name":"Mrah el Hariqa",
    "wof:placetype":"locality"
},
  "geometry": {"coordinates":[36.33833,34.3975],"type":"Point"}
}