{
  "type": "Feature",
  "properties": {
    "gn:admin1_code":"8.0",
    "gn:asciiname":"Aana",
    "gn:country_code":"LB",
    "gn:dem":982,
    "gn:feature_class":"P",
    "gn:feature_code":"PPL",
    "gn:name":"A\u00e2na",
    "gn:population":0,
    "gn:timezone":"Asia/Beirut",
    "iso:country":"LB",
    "name:ara_x_preferred":[
        "\u0639\u0627\u0646\u0627"
    ],
    "name:und_x_variant":[
        "\u2018\u0100n\u0101",
        "A\u00e2na"
    ],
    "wof:name":"Aana",
    "wof:placetype":"locality"
},
  "geometry": {"coordinates":[35.7525,33.69278],"type":"Point"}
}