{
  "type": "Feature",
  "properties": {
    "gn:admin1_code":"11.0",
    "gn:asciiname":"Ouadi Bnit",
    "gn:country_code":"LB",
    "gn:dem":1163,
    "gn:feature_class":"P",
    "gn:feature_code":"PPL",
    "gn:name":"Ou\u00e2di Bn\u00eet",
    "gn:population":0,
    "gn:timezone":"Asia/Beirut",
    "iso:country":"LB",
    "name:und_x_variant":[
        "Daoura",
        "W\u0101d\u012b Bunayt",
        "Ou\u00e2di Bn\u00eet"
    ],
    "wof:name":"Ouadi Bnit",
    "wof:placetype":"locality"
},
  "geometry": {"coordinates":[36.31639000000001,34.32917],"type":"Point"}
}