{
  "type": "Feature",
  "properties": {
    "gn:admin1_code":"5.0",
    "gn:asciiname":"Klilaiye",
    "gn:country_code":"LB",
    "gn:dem":334,
    "gn:feature_class":"P",
    "gn:feature_code":"PPL",
    "gn:name":"Kl\u00eela\u00efy\u00e9",
    "gn:population":0,
    "gn:timezone":"Asia/Beirut",
    "iso:country":"LB",
    "name:ara_x_preferred":[
        "\u0643\u0644\u064a\u0644\u064a"
    ],
    "name:und_x_variant":[
        "Kl\u012blay",
        "Kl\u00eela\u00efy\u00e9"
    ],
    "wof:name":"Klilaiye",
    "wof:placetype":"locality"
},
  "geometry": {"coordinates":[35.50806,33.70972],"type":"Point"}
}