{
  "type": "Feature",
  "properties": {
    "gn:admin1_code":"7.0",
    "gn:asciiname":"Froun",
    "gn:country_code":"LB",
    "gn:dem":419,
    "gn:feature_class":"P",
    "gn:feature_code":"PPL",
    "gn:name":"Fro\u00fbn",
    "gn:population":0,
    "gn:timezone":"Asia/Beirut",
    "iso:country":"LB",
    "name:ara_x_preferred":[
        "\u0641\u0631\u0648\u0646"
    ],
    "name:ara_x_variant":[
        "Fur\u016bn"
    ],
    "name:ita_x_preferred":[
        "Froun"
    ],
    "name:und_x_variant":[
        "Fr\u016bn",
        "Fro\u00fbn"
    ],
    "wof:name":"Froun",
    "wof:placetype":"locality"
},
  "geometry": {"coordinates":[35.42866,33.29539],"type":"Point"}
}