{
  "type": "Feature",
  "properties": {
    "gn:admin1_code":"5.0",
    "gn:asciiname":"Ech Chmaissat",
    "gn:country_code":"LB",
    "gn:dem":1002,
    "gn:feature_class":"P",
    "gn:feature_code":"PPL",
    "gn:name":"Ech Chma\u00efss\u00e2t",
    "gn:population":0,
    "gn:timezone":"Asia/Beirut",
    "iso:country":"LB",
    "name:und_x_variant":[
        "Ash Shumays\u0101t",
        "Ech Chma\u00efss\u00e2t"
    ],
    "wof:name":"Ech Chmaissat",
    "wof:placetype":"locality"
},
  "geometry": {"coordinates":[35.7775,34.16917],"type":"Point"}
}