{
  "type": "Feature",
  "properties": {
    "gn:admin1_code":"5.0",
    "gn:asciiname":"Mazraat ed Dahr",
    "gn:country_code":"LB",
    "gn:dem":648,
    "gn:feature_class":"P",
    "gn:feature_code":"PPL",
    "gn:name":"Mazraat ed Dahr",
    "gn:population":0,
    "gn:timezone":"Asia/Beirut",
    "iso:country":"LB",
    "name:ara_x_preferred":[
        "\u0645\u0632\u0631\u0639\u0629 \u0627\u0644\u0636\u0647\u0631"
    ],
    "name:glg_x_preferred":[
        "Masrat-al-Dahr"
    ],
    "name:ita_x_preferred":[
        "Mazraat el Daher"
    ],
    "name:und_x_variant":[
        "Mazra\u2018at a\u1e11 \u1e10ahr",
        "Mazraat ed Dahr"
    ],
    "wof:name":"Mazraat ed Dahr",
    "wof:placetype":"locality"
},
  "geometry": {"coordinates":[35.51528,33.59583],"type":"Point"}
}