{
  "type": "Feature",
  "properties": {
    "gn:admin1_code":"5.0",
    "gn:asciiname":"Harat Hamzah",
    "gn:cc2":"LB",
    "gn:country_code":"LB",
    "gn:dem":605,
    "gn:feature_class":"P",
    "gn:feature_code":"PPL",
    "gn:name":"\u1e28\u0101rat \u1e28amzah",
    "gn:population":0,
    "gn:timezone":"Asia/Beirut",
    "iso:country":"LB",
    "name:und_x_variant":[
        "H\u00e2ret Hamz\u00e9",
        "\u1e28\u0101rat \u1e28amzah"
    ],
    "wof:name":"Harat Hamzah",
    "wof:placetype":"locality"
},
  "geometry": {"coordinates":[35.65,33.75],"type":"Point"}
}