{
  "type": "Feature",
  "properties": {
    "gn:admin1_code":"7.0",
    "gn:asciiname":"El Meri",
    "gn:country_code":"LB",
    "gn:dem":444,
    "gn:feature_class":"P",
    "gn:feature_code":"PPL",
    "gn:name":"El Meri",
    "gn:population":0,
    "gn:timezone":"Asia/Beirut",
    "iso:country":"LB",
    "name:ara_x_preferred":[
        "\u0627\u0644\u0648\u0631\u064a"
    ],
    "name:und_x_variant":[
        "Al M\u0101r\u012b",
        "El-Mari",
        "El Meri",
        "Al Mar\u012b"
    ],
    "wof:name":"El Meri",
    "wof:placetype":"locality"
},
  "geometry": {"coordinates":[35.64226,33.32041],"type":"Point"}
}