{
  "type": "Feature",
  "properties": {
    "gn:admin1_code":"8.0",
    "gn:asciiname":"El Mhaidthe",
    "gn:country_code":"LB",
    "gn:dem":1154,
    "gn:feature_class":"P",
    "gn:feature_code":"PPL",
    "gn:name":"El Mha\u00efdth\u00e9",
    "gn:population":0,
    "gn:timezone":"Asia/Beirut",
    "iso:country":"LB",
    "name:ara_x_preferred":[
        "\u0627\u0644\u0645\u062d\u064a\u062f\u062b\u0629"
    ],
    "name:und_x_variant":[
        "Al Mu\u1e29aytah",
        "El Mouha\u00eft\u00e9",
        "Al Mu\u1e29aydithah",
        "El Mha\u00efdth\u00e9"
    ],
    "wof:name":"El Mhaidthe",
    "wof:placetype":"locality"
},
  "geometry": {"coordinates":[35.81167,33.55694],"type":"Point"}
}