{
  "type": "Feature",
  "properties": {
    "gn:admin1_code":"10.0",
    "gn:asciiname":"El Majdal",
    "gn:country_code":"LB",
    "gn:dem":397,
    "gn:feature_class":"P",
    "gn:feature_code":"PPL",
    "gn:name":"El Majdal",
    "gn:population":0,
    "gn:timezone":"Asia/Beirut",
    "iso:country":"LB",
    "wof:name":"El Majdal",
    "wof:placetype":"locality"
},
  "geometry": {"coordinates":[36.39556,34.62917],"type":"Point"}
}