{
  "type": "Feature",
  "properties": {
    "gn:admin1_code":"5.0",
    "gn:asciiname":"Jouar",
    "gn:country_code":"LB",
    "gn:dem":644,
    "gn:feature_class":"P",
    "gn:feature_code":"PPL",
    "gn:name":"Jouar",
    "gn:population":0,
    "gn:timezone":"Asia/Beirut",
    "iso:country":"LB",
    "name:fra_x_preferred":[
        "Jouar"
    ],
    "name:nno_x_preferred":[
        "Jouar"
    ],
    "wof:name":"Jouar",
    "wof:placetype":"locality"
},
  "geometry": {"coordinates":[35.58472000000001,33.80333],"type":"Point"}
}