{
  "type": "Feature",
  "properties": {
    "gn:admin1_code":"8.0",
    "gn:asciiname":"Ma`zar",
    "gn:country_code":"LB",
    "gn:dem":1581,
    "gn:feature_class":"P",
    "gn:feature_code":"PPL",
    "gn:name":"Ma\u2018z\u0101r",
    "gn:population":0,
    "gn:timezone":"Asia/Beirut",
    "iso:country":"LB",
    "wof:name":"Ma`zar",
    "wof:placetype":"locality"
},
  "geometry": {"coordinates":[35.96667,33.58333],"type":"Point"}
}