{
  "type": "Feature",
  "properties": {
    "gn:admin1_code":"8.0",
    "gn:asciiname":"Ez Zaaroura",
    "gn:country_code":"LB",
    "gn:dem":898,
    "gn:feature_class":"P",
    "gn:feature_code":"PPL",
    "gn:name":"Ez Zaaro\u00fbra",
    "gn:population":0,
    "gn:timezone":"Asia/Beirut",
    "iso:country":"LB",
    "name:ara_x_preferred":[
        "\u0627\u0644\u0632\u0639\u0631\u0648\u0631\u0629"
    ],
    "name:und_x_variant":[
        "Az Zu\u2018r\u016brah",
        "Ez Zaaro\u00fbra",
        "Az Za\u2018r\u016brah"
    ],
    "wof:name":"Ez Zaaroura",
    "wof:placetype":"locality"
},
  "geometry": {"coordinates":[35.87083,33.8125],"type":"Point"}
}