{
  "type": "Feature",
  "properties": {
    "iso:country":"LB",
    "qs:gn_pop":0,
    "qs:name":"\u0627\u0644\u0627\u0634\u0631\u0641\u064a\u0629",
    "qs:name_adm0":"\u0644\u0628\u0646\u0627\u0646",
    "qs:name_adm1":"\u0628\u064a\u0631\u0648\u062a",
    "qs:photos":88,
    "qs:photos_1k":18,
    "qs:photos_9k":1,
    "qs:photos_9r":3,
    "qs:photos_all":88,
    "qs:photos_sr":3,
    "qs:placetype":"Suburb",
    "qs:pop_sr":"0",
    "qs:woe_adm0":23424873,
    "wof:name":"\u0627\u0644\u0627\u0634\u0631\u0641\u064a\u0629",
    "wof:placetype":"neighbourhood"
},
  "geometry": {"coordinates":[35.516979,33.886001],"type":"Point"}
}