{
  "type": "Feature",
  "properties": {
    "gn:admin1_code":"7.0",
    "gn:asciiname":"Markaba",
    "gn:country_code":"LB",
    "gn:dem":718,
    "gn:feature_class":"P",
    "gn:feature_code":"PPL",
    "gn:name":"Markaba",
    "gn:population":0,
    "gn:timezone":"Asia/Beirut",
    "iso:country":"LB",
    "name:ara_x_preferred":[
        "\u0645\u0631\u0643\u0628\u0627"
    ],
    "name:und_x_variant":[
        "Markab\u0101",
        "Markaba"
    ],
    "wof:name":"Markaba",
    "wof:placetype":"locality"
},
  "geometry": {"coordinates":[35.51306,33.23333],"type":"Point"}
}