{
  "type": "Feature",
  "properties": {
    "gn:admin1_code":"5.0",
    "gn:asciiname":"Tarouaa el Qattine",
    "gn:country_code":"LB",
    "gn:dem":777,
    "gn:feature_class":"P",
    "gn:feature_code":"PPL",
    "gn:name":"T\u00e2ro\u00fbaa el Qatt\u00eene",
    "gn:population":0,
    "gn:timezone":"Asia/Beirut",
    "iso:country":"LB",
    "name:und_x_variant":[
        "T\u0101r\u016b\u2018 al Qa\u0163\u0163\u012bn",
        "T\u00e2ro\u00fbaa el Qatt\u00eene"
    ],
    "wof:name":"Tarouaa el Qattine",
    "wof:placetype":"locality"
},
  "geometry": {"coordinates":[35.79167,34.08833],"type":"Point"}
}