{
  "type": "Feature",
  "properties": {
    "gn:admin1_code":"8.0",
    "gn:asciiname":"Makse",
    "gn:country_code":"LB",
    "gn:dem":952,
    "gn:feature_class":"P",
    "gn:feature_code":"PPL",
    "gn:name":"Maks\u00e9",
    "gn:population":0,
    "gn:timezone":"Asia/Beirut",
    "iso:country":"LB",
    "name:ara_x_preferred":[
        "\u0645\u0643\u0633\u0629"
    ],
    "name:und_x_variant":[
        "Maksah",
        "Maks\u00e9"
    ],
    "wof:name":"Makse",
    "wof:placetype":"locality"
},
  "geometry": {"coordinates":[35.83222,33.81056],"type":"Point"}
}