{
  "type": "Feature",
  "properties": {
    "gn:admin1_code":"10.0",
    "gn:asciiname":"Michmich",
    "gn:country_code":"LB",
    "gn:dem":1062,
    "gn:feature_class":"P",
    "gn:feature_code":"PPL",
    "gn:name":"Michmich",
    "gn:population":0,
    "gn:timezone":"Asia/Beirut",
    "iso:country":"LB",
    "name:ara_x_preferred":[
        "\u0645\u0634\u0645\u0634"
    ],
    "name:ita_x_preferred":[
        "Mechmech"
    ],
    "name:nno_x_preferred":[
        "Mish Mish"
    ],
    "name:und_x_variant":[
        "Mishmish",
        "Michmich"
    ],
    "wof:name":"Michmich",
    "wof:placetype":"locality"
},
  "geometry": {"coordinates":[36.17056,34.47222],"type":"Point"}
}