{
  "type": "Feature",
  "properties": {
    "gn:admin1_code":"7.0",
    "gn:asciiname":"Mazraat Ras el Baidar",
    "gn:country_code":"LB",
    "gn:dem":559,
    "gn:feature_class":"P",
    "gn:feature_code":"PPL",
    "gn:name":"Mazraat R\u00e2s el Ba\u00efdar",
    "gn:population":0,
    "gn:timezone":"Asia/Beirut",
    "iso:country":"LB",
    "name:ara_x_preferred":[
        "\u0645\u0632\u0631\u0639\u0629 \u0631\u0623\u0633 \u0627\u0644\u0628\u064a\u062f\u0631"
    ],
    "name:und_x_variant":[
        "Mazra\u2018at Ra\u2019s al Baydar",
        "Mazraat R\u00e2s el Ba\u00efdar"
    ],
    "wof:name":"Mazraat Ras el Baidar",
    "wof:placetype":"locality"
},
  "geometry": {"coordinates":[35.6681,33.40235999999999],"type":"Point"}
}