{
  "type": "Feature",
  "properties": {
    "gn:admin1_code":"8.0",
    "gn:asciiname":"Hai ej Jamia",
    "gn:country_code":"LB",
    "gn:dem":916,
    "gn:feature_class":"P",
    "gn:feature_code":"PPL",
    "gn:name":"Ha\u00ef ej J\u00e2mia",
    "gn:population":0,
    "gn:timezone":"Asia/Beirut",
    "iso:country":"LB",
    "name:ara_x_preferred":[
        "\u062d\u064a \u0627\u0644\u062c\u0627\u0645\u0639"
    ],
    "name:und_x_variant":[
        "\u1e28ayy al J\u0101mi\u2018",
        "Ha\u00ef ej J\u00e2mia"
    ],
    "wof:name":"Hai ej Jamia",
    "wof:placetype":"locality"
},
  "geometry": {"coordinates":[35.87167,33.81944],"type":"Point"}
}