{
  "type": "Feature",
  "properties": {
    "gn:admin1_code":"9.0",
    "gn:asciiname":"El Maqtouaa",
    "gn:country_code":"LB",
    "gn:dem":1108,
    "gn:feature_class":"P",
    "gn:feature_code":"PPL",
    "gn:name":"El Maqto\u00fbaa",
    "gn:population":0,
    "gn:timezone":"Asia/Beirut",
    "iso:country":"LB",
    "name:und_x_variant":[
        "Al Maq\u0163\u016b\u2018ah",
        "El Maqto\u00fbaa"
    ],
    "wof:name":"El Maqtouaa",
    "wof:placetype":"locality"
},
  "geometry": {"coordinates":[36.06111,34.40694000000001],"type":"Point"}
}