{
  "type": "Feature",
  "properties": {
    "gn:admin1_code":"5.0",
    "gn:asciiname":"Souq el Gharb",
    "gn:country_code":"LB",
    "gn:dem":746,
    "gn:feature_class":"P",
    "gn:feature_code":"PPL",
    "gn:name":"Souq el Gharb",
    "gn:population":0,
    "gn:timezone":"Asia/Beirut",
    "iso:country":"LB",
    "name:ara_x_preferred":[
        "\u0633\u0648\u0642 \u0627\u0644\u063a\u0631\u0628"
    ],
    "name:und_x_variant":[
        "S\u016bq al Gharb",
        "Souq el Gharb"
    ],
    "wof:name":"Souq el Gharb",
    "wof:placetype":"locality"
},
  "geometry": {"coordinates":[35.56556,33.79389],"type":"Point"}
}