{
  "type": "Feature",
  "properties": {
    "gn:admin1_code":"5.0",
    "gn:asciiname":"Maasser ech Chouf",
    "gn:country_code":"LB",
    "gn:dem":1165,
    "gn:feature_class":"P",
    "gn:feature_code":"PPL",
    "gn:name":"M\u0101\u00e2sser ech Cho\u00fbf",
    "gn:population":0,
    "gn:timezone":"Asia/Beirut",
    "iso:country":"LB",
    "name:ara_x_preferred":[
        "\u0645\u0639\u0627\u0635\u0631 \u0627\u0644\u0634\u0648\u0641"
    ],
    "name:und_x_variant":[
        "Ma\u2018\u0101\u015fir ash Sh\u016bf",
        "M\u0101\u00e2sser ech Cho\u00fbf"
    ],
    "wof:name":"Maasser ech Chouf",
    "wof:placetype":"locality"
},
  "geometry": {"coordinates":[35.67139,33.66611],"type":"Point"}
}