{
  "type": "Feature",
  "properties": {
    "gn:admin1_code":"11.0",
    "gn:asciiname":"Mrah el Mechmechi",
    "gn:country_code":"LB",
    "gn:dem":1248,
    "gn:feature_class":"P",
    "gn:feature_code":"PPL",
    "gn:name":"Mr\u00e2h el Mechmechi",
    "gn:population":0,
    "gn:timezone":"Asia/Beirut",
    "iso:country":"LB",
    "name:und_x_variant":[
        "Mar\u0101\u1e29 al Mishmish\u012b",
        "Mr\u00e2h el Mechmechi"
    ],
    "wof:name":"Mrah el Mechmechi",
    "wof:placetype":"locality"
},
  "geometry": {"coordinates":[36.19583,34.16167],"type":"Point"}
}