{
  "type": "Feature",
  "properties": {
    "gn:admin1_code":"5.0",
    "gn:asciiname":"El Aazra",
    "gn:country_code":"LB",
    "gn:dem":723,
    "gn:feature_class":"P",
    "gn:feature_code":"PPL",
    "gn:name":"El Aazra",
    "gn:population":0,
    "gn:timezone":"Asia/Beirut",
    "iso:country":"LB",
    "name:ara_x_preferred":[
        "\u0627\u0644\u0639\u0630\u0631\u0629"
    ],
    "name:ara_x_variant":[
        "\u0627\u0644\u0639\u0630\u0631\u0629 \u0648 \u0627\u0644\u0639\u0630\u0631"
    ],
    "name:und_x_variant":[
        "El-\u2018Adhrah",
        "El Aadra",
        "El-Azrah",
        "Al \u2018Adhr\u0101\u2019",
        "El Aazra",
        "Al \u2018Udhrah wa al \u2018Udhr",
        "Al \u2018Adhrah"
    ],
    "wof:name":"El Aazra",
    "wof:placetype":"locality"
},
  "geometry": {"coordinates":[35.69631,34.06355],"type":"Point"}
}