{
  "type": "Feature",
  "properties": {
    "gn:admin1_code":"5.0",
    "gn:asciiname":"Er Roummane",
    "gn:country_code":"LB",
    "gn:dem":377,
    "gn:feature_class":"P",
    "gn:feature_code":"PPL",
    "gn:name":"Er Roumm\u00e2n\u00e9",
    "gn:population":0,
    "gn:timezone":"Asia/Beirut",
    "iso:country":"LB",
    "name:ara_x_preferred":[
        "\u0627\u0644\u0631\u0645\u0627\u0646\u0629"
    ],
    "name:ara_x_variant":[
        "\u0627\u0644\u0631\u0645\u0651\u0627\u0646\u0629"
    ],
    "name:und_x_variant":[
        "Er Rouman\u00e9",
        "Ar Rumm\u0101nah",
        "Er Roumm\u00e2n\u00e9"
    ],
    "wof:name":"Er Roummane",
    "wof:placetype":"locality"
},
  "geometry": {"coordinates":[35.48657,33.71925],"type":"Point"}
}