{
  "type": "Feature",
  "properties": {
    "gn:admin1_code":"9.0",
    "gn:asciiname":"Aarkaba",
    "gn:country_code":"LB",
    "gn:dem":152,
    "gn:feature_class":"P",
    "gn:feature_code":"PPL",
    "gn:name":"Aarkaba",
    "gn:population":0,
    "gn:timezone":"Asia/Beirut",
    "iso:country":"LB",
    "name:ara_x_preferred":[
        "\u0639\u0631\u0643\u0628\u0629"
    ],
    "name:und_x_variant":[
        "\u2018Arkabah"
    ],
    "wof:name":"Aarkaba",
    "wof:placetype":"locality"
},
  "geometry": {"coordinates":[35.64397,34.18399],"type":"Point"}
}