{
  "type": "Feature",
  "properties": {
    "gn:admin1_code":"5.0",
    "gn:asciiname":"Bkourkoz",
    "gn:country_code":"LB",
    "gn:dem":788,
    "gn:feature_class":"P",
    "gn:feature_code":"PPL",
    "gn:name":"Bkourkoz",
    "gn:population":0,
    "gn:timezone":"Asia/Beirut",
    "iso:country":"LB",
    "name:ara_x_preferred":[
        "\u0628\u0643\u0631\u0643\u0632"
    ],
    "name:ara_x_variant":[
        "\u0643\u0631\u0643\u0632"
    ],
    "name:und_x_variant":[
        "Bkirkoz",
        "Bkourkouz",
        "Bkirkuz",
        "Bkourkoz",
        "Kirkuz",
        "Bikirkuz"
    ],
    "wof:name":"Bkourkoz",
    "wof:placetype":"locality"
},
  "geometry": {"coordinates":[35.73028,34.10433],"type":"Point"}
}