{
  "type": "Feature",
  "properties": {
    "gn:admin1_code":"5.0",
    "gn:asciiname":"El Braij",
    "gn:country_code":"LB",
    "gn:dem":694,
    "gn:feature_class":"P",
    "gn:feature_code":"PPL",
    "gn:name":"El Bra\u00efj",
    "gn:population":0,
    "gn:timezone":"Asia/Beirut",
    "iso:country":"LB",
    "name:ara_x_preferred":[
        "\u0627\u0644\u0628\u0631\u064a\u062c"
    ],
    "name:und_x_variant":[
        "Al Burayj",
        "El Bra\u00efj"
    ],
    "wof:name":"El Braij",
    "wof:placetype":"locality"
},
  "geometry": {"coordinates":[35.70361,34.11944],"type":"Point"}
}