{
  "type": "Feature",
  "properties": {
    "gn:admin1_code":"7.0",
    "gn:asciiname":"Hanine",
    "gn:country_code":"LB",
    "gn:dem":664,
    "gn:feature_class":"P",
    "gn:feature_code":"PPL",
    "gn:name":"Han\u00efne",
    "gn:population":0,
    "gn:timezone":"Asia/Beirut",
    "iso:country":"LB",
    "name:ara_x_preferred":[
        "\u062d\u0627\u0646\u064a\u0646"
    ],
    "name:ita_x_preferred":[
        "Hanine"
    ],
    "name:und_x_variant":[
        "Haneen",
        "\u1e28\u0101n\u012bn",
        "Han\u00efne"
    ],
    "wof:name":"Hanine",
    "wof:placetype":"locality"
},
  "geometry": {"coordinates":[35.38111,33.10972],"type":"Point"}
}