{
  "type": "Feature",
  "properties": {
    "gn:admin1_code":"5.0",
    "gn:asciiname":"Ed Dekouane",
    "gn:country_code":"LB",
    "gn:dem":33,
    "gn:feature_class":"P",
    "gn:feature_code":"PPL",
    "gn:name":"Ed Dekouan\u00e9",
    "gn:population":0,
    "gn:timezone":"Asia/Beirut",
    "iso:country":"LB",
    "name:ara_x_preferred":[
        "\u0627\u0644\u062f\u0643\u0648\u0627\u0646\u0629"
    ],
    "name:und_x_variant":[
        "Ad Dikw\u0101n\u012b",
        "Ad Dikw\u0101nih",
        "Ad Dikw\u0101nah",
        "Ed Dekouan\u00e9"
    ],
    "wof:name":"Ed Dekouane",
    "wof:placetype":"locality"
},
  "geometry": {"coordinates":[35.55083,33.87806],"type":"Point"}
}