{
  "type": "Feature",
  "properties": {
    "gn:admin1_code":"7.0",
    "gn:asciiname":"Marjayoun",
    "gn:country_code":"LB",
    "gn:dem":731,
    "gn:feature_class":"P",
    "gn:feature_code":"PPLA2",
    "gn:name":"Marjayo\u00fbn",
    "gn:population":0,
    "gn:timezone":"Asia/Beirut",
    "iso:country":"LB",
    "name:ara_x_preferred":[
        "\u0645\u0631\u062c\u0639\u064a\u0648\u0646"
    ],
    "name:und_x_variant":[
        "Djedeideh",
        "El Judeide",
        "Marji\u2018y\u016bn",
        "Marjayo\u00fbn",
        "Marjaayoun"
    ],
    "wof:name":"Marjayoun",
    "wof:placetype":"locality"
},
  "geometry": {"coordinates":[35.59111,33.36028],"type":"Point"}
}