{
  "type": "Feature",
  "properties": {
    "gn:admin1_code":"8.0",
    "gn:asciiname":"Qamar ed Dine",
    "gn:country_code":"LB",
    "gn:dem":1161,
    "gn:feature_class":"P",
    "gn:feature_code":"PPL",
    "gn:name":"Qamar ed D\u00eene",
    "gn:population":0,
    "gn:timezone":"Asia/Beirut",
    "iso:country":"LB",
    "wof:name":"Qamar ed Dine",
    "wof:placetype":"locality"
},
  "geometry": {"coordinates":[35.90278,33.85694],"type":"Point"}
}