{
  "type": "Feature",
  "properties": {
    "gn:admin1_code":"10.0",
    "gn:asciiname":"Bqerzla",
    "gn:country_code":"LB",
    "gn:dem":260,
    "gn:feature_class":"P",
    "gn:feature_code":"PPL",
    "gn:name":"Bqerzl\u00e2",
    "gn:population":0,
    "gn:timezone":"Asia/Beirut",
    "iso:country":"LB",
    "name:und_x_variant":[
        "Bkerzala",
        "Bqirzla",
        "Bqarzl\u0101",
        "Bqerzl\u00e2"
    ],
    "wof:name":"Bqerzla",
    "wof:placetype":"locality"
},
  "geometry": {"coordinates":[36.05556,34.51167],"type":"Point"}
}