{
  "type": "Feature",
  "properties": {
    "gn:admin1_code":"9.0",
    "gn:asciiname":"Kfar Hilda",
    "gn:country_code":"LB",
    "gn:dem":621,
    "gn:feature_class":"P",
    "gn:feature_code":"PPL",
    "gn:name":"Kfar Hilda",
    "gn:population":0,
    "gn:timezone":"Asia/Beirut",
    "iso:country":"LB",
    "name:ara_x_preferred":[
        "\u0643\u0641\u0631 \u062d\u0644\u062f\u0627"
    ],
    "name:ara_x_variant":[
        "\u0643\u0641\u0631 \u062d\u0644\u062f\u0629"
    ],
    "name:und_x_variant":[
        "Be\u00eft Ch\u00e9la",
        "Bayt Shil\u0101l\u0101",
        "Be\u00eft Chel\u00e2la",
        "Beit Chl\u00e9la",
        "Beit Chl\u00e9l\u00e9",
        "Kafr \u1e28ild\u0101",
        "Kfar Hilda",
        "Kafr \u1e28ildah"
    ],
    "wof:name":"Kfar Hilda",
    "wof:placetype":"locality"
},
  "geometry": {"coordinates":[35.84056,34.22528],"type":"Point"}
}