{
  "type": "Feature",
  "properties": {
    "gn:admin1_code":"5.0",
    "gn:asciiname":"Ghbaline",
    "gn:country_code":"LB",
    "gn:dem":366,
    "gn:feature_class":"P",
    "gn:feature_code":"PPL",
    "gn:name":"Ghb\u00e2l\u00eene",
    "gn:population":0,
    "gn:timezone":"Asia/Beirut",
    "iso:country":"LB",
    "name:und_x_variant":[
        "Ghbaleen",
        "Ghb\u0101l\u012bn",
        "Ghb\u00e2l\u00eene"
    ],
    "wof:name":"Ghbaline",
    "wof:placetype":"locality"
},
  "geometry": {"coordinates":[35.69361,34.18417],"type":"Point"}
}