{
  "type": "Feature",
  "properties": {
    "iso:country":"LB",
    "qs:gn_pop":0,
    "qs:name":"\u0627\u0644\u0635\u0641\u0631\u0627",
    "qs:name_adm0":"\u0644\u0628\u0646\u0627\u0646",
    "qs:name_adm1":"\u062c\u0628\u0644 \u0644\u0628\u0646\u0627\u0646",
    "qs:photos":42,
    "qs:photos_1k":9,
    "qs:photos_9k":1,
    "qs:photos_9r":2,
    "qs:photos_all":42,
    "qs:photos_sr":2,
    "qs:placetype":"Town",
    "qs:pop_sr":"0",
    "qs:woe_adm0":23424873,
    "wof:name":"\u0627\u0644\u0635\u0641\u0631\u0627",
    "wof:placetype":"locality"
},
  "geometry": {"coordinates":[35.63768,34.0425495],"type":"Point"}
}