{
  "type": "Feature",
  "properties": {
    "gn:admin1_code":"6.0",
    "gn:asciiname":"Arzoun",
    "gn:country_code":"LB",
    "gn:dem":348,
    "gn:feature_class":"P",
    "gn:feature_code":"PPL",
    "gn:name":"Arzo\u00fbn",
    "gn:population":0,
    "gn:timezone":"Asia/Beirut",
    "iso:country":"LB",
    "name:ara_x_preferred":[
        "\u0623\u0631\u0632\u0648\u0646"
    ],
    "name:und_x_variant":[
        "Arz\u016bn",
        "Arzo\u00fbn"
    ],
    "wof:name":"Arzoun",
    "wof:placetype":"locality"
},
  "geometry": {"coordinates":[35.37722,33.28278],"type":"Point"}
}