{
  "type": "Feature",
  "properties": {
    "gn:admin1_code":"6.0",
    "gn:asciiname":"Sfaray",
    "gn:country_code":"LB",
    "gn:dem":525,
    "gn:feature_class":"P",
    "gn:feature_code":"PPL",
    "gn:name":"Sf\u00e2ray",
    "gn:population":0,
    "gn:timezone":"Asia/Beirut",
    "iso:country":"LB",
    "name:ara_x_preferred":[
        "\u0635\u0641\u0627\u0631\u064a\u0629"
    ],
    "name:ara_x_variant":[
        "\u0635\u0641\u0627\u0631\u0627\u064a"
    ],
    "name:und_x_variant":[
        "Fulf\u0101r\u012byah",
        "\u015eaf\u0101r\u012b",
        "Sf\u00e2ray",
        "\u015eaf\u0101rayah",
        "\u015eaf\u0101r\u0101y"
    ],
    "wof:name":"Sfaray",
    "wof:placetype":"locality"
},
  "geometry": {"coordinates":[35.49389,33.55528],"type":"Point"}
}