{
  "type": "Feature",
  "properties": {
    "gn:admin1_code":"5.0",
    "gn:asciiname":"Bqechqech",
    "gn:country_code":"LB",
    "gn:dem":1027,
    "gn:feature_class":"P",
    "gn:feature_code":"PPL",
    "gn:name":"Bqechqech",
    "gn:population":0,
    "gn:timezone":"Asia/Beirut",
    "iso:country":"LB",
    "name:ara_x_preferred":[
        "\u0628\u0642\u0634\u0642\u0634"
    ],
    "name:und_x_variant":[
        "Baqashqash"
    ],
    "wof:name":"Bqechqech",
    "wof:placetype":"locality"
},
  "geometry": {"coordinates":[35.87871,34.09401],"type":"Point"}
}