{
  "type": "Feature",
  "properties": {
    "gn:admin1_code":"6.0",
    "gn:asciiname":"Derdghaya",
    "gn:country_code":"LB",
    "gn:dem":398,
    "gn:feature_class":"P",
    "gn:feature_code":"PPL",
    "gn:name":"Derdghaya",
    "gn:population":0,
    "gn:timezone":"Asia/Beirut",
    "iso:country":"LB",
    "name:ara_x_preferred":[
        "\u062f\u0631\u062f\u063a\u064a\u0627"
    ],
    "name:und_x_variant":[
        "Dardagheiya",
        "Derdarha\u00efya",
        "Dirdghayy\u0101",
        "Derdghaya",
        "Dordghaya"
    ],
    "wof:name":"Derdghaya",
    "wof:placetype":"locality"
},
  "geometry": {"coordinates":[35.37110999999999,33.28083],"type":"Point"}
}