{
  "type": "Feature",
  "properties": {
    "gn:admin1_code":"9.0",
    "gn:asciiname":"Chira",
    "gn:country_code":"LB",
    "gn:dem":718,
    "gn:feature_class":"P",
    "gn:feature_code":"PPL",
    "gn:name":"Ch\u00eera",
    "gn:population":0,
    "gn:timezone":"Asia/Beirut",
    "iso:country":"LB",
    "name:ara_x_preferred":[
        "\u0634\u064a\u0631\u0627"
    ],
    "name:und_x_variant":[
        "Sh\u012br\u0101",
        "Ch\u00eera"
    ],
    "wof:name":"Chira",
    "wof:placetype":"locality"
},
  "geometry": {"coordinates":[35.86582999999999,34.2725],"type":"Point"}
}