{
  "type": "Feature",
  "properties": {
    "gn:admin1_code":"5.0",
    "gn:asciiname":"Es Seffai",
    "gn:country_code":"LB",
    "gn:dem":926,
    "gn:feature_class":"P",
    "gn:feature_code":"PPL",
    "gn:name":"Es Seffa\u00ef",
    "gn:population":0,
    "gn:timezone":"Asia/Beirut",
    "iso:country":"LB",
    "name:ara_x_preferred":[
        "\u0627\u0644\u0635\u0641\u0651\u064a"
    ],
    "name:und_x_variant":[
        "Es Soffi",
        "Es-Siffi",
        "Es Safi",
        "A\u015f \u015eiff\u012b",
        "Es Seffa\u00ef",
        "A\u015f \u015eaff\u012b"
    ],
    "wof:name":"Es Seffai",
    "wof:placetype":"locality"
},
  "geometry": {"coordinates":[35.68389000000001,33.74056],"type":"Point"}
}