{
  "type": "Feature",
  "properties": {
    "gn:admin1_code":"9.0",
    "gn:asciiname":"Ech Chrife",
    "gn:country_code":"LB",
    "gn:dem":624,
    "gn:feature_class":"P",
    "gn:feature_code":"PPL",
    "gn:name":"Ech Chr\u00eef\u00e9",
    "gn:population":0,
    "gn:timezone":"Asia/Beirut",
    "iso:country":"LB",
    "name:und_x_variant":[
        "Ash Shar\u012bfah",
        "Ech Chr\u00eef\u00e9"
    ],
    "wof:name":"Ech Chrife",
    "wof:placetype":"locality"
},
  "geometry": {"coordinates":[35.79639,34.23194],"type":"Point"}
}