{
  "type": "Feature",
  "properties": {
    "gn:admin1_code":"6.0",
    "gn:asciiname":"Ej Jarmaq",
    "gn:country_code":"LB",
    "gn:dem":422,
    "gn:feature_class":"P",
    "gn:feature_code":"PPL",
    "gn:name":"Ej Jarmaq",
    "gn:population":0,
    "gn:timezone":"Asia/Beirut",
    "iso:country":"LB",
    "name:ara_x_preferred":[
        "\u0627\u0644\u062c\u0631\u0645\u0642"
    ],
    "name:ara_x_variant":[
        "\u062c\u0631\u0645\u0642"
    ],
    "name:ita_x_preferred":[
        "Jarmak"
    ],
    "name:und_x_variant":[
        "Al Jarmaq",
        "El-Jarmaq",
        "Jarmaq",
        "Ej Jarmaq"
    ],
    "wof:name":"Ej Jarmaq",
    "wof:placetype":"locality"
},
  "geometry": {"coordinates":[35.535,33.38583],"type":"Point"}
}