{
  "type": "Feature",
  "properties": {
    "gn:admin1_code":"9.0",
    "gn:asciiname":"Yarita",
    "gn:country_code":"LB",
    "gn:dem":667,
    "gn:feature_class":"P",
    "gn:feature_code":"PPL",
    "gn:name":"Y\u00e2r\u00eeta",
    "gn:population":0,
    "gn:timezone":"Asia/Beirut",
    "iso:country":"LB",
    "name:ara_x_preferred":[
        "\u064a\u0627\u0631\u064a\u062a\u0627"
    ],
    "name:ara_x_variant":[
        "Y\u0101r\u012bt\u0101"
    ],
    "name:und_x_variant":[
        "Y\u00e2r\u00eeta"
    ],
    "wof:name":"Yarita",
    "wof:placetype":"locality"
},
  "geometry": {"coordinates":[35.79028,34.22694],"type":"Point"}
}