{
  "type": "Feature",
  "properties": {
    "gn:admin1_code":"7.0",
    "gn:asciiname":"Aarab Salim",
    "gn:country_code":"LB",
    "gn:dem":577,
    "gn:feature_class":"P",
    "gn:feature_code":"PPL",
    "gn:name":"Aarab Sal\u00eem",
    "gn:population":0,
    "gn:timezone":"Asia/Beirut",
    "iso:country":"LB",
    "name:ara_x_preferred":[
        "\u0639\u0631\u0628 \u0635\u0644\u064a\u0645"
    ],
    "name:und_x_variant":[
        "\u2018Arab \u015e\u0101l\u012bm",
        "\u2018Arab Bsaleem",
        "Aarab Sal\u00eem"
    ],
    "wof:name":"Aarab Salim",
    "wof:placetype":"locality"
},
  "geometry": {"coordinates":[35.51583,33.42972],"type":"Point"}
}