{
  "type": "Feature",
  "properties": {
    "gn:admin1_code":"5.0",
    "gn:asciiname":"Qornayel",
    "gn:country_code":"LB",
    "gn:dem":1170,
    "gn:feature_class":"P",
    "gn:feature_code":"PPL",
    "gn:name":"Qorn\u00e2yel",
    "gn:population":0,
    "gn:timezone":"Asia/Beirut",
    "iso:country":"LB",
    "name:ara_x_preferred":[
        "\u0642\u0631\u0646\u0627\u064a\u0644"
    ],
    "name:ceb_x_preferred":[
        "Qorn\u00e2yel"
    ],
    "name:fra_x_preferred":[
        "Qornayel"
    ],
    "name:ita_x_preferred":[
        "Qornayel"
    ],
    "name:nno_x_preferred":[
        "Qarnayel"
    ],
    "name:pam_x_preferred":[
        "Qarnayel"
    ],
    "name:swe_x_preferred":[
        "Qorn\u00e2yel"
    ],
    "name:und_x_variant":[
        "Qurn\u0101yil",
        "Qorn\u00e2yel"
    ],
    "wof:name":"Qornayel",
    "wof:placetype":"locality"
},
  "geometry": {"coordinates":[35.72639,33.85528],"type":"Point"}
}