{
  "type": "Feature",
  "properties": {
    "gn:admin1_code":"8.0",
    "gn:asciiname":"Tell ez Zaazeaa",
    "gn:country_code":"LB",
    "gn:dem":869,
    "gn:feature_class":"P",
    "gn:feature_code":"PPL",
    "gn:name":"Tell ez Zaazeaa",
    "gn:population":0,
    "gn:timezone":"Asia/Beirut",
    "iso:country":"LB",
    "name:ara_x_preferred":[
        "\u062a\u0644 \u0627\u0644\u0632\u0639\u0627\u0632\u0639"
    ],
    "name:und_x_variant":[
        "Aabd el Fatt\u00e2h",
        "Tall az Za\u2018\u0101zi\u2018",
        "Tell ez Zaazeaa"
    ],
    "wof:name":"Tell ez Zaazeaa",
    "wof:placetype":"locality"
},
  "geometry": {"coordinates":[35.85361,33.67361],"type":"Point"}
}