{
  "type": "Feature",
  "properties": {
    "gn:admin1_code":"8.0",
    "gn:asciiname":"Libbaya",
    "gn:country_code":"LB",
    "gn:dem":1219,
    "gn:feature_class":"P",
    "gn:feature_code":"PPL",
    "gn:name":"Libb\u00e2ya",
    "gn:population":0,
    "gn:timezone":"Asia/Beirut",
    "iso:country":"LB",
    "name:ara_x_preferred":[
        "\u0644\u0628\u0651\u0627\u064a\u0627"
    ],
    "name:und_x_variant":[
        "Lebbaya",
        "Libb\u00e2ya",
        "Libb\u0101y\u0101"
    ],
    "wof:name":"Libbaya",
    "wof:placetype":"locality"
},
  "geometry": {"coordinates":[35.72417,33.48222],"type":"Point"}
}