{
  "type": "Feature",
  "properties": {
    "gn:gn_country":"LB",
    "gn:gn_fcode":"PPL",
    "gn:gn_pop":0,
    "iso:country":"LB",
    "qs_pg:aaroncc":"LB",
    "qs_pg:gn_country":"LB",
    "qs_pg:gn_fcode":"PPL",
    "qs_pg:gn_pop":0,
    "qs_pg:name":"Tall Az Za\u2019tar",
    "qs_pg:name_adm0":"\u0644\u0628\u0646\u0627\u0646",
    "qs_pg:name_adm1":"\u062c\u0628\u0644 \u0644\u0628\u0646\u0627\u0646",
    "qs_pg:photos":67,
    "qs_pg:photos_1k":14,
    "qs_pg:photos_9k":1,
    "qs_pg:photos_9r":2,
    "qs_pg:photos_all":67,
    "qs_pg:photos_sr":2,
    "qs_pg:pop_sr":0,
    "qs_pg:qs_pg_placetype":"neighbourhood",
    "qs_pg:qs_pg_placetype_gp":"Suburb",
    "qs_pg:woe_adm0":23424873,
    "woe:adm0_id":23424873,
    "woe:name_adm0":"\u0644\u0628\u0646\u0627\u0646",
    "woe:name_adm1":"\u062c\u0628\u0644 \u0644\u0628\u0646\u0627\u0646",
    "woe:placetype":"Suburb",
    "wof:name":"Tall Az Za\u2019tar",
    "wof:placetype":"neighbourhood"
},
  "geometry": {"coordinates":[35.54917,33.86861],"type":"Point"}
}