{
  "type": "Feature",
  "properties": {
    "gn:admin1_code":"10.0",
    "gn:asciiname":"Hrar",
    "gn:country_code":"LB",
    "gn:dem":870,
    "gn:feature_class":"P",
    "gn:feature_code":"PPL",
    "gn:name":"Hr\u00e2r",
    "gn:population":0,
    "gn:timezone":"Asia/Beirut",
    "iso:country":"LB",
    "wof:name":"Hrar",
    "wof:placetype":"locality"
},
  "geometry": {"coordinates":[36.12167,34.45722],"type":"Point"}
}