{
  "type": "Feature",
  "properties": {
    "gn:admin1_code":"11.0",
    "gn:asciiname":"Ez Zire",
    "gn:country_code":"LB",
    "gn:dem":825,
    "gn:feature_class":"P",
    "gn:feature_code":"PPL",
    "gn:name":"Ez Z\u00eer\u00e9",
    "gn:population":0,
    "gn:timezone":"Asia/Beirut",
    "iso:country":"LB",
    "name:und_x_variant":[
        "Az Z\u012brah",
        "Ez Z\u00eer\u00e9"
    ],
    "wof:name":"Ez Zire",
    "wof:placetype":"locality"
},
  "geometry": {"coordinates":[36.34833,34.23889],"type":"Point"}
}