{
  "type": "Feature",
  "properties": {
    "gn:admin1_code":"5.0",
    "gn:asciiname":"El Msaijed",
    "gn:country_code":"LB",
    "gn:dem":893,
    "gn:feature_class":"P",
    "gn:feature_code":"PPL",
    "gn:name":"El Msa\u00efjed",
    "gn:population":0,
    "gn:timezone":"Asia/Beirut",
    "iso:country":"LB",
    "name:ara_x_preferred":[
        "\u0627\u0644\u0645\u0633\u064a\u062c\u062f"
    ],
    "name:und_x_variant":[
        "Al Musayjid",
        "El Msa\u00efjed"
    ],
    "wof:name":"El Msaijed",
    "wof:placetype":"locality"
},
  "geometry": {"coordinates":[35.5675,33.68083],"type":"Point"}
}