{
  "type": "Feature",
  "properties": {
    "gn:admin1_code":"7.0",
    "gn:asciiname":"Mazraat el Hmaile",
    "gn:country_code":"LB",
    "gn:dem":474,
    "gn:feature_class":"P",
    "gn:feature_code":"PPL",
    "gn:name":"Mazraat el Hma\u00efl\u00e9",
    "gn:population":0,
    "gn:timezone":"Asia/Beirut",
    "iso:country":"LB",
    "name:ara_x_preferred":[
        "\u0645\u0632\u0631\u0639\u0629 \u062d\u0645\u064a\u0644\u0629"
    ],
    "name:ara_x_variant":[
        "\u0645\u0632\u0631\u0639\u0629 \u0627\u0644\u062d\u0645\u064a\u0644\u0629"
    ],
    "name:und_x_variant":[
        "Hmeilah",
        "Mazra\u2018at al \u1e28umaylah",
        "Mazraat el Hma\u00efl\u00e9",
        "Mazra\u2018at \u1e28umaylah"
    ],
    "wof:name":"Mazraat el Hmaile",
    "wof:placetype":"locality"
},
  "geometry": {"coordinates":[35.46886,33.44825],"type":"Point"}
}