{
  "type": "Feature",
  "properties": {
    "gn:admin1_code":"5.0",
    "gn:asciiname":"Bmakkine",
    "gn:country_code":"LB",
    "gn:dem":865,
    "gn:feature_class":"P",
    "gn:feature_code":"PPL",
    "gn:name":"Bmakkine",
    "gn:population":0,
    "gn:timezone":"Asia/Beirut",
    "iso:country":"LB",
    "name:ara_x_preferred":[
        "\u0628\u0645\u0643\u064a\u0646"
    ],
    "name:und_x_variant":[
        "Bmakk\u012bn"
    ],
    "wof:name":"Bmakkine",
    "wof:placetype":"locality"
},
  "geometry": {"coordinates":[35.56739,33.79617],"type":"Point"}
}