{
  "type": "Feature",
  "properties": {
    "gn:admin1_code":"8.0",
    "gn:asciiname":"En Naqbe",
    "gn:country_code":"LB",
    "gn:dem":912,
    "gn:feature_class":"P",
    "gn:feature_code":"PPL",
    "gn:name":"En Naqb\u00e9",
    "gn:population":0,
    "gn:timezone":"Asia/Beirut",
    "iso:country":"LB",
    "name:ara_x_preferred":[
        "\u0627\u0644\u0646\u0642\u0628\u0629"
    ],
    "name:und_x_variant":[
        "An Naqbah",
        "En Naqb\u00e9"
    ],
    "wof:name":"En Naqbe",
    "wof:placetype":"locality"
},
  "geometry": {"coordinates":[35.83694000000001,33.80833],"type":"Point"}
}