{
  "type": "Feature",
  "properties": {
    "gn:admin1_code":"5.0",
    "gn:asciiname":"Mazraat ech Chouf",
    "gn:country_code":"LB",
    "gn:dem":937,
    "gn:feature_class":"P",
    "gn:feature_code":"PPL",
    "gn:name":"Mazraat ech Cho\u00fbf",
    "gn:population":0,
    "gn:timezone":"Asia/Beirut",
    "iso:country":"LB",
    "name:ara_x_preferred":[
        "\u0645\u0632\u0631\u0639\u0629 \u0627\u0644\u0634\u0648\u0641"
    ],
    "name:und_x_variant":[
        "Mazra\u2018at ash Sh\u016bf",
        "Mazraat ech Cho\u00fbf"
    ],
    "wof:name":"Mazraat ech Chouf",
    "wof:placetype":"locality"
},
  "geometry": {"coordinates":[35.58667,33.64278],"type":"Point"}
}