{
  "type": "Feature",
  "properties": {
    "gn:admin1_code":"6.0",
    "gn:asciiname":"El Maqsaf",
    "gn:country_code":"LB",
    "gn:dem":13,
    "gn:feature_class":"P",
    "gn:feature_code":"PPL",
    "gn:name":"El Maqsaf",
    "gn:population":0,
    "gn:timezone":"Asia/Beirut",
    "iso:country":"LB",
    "name:ara_x_preferred":[
        "\u0627\u0644\u0645\u0642\u0635\u0641"
    ],
    "name:und_x_variant":[
        "Al Maq\u015faf"
    ],
    "wof:name":"El Maqsaf",
    "wof:placetype":"locality"
},
  "geometry": {"coordinates":[35.37556,33.56472],"type":"Point"}
}