{
  "type": "Feature",
  "properties": {
    "gn:admin1_code":"5.0",
    "gn:asciiname":"Bmahrai",
    "gn:country_code":"LB",
    "gn:dem":1206,
    "gn:feature_class":"P",
    "gn:feature_code":"PPL",
    "gn:name":"Bmahra\u00ef",
    "gn:population":0,
    "gn:timezone":"Asia/Beirut",
    "iso:country":"LB",
    "name:ara_x_preferred":[
        "\u0628\u0645\u0647\u0631\u0627\u064a"
    ],
    "name:ara_x_variant":[
        "\u0628\u0645\u0647\u0631\u064a\u0647"
    ],
    "name:fas_x_preferred":[
        "\u0628\u0645\u0647\u0631\u06cc\u0647"
    ],
    "name:ita_x_preferred":[
        "Bmahray"
    ],
    "name:nno_x_preferred":[
        "Bmahray"
    ],
    "name:und_x_variant":[
        "Bmahr\u0101y",
        "Bmahra\u00ef"
    ],
    "name:urd_x_preferred":[
        "\u0628\u0645\u06c1\u0631\u06cc\u06c1"
    ],
    "wof:name":"Bmahrai",
    "wof:placetype":"locality"
},
  "geometry": {"coordinates":[35.7175,33.75667],"type":"Point"}
}