{
  "type": "Feature",
  "properties": {
    "gn:admin1_code":"9.0",
    "gn:asciiname":"Maassarati",
    "gn:country_code":"LB",
    "gn:dem":658,
    "gn:feature_class":"P",
    "gn:feature_code":"PPL",
    "gn:name":"Maassar\u00e2t\u012b",
    "gn:population":0,
    "gn:timezone":"Asia/Beirut",
    "iso:country":"LB",
    "name:und_x_variant":[
        "Ma\u2018\u015far\u0101t\u012b",
        "Maassar\u00e2t\u012b"
    ],
    "wof:name":"Maassarati",
    "wof:placetype":"locality"
},
  "geometry": {"coordinates":[35.99472,34.40722],"type":"Point"}
}