{
  "type": "Feature",
  "properties": {
    "gn:admin1_code":"9.0",
    "gn:asciiname":"Debaal",
    "gn:country_code":"LB",
    "gn:dem":613,
    "gn:feature_class":"P",
    "gn:feature_code":"PPL",
    "gn:name":"Debaal",
    "gn:population":0,
    "gn:timezone":"Asia/Beirut",
    "iso:country":"LB",
    "name:und_x_variant":[
        "Deba\u00efl",
        "Dib\u2018il",
        "Debaal"
    ],
    "wof:name":"Debaal",
    "wof:placetype":"locality"
},
  "geometry": {"coordinates":[36.07639,34.43472],"type":"Point"}
}