{
  "type": "Feature",
  "properties": {
    "gn:admin1_code":"5.0",
    "gn:asciiname":"Bentaael",
    "gn:country_code":"LB",
    "gn:dem":509,
    "gn:feature_class":"P",
    "gn:feature_code":"PPL",
    "gn:name":"Bent\u00e2ael",
    "gn:population":0,
    "gn:timezone":"Asia/Beirut",
    "iso:country":"LB",
    "name:ara_x_preferred":[
        "\u0628\u0646\u062a\u0627\u0639\u0644"
    ],
    "name:und_x_variant":[
        "Benta\u00ebl",
        "Binta\u2018el",
        "Binntail",
        "Bint\u0101\u2018il",
        "Bent\u00e2ael"
    ],
    "wof:name":"Bentaael",
    "wof:placetype":"locality"
},
  "geometry": {"coordinates":[35.69417,34.14583],"type":"Point"}
}