{
  "type": "Feature",
  "properties": {
    "gn:admin1_code":"6.0",
    "gn:asciiname":"Ej Jdaide",
    "gn:country_code":"LB",
    "gn:dem":717,
    "gn:feature_class":"P",
    "gn:feature_code":"PPL",
    "gn:name":"Ej Jda\u00efd\u00e9",
    "gn:population":0,
    "gn:timezone":"Asia/Beirut",
    "iso:country":"LB",
    "name:ara_x_preferred":[
        "\u0627\u0644\u062c\u062f\u064a\u062f\u0629"
    ],
    "name:und_x_variant":[
        "Al Judaydah",
        "Ej Jda\u00efd\u00e9"
    ],
    "wof:name":"Ej Jdaide",
    "wof:placetype":"locality"
},
  "geometry": {"coordinates":[35.58278,33.55444],"type":"Point"}
}