{
  "type": "Feature",
  "properties": {
    "gn:admin1_code":"5.0",
    "gn:asciiname":"Mihqane el Mazloum",
    "gn:country_code":"LB",
    "gn:dem":1409,
    "gn:feature_class":"P",
    "gn:feature_code":"PPL",
    "gn:name":"Mihq\u00e2ne el Mazlo\u00fbm",
    "gn:population":0,
    "gn:timezone":"Asia/Beirut",
    "iso:country":"LB",
    "name:ara_x_preferred":[
        "\u0645\u062d\u0642\u0627\u0646 \u0627\u0644\u0645\u0638\u0644\u0648\u0645"
    ],
    "name:und_x_variant":[
        "Mi\u1e29q\u0101n al Maz\u0327l\u016bm",
        "Mihq\u00e2ne el Mazlo\u00fbm"
    ],
    "wof:name":"Mihqane el Mazloum",
    "wof:placetype":"locality"
},
  "geometry": {"coordinates":[35.755,34.01611],"type":"Point"}
}