{
  "type": "Feature",
  "properties": {
    "gn:admin1_code":"5.0",
    "gn:asciiname":"Mezher",
    "gn:country_code":"LB",
    "gn:dem":65,
    "gn:feature_class":"P",
    "gn:feature_code":"PPL",
    "gn:name":"Mezher",
    "gn:population":0,
    "gn:timezone":"Asia/Beirut",
    "iso:country":"LB",
    "name:ara_x_preferred":[
        "\u0645\u0632\u0647\u0631"
    ],
    "name:ceb_x_preferred":[
        "Mezher"
    ],
    "name:fra_x_preferred":[
        "Mezher"
    ],
    "name:nno_x_preferred":[
        "Mezher"
    ],
    "name:swe_x_preferred":[
        "Mezher"
    ],
    "name:und_x_variant":[
        "Muzhir"
    ],
    "wof:name":"Mezher",
    "wof:placetype":"locality"
},
  "geometry": {"coordinates":[35.59139000000001,33.91111],"type":"Point"}
}