{
  "type": "Feature",
  "properties": {
    "gn:admin1_code":"5.0",
    "gn:asciiname":"Ech Chaara",
    "gn:country_code":"LB",
    "gn:dem":1299,
    "gn:feature_class":"P",
    "gn:feature_code":"PPL",
    "gn:name":"Ech Chaara",
    "gn:population":0,
    "gn:timezone":"Asia/Beirut",
    "iso:country":"LB",
    "name:und_x_variant":[
        "Ash Sha\u2018rah",
        "Ech Chaara"
    ],
    "wof:name":"Ech Chaara",
    "wof:placetype":"locality"
},
  "geometry": {"coordinates":[35.81028,34.01028],"type":"Point"}
}