{
  "type": "Feature",
  "properties": {
    "gn:admin1_code":"9.0",
    "gn:asciiname":"El Blat",
    "gn:country_code":"LB",
    "gn:dem":1023,
    "gn:feature_class":"P",
    "gn:feature_code":"PPL",
    "gn:name":"El Bl\u00e2t",
    "gn:population":0,
    "gn:timezone":"Asia/Beirut",
    "iso:country":"LB",
    "name:und_x_variant":[
        "Al Bal\u0101\u0163",
        "El Bl\u00e2t"
    ],
    "wof:name":"El Blat",
    "wof:placetype":"locality"
},
  "geometry": {"coordinates":[35.86278,34.2225],"type":"Point"}
}