{
  "type": "Feature",
  "properties": {
    "gn:admin1_code":"5.0",
    "gn:asciiname":"Ej Jaayel",
    "gn:country_code":"LB",
    "gn:dem":1063,
    "gn:feature_class":"P",
    "gn:feature_code":"PPL",
    "gn:name":"Ej Ja\u00e2yel",
    "gn:population":0,
    "gn:timezone":"Asia/Beirut",
    "iso:country":"LB",
    "name:ara_x_preferred":[
        "\u0627\u0644\u062c\u0639\u0627\u064a\u0644"
    ],
    "name:und_x_variant":[
        "Ej Ja\u00e2ye",
        "El Jaayel",
        "El-Ja\u2018ayil",
        "Al Ja\u2018\u0101yil",
        "Ej Ja\u00e2yel"
    ],
    "wof:name":"Ej Jaayel",
    "wof:placetype":"locality"
},
  "geometry": {"coordinates":[35.64972,33.72861],"type":"Point"}
}