{
  "type": "Feature",
  "properties": {
    "gn:admin1_code":"5.0",
    "gn:asciiname":"Es Sabtiye",
    "gn:country_code":"LB",
    "gn:dem":170,
    "gn:feature_class":"P",
    "gn:feature_code":"PPL",
    "gn:name":"Es Sabtiy\u00e9",
    "gn:population":0,
    "gn:timezone":"Asia/Beirut",
    "iso:country":"LB",
    "name:ara_x_preferred":[
        "\u0627\u0644\u0633\u0628\u062a\u064a\u0629"
    ],
    "name:und_x_variant":[
        "Sabt\u012byah",
        "Es Sabtiy\u00e9",
        "As Sabt\u012byah"
    ],
    "wof:name":"Es Sabtiye",
    "wof:placetype":"locality"
},
  "geometry": {"coordinates":[35.56778,33.87417],"type":"Point"}
}