{
  "type": "Feature",
  "properties": {
    "gn:admin1_code":"6.0",
    "gn:asciiname":"Mjeidil",
    "gn:country_code":"LB",
    "gn:dem":259,
    "gn:feature_class":"P",
    "gn:feature_code":"PPL",
    "gn:name":"Mje\u00efdil",
    "gn:population":0,
    "gn:timezone":"Asia/Beirut",
    "iso:country":"LB",
    "name:ara_x_preferred":[
        "\u0645\u062c\u064a\u062f\u0644"
    ],
    "name:und_x_variant":[
        "Al Mujaydil",
        "Mje\u00efdil",
        "Mujaydil"
    ],
    "wof:name":"Mjeidil",
    "wof:placetype":"locality"
},
  "geometry": {"coordinates":[35.44028,33.5175],"type":"Point"}
}