{
  "type": "Feature",
  "properties": {
    "gn:admin1_code":"9.0",
    "gn:asciiname":"Kafraiya",
    "gn:country_code":"LB",
    "gn:dem":401,
    "gn:feature_class":"P",
    "gn:feature_code":"PPL",
    "gn:name":"Kafra\u00efya",
    "gn:population":0,
    "gn:timezone":"Asia/Beirut",
    "iso:country":"LB",
    "name:ara_x_preferred":[
        "\u0643\u0641\u0631\u064a\u0627"
    ],
    "name:und_x_variant":[
        "Kafrayy\u0101",
        "Kafra\u00efya"
    ],
    "wof:name":"Kafraiya",
    "wof:placetype":"locality"
},
  "geometry": {"coordinates":[35.9597,34.44744],"type":"Point"}
}