{
  "type": "Feature",
  "properties": {
    "gn:admin1_code":"9.0",
    "gn:asciiname":"Beit ech Chaaer",
    "gn:country_code":"LB",
    "gn:dem":1334,
    "gn:feature_class":"P",
    "gn:feature_code":"PPL",
    "gn:name":"Be\u00eft ech Chaaer",
    "gn:population":0,
    "gn:timezone":"Asia/Beirut",
    "iso:country":"LB",
    "name:und_x_variant":[
        "Bayt ash Sh\u0101\u2018ir",
        "Be\u00eft ech Chaaer"
    ],
    "wof:name":"Beit ech Chaaer",
    "wof:placetype":"locality"
},
  "geometry": {"coordinates":[35.88556,34.19],"type":"Point"}
}