{
  "type": "Feature",
  "properties": {
    "gn:admin1_code":"8.0",
    "gn:asciiname":"Aammiq",
    "gn:country_code":"LB",
    "gn:dem":1007,
    "gn:feature_class":"P",
    "gn:feature_code":"PPL",
    "gn:name":"Aamm\u00eeq",
    "gn:population":0,
    "gn:timezone":"Asia/Beirut",
    "iso:country":"LB",
    "name:ara_x_preferred":[
        "\u0639\u0645\u064a\u0642"
    ],
    "name:deu_x_preferred":[
        "Aammiq"
    ],
    "name:heb_x_preferred":[
        "\u05e2\u05de\u05d9\u05e7"
    ],
    "name:ita_x_preferred":[
        "Ammik"
    ],
    "name:und_x_variant":[
        "Amnik",
        "\u2018Amm\u012bq",
        "Aamm\u00eeq",
        "\u2018Am\u012bq"
    ],
    "name:urd_x_preferred":[
        "\u0622\u0645\u0642"
    ],
    "wof:name":"Aammiq",
    "wof:placetype":"locality"
},
  "geometry": {"coordinates":[35.76028,33.71306],"type":"Point"}
}