{
  "type": "Feature",
  "properties": {
    "gn:admin1_code":"9.0",
    "gn:asciiname":"Bqarsouna",
    "gn:country_code":"LB",
    "gn:dem":1102,
    "gn:feature_class":"P",
    "gn:feature_code":"PPL",
    "gn:name":"Bqarso\u00fbna",
    "gn:population":0,
    "gn:timezone":"Asia/Beirut",
    "iso:country":"LB",
    "name:und_x_variant":[
        "Arsouna",
        "Bqarso\u00fbn\u00e9",
        "Bqar\u015f\u016bnah",
        "Bqarso\u00fbna"
    ],
    "wof:name":"Bqarsouna",
    "wof:placetype":"locality"
},
  "geometry": {"coordinates":[36.04611,34.37860999999999],"type":"Point"}
}