{
  "type": "Feature",
  "properties": {
    "gn:admin1_code":"8.0",
    "gn:asciiname":"Taalabaya",
    "gn:country_code":"LB",
    "gn:dem":910,
    "gn:feature_class":"P",
    "gn:feature_code":"PPL",
    "gn:name":"Taalab\u00e2ya",
    "gn:population":0,
    "gn:timezone":"Asia/Beirut",
    "iso:country":"LB",
    "name:ara_x_preferred":[
        "\u062a\u0639\u0644\u0628\u0627\u064a\u0627"
    ],
    "name:und_x_variant":[
        "Ta\u2018lab\u0101y\u0101",
        "Taalab\u00e2ya"
    ],
    "wof:name":"Taalabaya",
    "wof:placetype":"locality"
},
  "geometry": {"coordinates":[35.86444,33.81361],"type":"Point"}
}