{
  "type": "Feature",
  "properties": {
    "gn:admin1_code":"5.0",
    "gn:asciiname":"Aanj en Nahle",
    "gn:country_code":"LB",
    "gn:dem":881,
    "gn:feature_class":"P",
    "gn:feature_code":"PPL",
    "gn:name":"Aanj en Nahl\u00e9",
    "gn:population":0,
    "gn:timezone":"Asia/Beirut",
    "iso:country":"LB",
    "name:ara_x_preferred":[
        "\u0639\u0646\u062c \u0627\u0644\u0646\u062d\u0644\u0629"
    ],
    "name:und_x_variant":[
        "\u2018Anj an Na\u1e29lah",
        "Aanj en Nahl\u00e9"
    ],
    "wof:name":"Aanj en Nahle",
    "wof:placetype":"locality"
},
  "geometry": {"coordinates":[35.56833,33.6775],"type":"Point"}
}