{
  "type": "Feature",
  "properties": {
    "gn:admin1_code":"5.0",
    "gn:asciiname":"El Manzle",
    "gn:country_code":"LB",
    "gn:dem":1828,
    "gn:feature_class":"P",
    "gn:feature_code":"PPL",
    "gn:name":"El Manzl\u00e9",
    "gn:population":0,
    "gn:timezone":"Asia/Beirut",
    "iso:country":"LB",
    "name:und_x_variant":[
        "Al Manzilah",
        "El Manzl\u00e9"
    ],
    "wof:name":"El Manzle",
    "wof:placetype":"locality"
},
  "geometry": {"coordinates":[35.87944,34.15917],"type":"Point"}
}