{
  "type": "Feature",
  "properties": {
    "gn:admin1_code":"7.0",
    "gn:asciiname":"El Manzale",
    "gn:country_code":"LB",
    "gn:dem":453,
    "gn:feature_class":"P",
    "gn:feature_code":"PPL",
    "gn:name":"El Manzal\u00e9",
    "gn:population":0,
    "gn:timezone":"Asia/Beirut",
    "iso:country":"LB",
    "name:ara_x_preferred":[
        "\u0627\u0644\u0645\u0646\u0632\u0644\u0629"
    ],
    "name:und_x_variant":[
        "Al Manzilah",
        "El Manzal\u00e9"
    ],
    "wof:name":"El Manzale",
    "wof:placetype":"locality"
},
  "geometry": {"coordinates":[35.50194000000001,33.35972],"type":"Point"}
}