{
  "type": "Feature",
  "properties": {
    "gn:admin1_code":"5.0",
    "gn:asciiname":"El Mnazil",
    "gn:country_code":"LB",
    "gn:dem":1028,
    "gn:feature_class":"P",
    "gn:feature_code":"PPL",
    "gn:name":"El Mn\u00e2z\u00eel",
    "gn:population":0,
    "gn:timezone":"Asia/Beirut",
    "iso:country":"LB",
    "name:und_x_variant":[
        "Al Man\u0101z\u012bl",
        "El Mn\u00e2z\u00eel"
    ],
    "wof:name":"El Mnazil",
    "wof:placetype":"locality"
},
  "geometry": {"coordinates":[35.74944,34.12639],"type":"Point"}
}