{
  "type": "Feature",
  "properties": {
    "gn:admin1_code":"5.0",
    "gn:asciiname":"Ghazir",
    "gn:country_code":"LB",
    "gn:dem":369,
    "gn:feature_class":"P",
    "gn:feature_code":"PPL",
    "gn:name":"Ghaz\u00eer",
    "gn:population":0,
    "gn:timezone":"Asia/Beirut",
    "iso:country":"LB",
    "name:ara_x_preferred":[
        "\u063a\u0632\u064a\u0631"
    ],
    "name:deu_x_preferred":[
        "Ghazir"
    ],
    "name:fra_x_preferred":[
        "Ghazir"
    ],
    "name:ita_x_preferred":[
        "Ghazir"
    ],
    "name:pol_x_preferred":[
        "Ghazir"
    ],
    "name:und_x_variant":[
        "Ghazeer",
        "Ghaz\u00eer",
        "Ghaz\u012br"
    ],
    "wof:name":"Ghazir",
    "wof:placetype":"locality"
},
  "geometry": {"coordinates":[35.66611,34.01823],"type":"Point"}
}