{
  "type": "Feature",
  "properties": {
    "gn:admin1_code":"5.0",
    "gn:asciiname":"Jdaidet Ghazir",
    "gn:country_code":"LB",
    "gn:dem":587,
    "gn:feature_class":"P",
    "gn:feature_code":"PPL",
    "gn:name":"Jda\u00efdet Ghaz\u00eer",
    "gn:population":0,
    "gn:timezone":"Asia/Beirut",
    "iso:country":"LB",
    "name:ara_x_preferred":[
        "\u062c\u062f\u064a\u062f\u0629 \u063a\u0632\u064a\u0631"
    ],
    "name:und_x_variant":[
        "Judaydat Ghaz\u012br",
        "Jda\u00efdet Ghaz\u00eer"
    ],
    "wof:name":"Jdaidet Ghazir",
    "wof:placetype":"locality"
},
  "geometry": {"coordinates":[35.69333,34.01972],"type":"Point"}
}