{
  "type": "Feature",
  "properties": {
    "gn:admin1_code":"9.0",
    "gn:asciiname":"Kfar Chellane",
    "gn:country_code":"LB",
    "gn:dem":404,
    "gn:feature_class":"P",
    "gn:feature_code":"PPL",
    "gn:name":"Kfar Chell\u00e2ne",
    "gn:population":0,
    "gn:timezone":"Asia/Beirut",
    "iso:country":"LB",
    "name:ara_x_preferred":[
        "\u0643\u0641\u0631 \u0634\u0644\u0627\u0646"
    ],
    "name:und_x_variant":[
        "Kafr Shill\u0101n",
        "Kfar Chell\u00e2ne"
    ],
    "wof:name":"Kfar Chellane",
    "wof:placetype":"locality"
},
  "geometry": {"coordinates":[35.98667000000001,34.42610999999999],"type":"Point"}
}