{
  "type": "Feature",
  "properties": {
    "gn:admin1_code":"9.0",
    "gn:asciiname":"Ghiyouta",
    "gn:country_code":"LB",
    "gn:dem":1711,
    "gn:feature_class":"P",
    "gn:feature_code":"PPL",
    "gn:name":"Gh\u00eeyo\u00fbta",
    "gn:population":0,
    "gn:timezone":"Asia/Beirut",
    "iso:country":"LB",
    "name:und_x_variant":[
        "Gh\u012by\u016btah",
        "Gh\u00eeyo\u00fbta"
    ],
    "wof:name":"Ghiyouta",
    "wof:placetype":"locality"
},
  "geometry": {"coordinates":[35.89222,34.16806],"type":"Point"}
}