{
  "type": "Feature",
  "properties": {
    "gn:admin1_code":"5.0",
    "gn:asciiname":"Roumiye",
    "gn:country_code":"LB",
    "gn:dem":325,
    "gn:feature_class":"P",
    "gn:feature_code":"PPL",
    "gn:name":"Roumiy\u00e9",
    "gn:population":0,
    "gn:timezone":"Asia/Beirut",
    "iso:country":"LB",
    "name:ara_x_preferred":[
        "\u0631\u0648\u0645\u064a\u0629"
    ],
    "name:und_x_variant":[
        "R\u016bmyah",
        "Roumiy\u00e9",
        "R\u016bm\u012byah"
    ],
    "wof:name":"Roumiye",
    "wof:placetype":"locality"
},
  "geometry": {"coordinates":[35.66472,34.17528],"type":"Point"}
}