{
  "type": "Feature",
  "properties": {
    "gn:admin1_code":"9.0",
    "gn:asciiname":"Zgharta",
    "gn:country_code":"LB",
    "gn:dem":126,
    "gn:feature_class":"P",
    "gn:feature_code":"PPLA2",
    "gn:name":"Zghart\u0101",
    "gn:population":0,
    "gn:timezone":"Asia/Beirut",
    "iso:country":"LB",
    "name:ara_x_preferred":[
        "\u0632\u063a\u0631\u062a\u0627"
    ],
    "name:und_x_variant":[
        "Ezgharta",
        "Zghart\u0101",
        "Zaghart\u0101"
    ],
    "wof:name":"Zgharta",
    "wof:placetype":"locality"
},
  "geometry": {"coordinates":[35.89493,34.39739],"type":"Point"}
}