{
  "type": "Feature",
  "properties": {
    "gn:admin1_code":"9.0",
    "gn:asciiname":"Zgharta",
    "gn:country_code":"LB",
    "gn:dem":126,
    "gn:feature_class":"P",
    "gn:feature_code":"PPLA2",
    "gn:name":"Zghart\u0101",
    "gn:population":0,
    "gn:timezone":"Asia/Beirut",
    "iso:country":"LB",
    "name:ara_x_preferred":[
        "\u0632\u063a\u0631\u062a\u0627"
    ],
    "name:ceb_x_preferred":[
        "Zghart\u0101"
    ],
    "name:deu_x_preferred":[
        "Zgharta"
    ],
    "name:ell_x_preferred":[
        "\u0396\u03b3\u03ac\u03c1\u03c4\u03b1"
    ],
    "name:fas_x_preferred":[
        "\u0632\u063a\u0631\u062a\u0627"
    ],
    "name:fra_x_preferred":[
        "Zghorta"
    ],
    "name:heb_x_preferred":[
        "\u05d6\u05e2'\u05e8\u05ea\u05d0"
    ],
    "name:hye_x_preferred":[
        "\u0536\u0572\u0561\u0580\u0569\u0561"
    ],
    "name:ita_x_preferred":[
        "Zgharta"
    ],
    "name:kor_x_preferred":[
        "\uc988\uac00\ub974\ud0c0"
    ],
    "name:nld_x_preferred":[
        "Zgharta"
    ],
    "name:nno_x_preferred":[
        "Zgharta"
    ],
    "name:nor_x_preferred":[
        "Zgharta"
    ],
    "name:pol_x_preferred":[
        "Zagharta"
    ],
    "name:por_x_preferred":[
        "Zgharta"
    ],
    "name:rus_x_preferred":[
        "\u0417\u0433\u0430\u0440\u0442\u0430"
    ],
    "name:spa_x_preferred":[
        "Zgharta"
    ],
    "name:srp_x_preferred":[
        "\u0417\u0433\u0430\u0440\u0442\u0430"
    ],
    "name:swe_x_preferred":[
        "Zghart\u0101"
    ],
    "name:ukr_x_preferred":[
        "\u0417\u0433\u0430\u0440\u0442\u0430"
    ],
    "name:und_x_variant":[
        "Ezgharta",
        "Zghart\u0101",
        "Zaghart\u0101"
    ],
    "name:zho_x_preferred":[
        "\u8332\u52a0\u723e\u5854"
    ],
    "wof:name":"Zgharta",
    "wof:placetype":"locality"
},
  "geometry": {"coordinates":[35.89493,34.39739],"type":"Point"}
}