{
  "type": "Feature",
  "properties": {
    "gn:admin1_code":"10.0",
    "gn:asciiname":"Bzaita",
    "gn:country_code":"LB",
    "gn:dem":469,
    "gn:feature_class":"P",
    "gn:feature_code":"PPL",
    "gn:name":"Bza\u00efta",
    "gn:population":0,
    "gn:timezone":"Asia/Beirut",
    "iso:country":"LB",
    "name:und_x_variant":[
        "Bzayt\u0101",
        "Bza\u00efta"
    ],
    "wof:name":"Bzaita",
    "wof:placetype":"locality"
},
  "geometry": {"coordinates":[36.08,34.4475],"type":"Point"}
}