{
  "type": "Feature",
  "properties": {
    "gn:admin1_code":"5.0",
    "gn:asciiname":"Aamaret Chalhoub",
    "gn:country_code":"LB",
    "gn:dem":9,
    "gn:feature_class":"P",
    "gn:feature_code":"PPL",
    "gn:name":"Aamaret Chalhoub",
    "gn:population":0,
    "gn:timezone":"Asia/Beirut",
    "iso:country":"LB",
    "name:ara_x_preferred":[
        "\u0639\u0645\u0627\u0631\u0629 \u0634\u0644\u0647\u0648\u0628"
    ],
    "name:und_x_variant":[
        "\u2018Am\u0101rat Shalh\u016bb"
    ],
    "wof:name":"Aamaret Chalhoub",
    "wof:placetype":"locality"
},
  "geometry": {"coordinates":[35.5675,33.89778],"type":"Point"}
}