{
  "type": "Feature",
  "properties": {
    "gn:admin1_code":"5.0",
    "gn:asciiname":"Maqsaba",
    "gn:country_code":"LB",
    "gn:dem":25,
    "gn:feature_class":"P",
    "gn:feature_code":"PPL",
    "gn:name":"Maqsaba",
    "gn:population":0,
    "gn:timezone":"Asia/Beirut",
    "iso:country":"LB",
    "name:ara_x_preferred":[
        "\u0645\u0642\u0635\u0628\u0629"
    ],
    "name:und_x_variant":[
        "Maq\u015fabah",
        "Maqsaba"
    ],
    "wof:name":"Maqsaba",
    "wof:placetype":"locality"
},
  "geometry": {"coordinates":[35.42297,33.68394],"type":"Point"}
}