{
  "type": "Feature",
  "properties": {
    "gn:admin1_code":"5.0",
    "gn:asciiname":"Qlaiaat",
    "gn:country_code":"LB",
    "gn:dem":1062,
    "gn:feature_class":"P",
    "gn:feature_code":"PPL",
    "gn:name":"Qla\u00efa\u00e2t",
    "gn:population":0,
    "gn:timezone":"Asia/Beirut",
    "iso:country":"LB",
    "name:und_x_variant":[
        "Al Qulay\u2018\u0101t",
        "Qla\u00efa\u00e2t"
    ],
    "wof:name":"Qlaiaat",
    "wof:placetype":"locality"
},
  "geometry": {"coordinates":[35.71278,33.97139],"type":"Point"}
}