{
  "type": "Feature",
  "properties": {
    "gn:admin1_code":"10.0",
    "gn:asciiname":"Tell Hmaira",
    "gn:country_code":"LB",
    "gn:dem":23,
    "gn:feature_class":"P",
    "gn:feature_code":"PPL",
    "gn:name":"Tell Hma\u00efra",
    "gn:population":0,
    "gn:timezone":"Asia/Beirut",
    "iso:country":"LB",
    "name:und_x_variant":[
        "Tall \u1e28umayrah",
        "Tell Hma\u00efra"
    ],
    "wof:name":"Tell Hmaira",
    "wof:placetype":"locality"
},
  "geometry": {"coordinates":[36.07667,34.6275],"type":"Point"}
}