{
  "type": "Feature",
  "properties": {
    "gn:admin1_code":"9.0",
    "gn:asciiname":"Kfar Hatna",
    "gn:country_code":"LB",
    "gn:dem":476,
    "gn:feature_class":"P",
    "gn:feature_code":"PPL",
    "gn:name":"Kfar Hatna",
    "gn:population":0,
    "gn:timezone":"Asia/Beirut",
    "iso:country":"LB",
    "name:ara_x_preferred":[
        "\u0643\u0641\u0631 \u062d\u062a\u0646\u0627"
    ],
    "name:und_x_variant":[
        "Aartez",
        "Kafr \u1e28atn\u0101",
        "Kfar Hatna"
    ],
    "wof:name":"Kfar Hatna",
    "wof:placetype":"locality"
},
  "geometry": {"coordinates":[35.74667,34.22944],"type":"Point"}
}