{
  "type": "Feature",
  "properties": {
    "gn:admin1_code":"5.0",
    "gn:asciiname":"Ech Chattouh",
    "gn:country_code":"LB",
    "gn:dem":1008,
    "gn:feature_class":"P",
    "gn:feature_code":"PPL",
    "gn:name":"Ech Chatto\u00fbh",
    "gn:population":0,
    "gn:timezone":"Asia/Beirut",
    "iso:country":"LB",
    "name:und_x_variant":[
        "Ash Sha\u0163\u0163\u016b\u1e29",
        "Ech Chatto\u00fbh"
    ],
    "wof:name":"Ech Chattouh",
    "wof:placetype":"locality"
},
  "geometry": {"coordinates":[35.71389,33.96528],"type":"Point"}
}