{
  "type": "Feature",
  "properties": {
    "gn:admin1_code":"7.0",
    "gn:asciiname":"Haret el Biyader",
    "gn:country_code":"LB",
    "gn:dem":694,
    "gn:feature_class":"P",
    "gn:feature_code":"PPL",
    "gn:name":"H\u00e2ret el Biy\u00e2der",
    "gn:population":0,
    "gn:timezone":"Asia/Beirut",
    "iso:country":"LB",
    "name:ara_x_preferred":[
        "\u062d\u0627\u0631\u0629 \u0627\u0644\u0628\u064a\u0627\u062f\u0631"
    ],
    "name:und_x_variant":[
        "\u1e28\u0101rat al Bay\u0101dir",
        "H\u00e2ret el Biy\u00e2der"
    ],
    "wof:name":"Haret el Biyader",
    "wof:placetype":"locality"
},
  "geometry": {"coordinates":[35.44222,33.18056],"type":"Point"}
}