{
  "type": "Feature",
  "properties": {
    "gn:admin1_code":"6.0",
    "gn:asciiname":"En Najjariye",
    "gn:country_code":"LB",
    "gn:dem":150,
    "gn:feature_class":"P",
    "gn:feature_code":"PPL",
    "gn:name":"En Najjar\u00eey\u00e9",
    "gn:population":0,
    "gn:timezone":"Asia/Beirut",
    "iso:country":"LB",
    "name:ara_x_preferred":[
        "\u0627\u0644\u062c\u0627\u0631\u064a\u0629"
    ],
    "name:ara_x_variant":[
        "\u0627\u0644\u0646\u062c\u0651\u0627\u0631\u064a\u0629"
    ],
    "name:und_x_variant":[
        "Enn Najj\u00e2riye",
        "En-Nijjariyah",
        "An Najj\u0101r\u012byah",
        "En Najjar\u00eey\u00e9"
    ],
    "wof:name":"En Najjariye",
    "wof:placetype":"locality"
},
  "geometry": {"coordinates":[35.34936,33.47153],"type":"Point"}
}