{
  "type": "Feature",
  "properties": {
    "gn:admin1_code":"5.0",
    "gn:asciiname":"El Aaqaibe",
    "gn:country_code":"LB",
    "gn:dem":9,
    "gn:feature_class":"P",
    "gn:feature_code":"PPL",
    "gn:name":"El Aaqa\u00efb\u00e9",
    "gn:population":0,
    "gn:timezone":"Asia/Beirut",
    "iso:country":"LB",
    "name:ara_x_preferred":[
        "\u0627\u0644\u0639\u0642\u064a\u0628\u0629"
    ],
    "name:und_x_variant":[
        "El Aaqa\u00efb\u00e9",
        "Al \u2018Uqaybah"
    ],
    "wof:name":"El Aaqaibe",
    "wof:placetype":"locality"
},
  "geometry": {"coordinates":[35.64360999999999,34.05972],"type":"Point"}
}