{
  "type": "Feature",
  "properties": {
    "gn:admin1_code":"5.0",
    "gn:asciiname":"Jdaidet el Matn",
    "gn:country_code":"LB",
    "gn:dem":32,
    "gn:feature_class":"P",
    "gn:feature_code":"PPLA2",
    "gn:name":"Jdaidet el Matn",
    "gn:population":0,
    "gn:timezone":"Asia/Beirut",
    "iso:country":"LB",
    "name:ara_x_preferred":[
        "\u062c\u062f\u064a\u062f\u0629 \u0627\u0644\u0645\u062a\u0646"
    ],
    "name:ara_x_variant":[
        "\u0627\u0644\u062c\u062f\u064a\u062f\u0629",
        "\u062c\u062f\u064a\u062f\u0629"
    ],
    "name:ceb_x_preferred":[
        "Jdaidet el Matn"
    ],
    "name:fas_x_preferred":[
        "\u062c\u062f\u06cc\u062f\u0647"
    ],
    "name:fra_x_preferred":[
        "Jdeideh"
    ],
    "name:ita_x_preferred":[
        "Judaydat al-Matn"
    ],
    "name:nld_x_preferred":[
        "Jdeideh"
    ],
    "name:nno_x_preferred":[
        "Jdeideh"
    ],
    "name:pam_x_preferred":[
        "Jdeideh"
    ],
    "name:pol_x_preferred":[
        "D\u017cudajda"
    ],
    "name:rus_x_preferred":[
        "\u042d\u043b\u044c-\u0414\u0436\u0443\u0434\u0435\u0439\u0434\u0430"
    ],
    "name:sco_x_preferred":[
        "Jdeideh"
    ],
    "name:swe_x_preferred":[
        "Jdaidet el Matn"
    ],
    "name:ukr_x_preferred":[
        "\u0415\u043b\u044c-\u0414\u0436\u0443\u0434\u0435\u0439\u0434\u0430"
    ],
    "name:und_x_variant":[
        "El Debiyeh",
        "Jedeide",
        "Djedeide",
        "El Judeide",
        "Judaydah al Matn",
        "Jdaid\u00e9",
        "Jdaidet el Matn",
        "Al Judaydah"
    ],
    "name:urd_x_preferred":[
        "\u062c\u062f\u06cc\u062f\u06c1"
    ],
    "name:zho_x_preferred":[
        "\u6731\u4ee3\u5fb7"
    ],
    "wof:name":"Jdaidet el Matn",
    "wof:placetype":"locality"
},
  "geometry": {"coordinates":[35.56639000000001,33.89056],"type":"Point"}
}