{
  "type": "Feature",
  "properties": {
    "gn:admin1_code":"5.0",
    "gn:asciiname":"Jdaidet el Matn",
    "gn:country_code":"LB",
    "gn:dem":32,
    "gn:feature_class":"P",
    "gn:feature_code":"PPLA2",
    "gn:name":"Jdaidet el Matn",
    "gn:population":0,
    "gn:timezone":"Asia/Beirut",
    "iso:country":"LB",
    "name:ara_x_preferred":[
        "\u062c\u062f\u064a\u062f\u0629 \u0627\u0644\u0645\u062a\u0646"
    ],
    "name:ara_x_variant":[
        "\u0627\u0644\u062c\u062f\u064a\u062f\u0629"
    ],
    "name:und_x_variant":[
        "El Debiyeh",
        "Jedeide",
        "Djedeide",
        "El Judeide",
        "Judaydah al Matn",
        "Jdaid\u00e9",
        "Jdaidet el Matn",
        "Al Judaydah"
    ],
    "wof:name":"Jdaidet el Matn",
    "wof:placetype":"locality"
},
  "geometry": {"coordinates":[35.56639000000001,33.89056],"type":"Point"}
}