{
  "type": "Feature",
  "properties": {
    "gn:admin1_code":"5.0",
    "gn:asciiname":"El Mejdel",
    "gn:country_code":"LB",
    "gn:dem":1243,
    "gn:feature_class":"P",
    "gn:feature_code":"PPL",
    "gn:name":"El Mejdel",
    "gn:population":0,
    "gn:timezone":"Asia/Beirut",
    "iso:country":"LB",
    "name:ara_x_preferred":[
        "\u0627\u0644\u0645\u062c\u062f\u0644"
    ],
    "name:und_x_variant":[
        "El Medjel",
        "El Majdel",
        "Al Majdal",
        "El Mejdel"
    ],
    "wof:name":"El Mejdel",
    "wof:placetype":"locality"
},
  "geometry": {"coordinates":[35.90222,34.10611],"type":"Point"}
}