{
  "type": "Feature",
  "properties": {
    "gn:admin1_code":"5.0",
    "gn:asciiname":"Ghobeire",
    "gn:country_code":"LB",
    "gn:dem":48,
    "gn:feature_class":"P",
    "gn:feature_code":"PPL",
    "gn:name":"Ghobe\u00efr\u00e9",
    "gn:population":0,
    "gn:timezone":"Asia/Beirut",
    "iso:country":"LB",
    "name:ara_x_preferred":[
        "\u0627\u0644\u063a\u0628\u064a\u0631\u064a"
    ],
    "name:und_x_variant":[
        "Al Ghubayri",
        "El-Ghbeirih",
        "Ghba\u00efr\u00e9",
        "Ghobair\u00e9",
        "Al Ghubayrah",
        "Ghobe\u00efr\u00e9",
        "Al Ghubayr\u012b"
    ],
    "wof:name":"Ghobeire",
    "wof:placetype":"locality"
},
  "geometry": {"coordinates":[35.50972,33.86],"type":"Point"}
}