{
  "type": "Feature",
  "properties": {
    "gn:admin1_code":"5.0",
    "gn:asciiname":"Mafraq ech Chellalat",
    "gn:country_code":"LB",
    "gn:dem":2,
    "gn:feature_class":"P",
    "gn:feature_code":"PPL",
    "gn:name":"Mafraq ech Chell\u00e2l\u00e2t",
    "gn:population":0,
    "gn:timezone":"Asia/Beirut",
    "iso:country":"LB",
    "name:und_x_variant":[
        "Mafraq ash Shall\u0101l\u0101t",
        "Mafraq ech Chell\u00e2l\u00e2t"
    ],
    "wof:name":"Mafraq ech Chellalat",
    "wof:placetype":"locality"
},
  "geometry": {"coordinates":[35.64360999999999,34.06361],"type":"Point"}
}