{
  "type": "Feature",
  "properties": {
    "gn:admin1_code":"10.0",
    "gn:asciiname":"El Mdiq",
    "gn:country_code":"LB",
    "gn:dem":161,
    "gn:feature_class":"P",
    "gn:feature_code":"PPL",
    "gn:name":"El Mdiq",
    "gn:population":0,
    "gn:timezone":"Asia/Beirut",
    "iso:country":"LB",
    "name:ara_x_preferred":[
        "\u0627\u0644\u0645\u0636\u064a\u0642"
    ],
    "name:und_x_variant":[
        "Al Ma\u1e11\u012bq"
    ],
    "wof:name":"El Mdiq",
    "wof:placetype":"locality"
},
  "geometry": {"coordinates":[35.883,34.42776],"type":"Point"}
}