{
  "type": "Feature",
  "properties": {
    "gn:admin1_code":"5.0",
    "gn:asciiname":"Chemlane",
    "gn:country_code":"LB",
    "gn:dem":672,
    "gn:feature_class":"P",
    "gn:feature_code":"PPL",
    "gn:name":"Cheml\u00e2ne",
    "gn:population":0,
    "gn:timezone":"Asia/Beirut",
    "iso:country":"LB",
    "name:ara_x_preferred":[
        "\u0634\u0645\u0644\u0627\u0646"
    ],
    "name:und_x_variant":[
        "Chaml\u00e2ne",
        "Shiml\u0101n",
        "Cheml\u00e2ne"
    ],
    "wof:name":"Chemlane",
    "wof:placetype":"locality"
},
  "geometry": {"coordinates":[35.54555999999999,33.78028],"type":"Point"}
}