{
  "type": "Feature",
  "properties": {
    "gn:admin1_code":"5.0",
    "gn:asciiname":"El Ghabat",
    "gn:country_code":"LB",
    "gn:dem":1074,
    "gn:feature_class":"P",
    "gn:feature_code":"PPL",
    "gn:name":"El Gh\u00e2b\u00e2t",
    "gn:population":0,
    "gn:timezone":"Asia/Beirut",
    "iso:country":"LB",
    "name:ara_x_preferred":[
        "\u0627\u0644\u063a\u0627\u0628\u0627\u062a"
    ],
    "name:und_x_variant":[
        "Ghabat",
        "Al Gh\u0101b\u0101t",
        "El Gh\u00e2b\u00e2t"
    ],
    "wof:name":"El Ghabat",
    "wof:placetype":"locality"
},
  "geometry": {"coordinates":[35.87333,34.08222],"type":"Point"}
}