{
  "type": "Feature",
  "properties": {
    "gn:admin1_code":"5.0",
    "gn:asciiname":"Zebdine",
    "gn:country_code":"LB",
    "gn:dem":603,
    "gn:feature_class":"P",
    "gn:feature_code":"PPL",
    "gn:name":"Zebd\u00eene",
    "gn:population":0,
    "gn:timezone":"Asia/Beirut",
    "iso:country":"LB",
    "name:ara_x_preferred":[
        "\u0632\u0628\u062f\u064a\u0646"
    ],
    "name:und_x_variant":[
        "Zibd\u012bn",
        "Zebd\u00eene"
    ],
    "wof:name":"Zebdine",
    "wof:placetype":"locality"
},
  "geometry": {"coordinates":[35.71769000000001,34.09441],"type":"Point"}
}