{
  "type": "Feature",
  "properties": {
    "gn:admin1_code":"9.0",
    "gn:asciiname":"Kfar Saroun",
    "gn:country_code":"LB",
    "gn:dem":343,
    "gn:feature_class":"P",
    "gn:feature_code":"PPL",
    "gn:name":"Kfar S\u00e2ro\u00fbn",
    "gn:population":0,
    "gn:timezone":"Asia/Beirut",
    "iso:country":"LB",
    "name:ara_x_preferred":[
        "\u0643\u0641\u0631 \u0635\u0627\u0631\u0648\u0646"
    ],
    "name:und_x_variant":[
        "Kafr \u015e\u0101r\u016bn",
        "Kfar S\u00e2ro\u00fbn"
    ],
    "wof:name":"Kfar Saroun",
    "wof:placetype":"locality"
},
  "geometry": {"coordinates":[35.83489,34.2978],"type":"Point"}
}