{
  "type": "Feature",
  "properties": {
    "gn:admin1_code":"10.0",
    "gn:asciiname":"Tell Bibi",
    "gn:country_code":"LB",
    "gn:dem":11,
    "gn:feature_class":"P",
    "gn:feature_code":"PPL",
    "gn:name":"Tell B\u00eeb\u00ee",
    "gn:population":0,
    "gn:timezone":"Asia/Beirut",
    "iso:country":"LB",
    "name:und_x_variant":[
        "Tall B\u012bb\u012b",
        "Tell B\u00eeb\u00ee"
    ],
    "wof:name":"Tell Bibi",
    "wof:placetype":"locality"
},
  "geometry": {"coordinates":[36.00667,34.61722],"type":"Point"}
}