{
  "type": "Feature",
  "properties": {
    "gn:admin1_code":"10.0",
    "gn:asciiname":"Tell Aabbas ech Charqi",
    "gn:country_code":"LB",
    "gn:dem":46,
    "gn:feature_class":"P",
    "gn:feature_code":"PPL",
    "gn:name":"Tell Aabb\u00e2s ech Charqi",
    "gn:population":0,
    "gn:timezone":"Asia/Beirut",
    "iso:country":"LB",
    "name:und_x_variant":[
        "Tall \u2018Abb\u0101s ash Sharq\u012b",
        "Tell Aabb\u00e2s ech Charqi"
    ],
    "wof:name":"Tell Aabbas ech Charqi",
    "wof:placetype":"locality"
},
  "geometry": {"coordinates":[36.07917,34.58833],"type":"Point"}
}