{
  "type": "Feature",
  "properties": {
    "gn:admin1_code":"7.0",
    "gn:asciiname":"Hilta el Faouqa",
    "gn:country_code":"LB",
    "gn:dem":563,
    "gn:feature_class":"P",
    "gn:feature_code":"PPL",
    "gn:name":"Hilta el Faouqa",
    "gn:population":0,
    "gn:timezone":"Asia/Beirut",
    "iso:country":"LB",
    "name:ara_x_preferred":[
        "\u062d\u0644\u062a\u0627 \u0627\u0644\u0641\u0648\u0642\u0627"
    ],
    "name:und_x_variant":[
        "\u1e28alt\u0101",
        "Haltaa",
        "Hilta el Faouqa",
        "\u1e28ilt\u0101 al Fawq\u0101"
    ],
    "wof:name":"Hilta el Faouqa",
    "wof:placetype":"locality"
},
  "geometry": {"coordinates":[35.66674000000001,33.30883],"type":"Point"}
}