{
  "type": "Feature",
  "properties": {
    "gn:admin1_code":"5.0",
    "gn:asciiname":"El Qattara",
    "gn:country_code":"LB",
    "gn:dem":1555,
    "gn:feature_class":"P",
    "gn:feature_code":"PPL",
    "gn:name":"El Qatt\u00e2ra",
    "gn:population":0,
    "gn:timezone":"Asia/Beirut",
    "iso:country":"LB",
    "name:und_x_variant":[
        "Al Qa\u0163\u0163\u0101rah",
        "El Qatt\u00e2ra"
    ],
    "wof:name":"El Qattara",
    "wof:placetype":"locality"
},
  "geometry": {"coordinates":[35.7925,33.90028],"type":"Point"}
}