{
  "type": "Feature",
  "properties": {
    "gn:admin1_code":"9.0",
    "gn:asciiname":"Kousba",
    "gn:country_code":"LB",
    "gn:dem":448,
    "gn:feature_class":"P",
    "gn:feature_code":"PPL",
    "gn:name":"Ko\u00fbsba",
    "gn:population":0,
    "gn:timezone":"Asia/Beirut",
    "iso:country":"LB",
    "name:ara_x_preferred":[
        "\u0643\u0648\u0633\u0628\u0627"
    ],
    "name:ara_x_variant":[
        "K\u016bsib\u0101"
    ],
    "name:fra_x_preferred":[
        "Kousba"
    ],
    "name:ita_x_preferred":[
        "Kosba"
    ],
    "name:nno_x_preferred":[
        "Kousba"
    ],
    "name:spa_x_preferred":[
        "Kousba"
    ],
    "name:und_x_variant":[
        "K\u016bsb\u0101",
        "Ko\u00fbsba"
    ],
    "wof:name":"Kousba",
    "wof:placetype":"locality"
},
  "geometry": {"coordinates":[35.85055999999999,34.29972],"type":"Point"}
}