{
  "type": "Feature",
  "properties": {
    "iso:country":"LB",
    "name:ara_x_preferred":[
        "\u0642\u0631\u0637\u0628\u0627"
    ],
    "name:dut_x_preferred":[
        "Qartaba"
    ],
    "name:eng_x_preferred":[
        "Qartaba"
    ],
    "name:fre_x_preferred":[
        "Qartaba"
    ],
    "name:mzn_x_preferred":[
        "\u0642\u0631\u0637\u0628\u0647"
    ],
    "name:nno_x_preferred":[
        "Qartaba"
    ],
    "name:per_x_preferred":[
        "\u0642\u0631\u0637\u0628\u0647"
    ],
    "name:unk_x_variant":[
        "Qartaba"
    ],
    "qs:gn_country":"LB",
    "qs:gn_fcode":"PPL",
    "qs:gn_pop":0,
    "qs:name":"\u0642\u0631\u0637\u0628\u0627",
    "qs:name_adm0":"\u0644\u0628\u0646\u0627\u0646",
    "qs:name_adm1":"\u062c\u0628\u0644 \u0644\u0628\u0646\u0627\u0646",
    "qs:photos":1,
    "qs:photos_1k":1,
    "qs:photos_9k":1,
    "qs:photos_9r":1,
    "qs:photos_all":1,
    "qs:photos_sr":1,
    "qs:placetype":"Town",
    "qs:pop_sr":"0",
    "qs:woe_adm0":23424873,
    "wof:name":"\u0642\u0631\u0637\u0628\u0627",
    "wof:placetype":"locality"
},
  "geometry": {"coordinates":[35.84778,34.095],"type":"Point"}
}