{
  "type": "Feature",
  "properties": {
    "gn:admin1_code":"6.0",
    "gn:asciiname":"Choualiq",
    "gn:country_code":"LB",
    "gn:dem":338,
    "gn:feature_class":"P",
    "gn:feature_code":"PPL",
    "gn:name":"Chou\u00e2l\u00eeq",
    "gn:population":0,
    "gn:timezone":"Asia/Beirut",
    "iso:country":"LB",
    "name:ara_x_preferred":[
        "\u0627\u0644\u0634\u0648\u0627\u0644\u064a\u0642"
    ],
    "name:ara_x_variant":[
        "\u0634\u0648\u0627\u0644\u064a\u0642"
    ],
    "name:und_x_variant":[
        "Ech Chaoual\u00eeq",
        "Choualiq",
        "Shaw\u0101l\u012bq",
        "Chou\u00e2l\u00eeq",
        "Ash Shaw\u0101l\u012bq"
    ],
    "wof:name":"Choualiq",
    "wof:placetype":"locality"
},
  "geometry": {"coordinates":[35.43933,33.55504000000001],"type":"Point"}
}