{
  "type": "Feature",
  "properties": {
    "gn:admin1_code":"9.0",
    "gn:asciiname":"Qnat",
    "gn:country_code":"LB",
    "gn:dem":1137,
    "gn:feature_class":"P",
    "gn:feature_code":"PPL",
    "gn:name":"Qn\u00e2t",
    "gn:population":0,
    "gn:timezone":"Asia/Beirut",
    "iso:country":"LB",
    "name:ara_x_preferred":[
        "\u0642\u0646\u0627\u062a"
    ],
    "name:und_x_variant":[
        "Qn\u0101t",
        "Qn\u00e2t",
        "Qan\u0101t"
    ],
    "wof:name":"Qnat",
    "wof:placetype":"locality"
},
  "geometry": {"coordinates":[35.89444,34.25333],"type":"Point"}
}