{
  "type": "Feature",
  "properties": {
    "gn:admin1_code":"5.0",
    "gn:asciiname":"Mazraat en Nahr",
    "gn:country_code":"LB",
    "gn:dem":546,
    "gn:feature_class":"P",
    "gn:feature_code":"PPL",
    "gn:name":"Mazraat en Nahr",
    "gn:population":0,
    "gn:timezone":"Asia/Beirut",
    "iso:country":"LB",
    "name:ara_x_preferred":[
        "\u0645\u0632\u0631\u0639\u0629 \u0627\u0644\u0646\u0647\u0631"
    ],
    "name:und_x_variant":[
        "Mazra\u2018at an Nahr",
        "Mazraat en Nahr"
    ],
    "wof:name":"Mazraat en Nahr",
    "wof:placetype":"locality"
},
  "geometry": {"coordinates":[35.645,33.75083],"type":"Point"}
}