{
  "type": "Feature",
  "properties": {
    "gn:admin1_code":"5.0",
    "gn:asciiname":"Dmit ej Jouaniye",
    "gn:country_code":"LB",
    "gn:dem":446,
    "gn:feature_class":"P",
    "gn:feature_code":"PPL",
    "gn:name":"Dm\u00eet ej Jou\u00e2n\u00eey\u00e9",
    "gn:population":0,
    "gn:timezone":"Asia/Beirut",
    "iso:country":"LB",
    "name:ara_x_preferred":[
        "\u062f\u0645\u064a\u062a \u0627\u0644\u062c\u0648\u0627\u0646\u064a\u0629"
    ],
    "name:und_x_variant":[
        "Dimet",
        "Dm\u00eete",
        "Dmeet",
        "Dm\u012bt al Jaww\u0101n\u012byah",
        "Dm\u00eet ej Jou\u00e2n\u00eey\u00e9"
    ],
    "wof:name":"Dmit ej Jouaniye",
    "wof:placetype":"locality"
},
  "geometry": {"coordinates":[35.50917000000001,33.69333],"type":"Point"}
}