{
  "type": "Feature",
  "properties": {
    "gn:admin1_code":"7.0",
    "gn:asciiname":"Es Salhani",
    "gn:country_code":"LB",
    "gn:dem":626,
    "gn:feature_class":"P",
    "gn:feature_code":"PPL",
    "gn:name":"Es S\u00e2lh\u00e2ni",
    "gn:population":0,
    "gn:timezone":"Asia/Beirut",
    "iso:country":"LB",
    "name:ara_x_preferred":[
        "\u0635\u0627\u0644\u062d\u0627\u0646\u064a"
    ],
    "name:ara_x_variant":[
        "\u0627\u0644\u0635\u0627\u0644\u062d\u0627\u0646\u064a"
    ],
    "name:und_x_variant":[
        "A\u015f \u015e\u0101li\u1e29\u0101n\u012b",
        "Es S\u00e2lh\u00e2ni",
        "\u015e\u0101li\u1e29\u0101n\u012b"
    ],
    "wof:name":"Es Salhani",
    "wof:placetype":"locality"
},
  "geometry": {"coordinates":[35.30345,33.1289],"type":"Point"}
}