{
  "type": "Feature",
  "properties": {
    "gn:admin1_code":"9.0",
    "gn:asciiname":"Faqous",
    "gn:country_code":"LB",
    "gn:dem":742,
    "gn:feature_class":"P",
    "gn:feature_code":"PPL",
    "gn:name":"F\u00e2qo\u00fbs",
    "gn:population":0,
    "gn:timezone":"Asia/Beirut",
    "iso:country":"LB",
    "name:und_x_variant":[
        "F\u0101q\u016bs",
        "F\u00e2qo\u00fbs"
    ],
    "wof:name":"Faqous",
    "wof:placetype":"locality"
},
  "geometry": {"coordinates":[35.97333,34.38778],"type":"Point"}
}