{
  "type": "Feature",
  "properties": {
    "gn:admin1_code":"5.0",
    "gn:asciiname":"Ech Chaouiye",
    "gn:country_code":"LB",
    "gn:dem":1336,
    "gn:feature_class":"P",
    "gn:feature_code":"PPL",
    "gn:name":"Ech Ch\u00e2ouiy\u00e9",
    "gn:population":0,
    "gn:timezone":"Asia/Beirut",
    "iso:country":"LB",
    "name:und_x_variant":[
        "Ash Sh\u0101wiyah",
        "Ech Ch\u00e2ouiy\u00e9"
    ],
    "wof:name":"Ech Chaouiye",
    "wof:placetype":"locality"
},
  "geometry": {"coordinates":[35.81194,34.01639],"type":"Point"}
}