{
  "type": "Feature",
  "properties": {
    "gn:admin1_code":"5.0",
    "gn:asciiname":"El Mahatta",
    "gn:country_code":"LB",
    "gn:dem":24,
    "gn:feature_class":"P",
    "gn:feature_code":"PPL",
    "gn:name":"El Mahatta",
    "gn:population":0,
    "gn:timezone":"Asia/Beirut",
    "iso:country":"LB",
    "name:und_x_variant":[
        "Al Ma\u1e29a\u0163\u0163ah",
        "El Mahatta"
    ],
    "wof:name":"El Mahatta",
    "wof:placetype":"locality"
},
  "geometry": {"coordinates":[35.64583,34.00333],"type":"Point"}
}