{
  "type": "Feature",
  "properties": {
    "gn:admin1_code":"5.0",
    "gn:asciiname":"El Marji",
    "gn:country_code":"LB",
    "gn:dem":785,
    "gn:feature_class":"P",
    "gn:feature_code":"PPL",
    "gn:name":"El Marji",
    "gn:population":0,
    "gn:timezone":"Asia/Beirut",
    "iso:country":"LB",
    "name:und_x_variant":[
        "Al Marj\u012b",
        "El Marji"
    ],
    "wof:name":"El Marji",
    "wof:placetype":"locality"
},
  "geometry": {"coordinates":[35.70333,34.06722],"type":"Point"}
}