{
  "type": "Feature",
  "properties": {
    "gn:admin1_code":"10.0",
    "gn:asciiname":"Beit el Haj",
    "gn:country_code":"LB",
    "gn:dem":141,
    "gn:feature_class":"P",
    "gn:feature_code":"PPL",
    "gn:name":"Be\u00eft el H\u00e2j",
    "gn:population":0,
    "gn:timezone":"Asia/Beirut",
    "iso:country":"LB",
    "name:und_x_variant":[
        "Beit Hajj",
        "Bayt \u1e28\u0101jj",
        "Be\u00eft el Hajj",
        "Bayt al \u1e28\u0101jj",
        "Be\u00eft el H\u00e2j"
    ],
    "wof:name":"Beit el Haj",
    "wof:placetype":"locality"
},
  "geometry": {"coordinates":[36.10611,34.55917],"type":"Point"}
}