{
  "type": "Feature",
  "properties": {
    "gn:admin1_code":"6.0",
    "gn:asciiname":"Aamrane",
    "gn:country_code":"LB",
    "gn:dem":133,
    "gn:feature_class":"P",
    "gn:feature_code":"PPL",
    "gn:name":"Aamrane",
    "gn:population":0,
    "gn:timezone":"Asia/Beirut",
    "iso:country":"LB",
    "name:ara_x_preferred":[
        "\u0639\u0645\u0631\u0627\u0646"
    ],
    "name:ara_x_variant":[
        "\u2018Amr\u0101n"
    ],
    "wof:name":"Aamrane",
    "wof:placetype":"locality"
},
  "geometry": {"coordinates":[35.23888,33.1946],"type":"Point"}
}