{
  "type": "Feature",
  "properties": {
    "gn:admin1_code":"5.0",
    "gn:asciiname":"Haret Baasir",
    "gn:country_code":"LB",
    "gn:dem":366,
    "gn:feature_class":"P",
    "gn:feature_code":"PPL",
    "gn:name":"Haret Baasir",
    "gn:population":0,
    "gn:timezone":"Asia/Beirut",
    "iso:country":"LB",
    "wof:name":"Haret Baasir",
    "wof:placetype":"locality"
},
  "geometry": {"coordinates":[35.44844000000001,33.6635],"type":"Point"}
}