{
  "type": "Feature",
  "properties": {
    "iso:country":"LB",
    "name:ara_x_preferred":[
        "\u0639\u064a\u0646 \u0627\u0644\u062a\u064a\u0646\u0629"
    ],
    "name:eng_x_preferred":[
        "Ain At Tina"
    ],
    "qs:gn_pop":0,
    "qs:name":"\u0639\u064a\u0646 \u0627\u0644\u062a\u064a\u0646\u0629",
    "qs:name_adm0":"\u0644\u0628\u0646\u0627\u0646",
    "qs:name_adm1":"\u0628\u064a\u0631\u0648\u062a",
    "qs:photos":6,
    "qs:photos_1k":1,
    "qs:photos_9k":1,
    "qs:photos_9r":1,
    "qs:photos_all":6,
    "qs:photos_sr":1,
    "qs:placetype":"Suburb",
    "qs:pop_sr":"0",
    "qs:woe_adm0":23424873,
    "wof:name":"Ain At Tina",
    "wof:placetype":"neighbourhood"
},
  "geometry": {"coordinates":[35.479255,33.886596],"type":"Point"}
}