{
  "type": "Feature",
  "properties": {
    "gn:admin1_code":"10.0",
    "gn:asciiname":"Mar Touma",
    "gn:country_code":"LB",
    "gn:dem":179,
    "gn:feature_class":"P",
    "gn:feature_code":"PPL",
    "gn:name":"M\u00e2r To\u00fbma",
    "gn:population":0,
    "gn:timezone":"Asia/Beirut",
    "iso:country":"LB",
    "name:und_x_variant":[
        "M\u0101r T\u016bm\u0101",
        "M\u00e2r To\u00fbma"
    ],
    "wof:name":"Mar Touma",
    "wof:placetype":"locality"
},
  "geometry": {"coordinates":[36.02806,34.51222],"type":"Point"}
}