{
  "type": "Feature",
  "properties": {
    "gn:admin1_code":"5.0",
    "gn:asciiname":"Greater Beirut Area",
    "gn:country_code":"LB",
    "gn:dem":120,
    "gn:feature_class":"P",
    "gn:feature_code":"PPLL",
    "gn:name":"Greater Beirut Area",
    "gn:population":0,
    "gn:timezone":"Asia/Beirut",
    "iso:country":"LB",
    "wof:name":"Greater Beirut Area",
    "wof:placetype":"locality"
},
  "geometry": {"coordinates":[35.55694000000001,33.84778],"type":"Point"}
}