{
  "type": "Feature",
  "properties": {
    "gn:admin1_code":"6.0",
    "gn:asciiname":"Er Rachidiye",
    "gn:country_code":"LB",
    "gn:dem":16,
    "gn:feature_class":"P",
    "gn:feature_code":"PPL",
    "gn:name":"Er Rach\u00eed\u00eey\u00e9",
    "gn:population":0,
    "gn:timezone":"Asia/Beirut",
    "iso:country":"LB",
    "name:ara_x_preferred":[
        "\u0627\u0644\u0631\u0627\u0634\u062f\u064a\u0629"
    ],
    "name:ara_x_variant":[
        "\u0627\u0644\u0631\u0634\u064a\u062f\u064a\u0651\u0629"
    ],
    "name:und_x_variant":[
        "Ar Rushayd\u012byah",
        "Er-Rashadiyah",
        "Er Rusheidiye",
        "Ar Rash\u012bd\u012byah",
        "Er Rach\u00eed\u00eey\u00e9",
        "Ar R\u0101shid\u012byah"
    ],
    "wof:name":"Er Rachidiye",
    "wof:placetype":"locality"
},
  "geometry": {"coordinates":[35.21725,33.23692],"type":"Point"}
}