{
  "type": "Feature",
  "properties": {
    "gn:admin1_code":"9.0",
    "gn:asciiname":"Kfar Habou",
    "gn:country_code":"LB",
    "gn:dem":286,
    "gn:feature_class":"P",
    "gn:feature_code":"PPL",
    "gn:name":"Kfar Habou",
    "gn:population":0,
    "gn:timezone":"Asia/Beirut",
    "iso:country":"LB",
    "wof:name":"Kfar Habou",
    "wof:placetype":"locality"
},
  "geometry": {"coordinates":[35.95947,34.41445],"type":"Point"}
}