{
  "type": "Feature",
  "properties": {
    "gn:admin1_code":"9.0",
    "gn:asciiname":"Sakhra",
    "gn:country_code":"LB",
    "gn:dem":287,
    "gn:feature_class":"P",
    "gn:feature_code":"PPL",
    "gn:name":"Sakhra",
    "gn:population":0,
    "gn:timezone":"Asia/Beirut",
    "iso:country":"LB",
    "name:ara_x_preferred":[
        "\u0635\u062e\u0631\u0629"
    ],
    "name:ara_x_variant":[
        "\u0642\u0631\u064a\u0629 \u0635\u062e\u0631"
    ],
    "name:und_x_variant":[
        "\u015eakhrah",
        "Sakhra",
        "Qaryat Sakhr"
    ],
    "wof:name":"Sakhra",
    "wof:placetype":"locality"
},
  "geometry": {"coordinates":[35.92019000000001,34.36043],"type":"Point"}
}