{
  "type": "Feature",
  "properties": {
    "gn:admin1_code":"5.0",
    "gn:asciiname":"Zouq Mosbeh",
    "gn:country_code":"LB",
    "gn:dem":208,
    "gn:feature_class":"P",
    "gn:feature_code":"PPL",
    "gn:name":"Zouq Mosbeh",
    "gn:population":0,
    "gn:timezone":"Asia/Beirut",
    "iso:country":"LB",
    "name:und_x_variant":[
        "Z\u016bq Mu\u015fbi\u1e29",
        "Zouq Mosbeh",
        "Zouk Mosbeh"
    ],
    "wof:name":"Zouq Mosbeh",
    "wof:placetype":"locality"
},
  "geometry": {"coordinates":[35.62,33.95667],"type":"Point"}
}