{
  "type": "Feature",
  "properties": {
    "gn:admin1_code":"5.0",
    "gn:asciiname":"Lehfed",
    "gn:country_code":"LB",
    "gn:dem":986,
    "gn:feature_class":"P",
    "gn:feature_code":"PPL",
    "gn:name":"Lehfed",
    "gn:population":0,
    "gn:timezone":"Asia/Beirut",
    "iso:country":"LB",
    "name:ara_x_preferred":[
        "\u0644\u062d\u0641\u062f"
    ],
    "name:ita_x_preferred":[
        "Lehfed"
    ],
    "name:und_x_variant":[
        "Li\u1e29fid",
        "Lehfed"
    ],
    "wof:name":"Lehfed",
    "wof:placetype":"locality"
},
  "geometry": {"coordinates":[35.7775,34.16472],"type":"Point"}
}