{
  "type": "Feature",
  "properties": {
    "gn:admin1_code":"5.0",
    "gn:asciiname":"Falouqha",
    "gn:country_code":"LB",
    "gn:dem":1229,
    "gn:feature_class":"P",
    "gn:feature_code":"PPL",
    "gn:name":"F\u00e2lo\u00fbqha",
    "gn:population":0,
    "gn:timezone":"Asia/Beirut",
    "iso:country":"LB",
    "name:ara_x_preferred":[
        "\u0641\u0627\u0644\u0648\u063a\u0627"
    ],
    "name:und_x_variant":[
        "Falourha",
        "Felugha",
        "F\u0101l\u016bgh\u0101",
        "F\u00e2lo\u00fbqha"
    ],
    "wof:name":"Falouqha",
    "wof:placetype":"locality"
},
  "geometry": {"coordinates":[35.74082999999999,33.83778],"type":"Point"}
}