{
  "type": "Feature",
  "properties": {
    "gn:admin1_code":"6.0",
    "gn:asciiname":"Mazraat Tibna",
    "gn:country_code":"LB",
    "gn:dem":183,
    "gn:feature_class":"P",
    "gn:feature_code":"PPL",
    "gn:name":"Mazraat Tibn\u00e2",
    "gn:population":0,
    "gn:timezone":"Asia/Beirut",
    "iso:country":"LB",
    "name:ara_x_preferred":[
        "\u0645\u0632\u0631\u0639\u0629 \u062a\u0628\u0646\u0627"
    ],
    "name:und_x_variant":[
        "Mazra\u2018at Tibn\u0101",
        "Mazraat Tibn\u00e2"
    ],
    "wof:name":"Mazraat Tibna",
    "wof:placetype":"locality"
},
  "geometry": {"coordinates":[35.33815,33.44528],"type":"Point"}
}