{
  "type": "Feature",
  "properties": {
    "gn:admin1_code":"9.0",
    "gn:asciiname":"Aaoura",
    "gn:country_code":"LB",
    "gn:dem":686,
    "gn:feature_class":"P",
    "gn:feature_code":"PPL",
    "gn:name":"Aaoura",
    "gn:population":0,
    "gn:timezone":"Asia/Beirut",
    "iso:country":"LB",
    "name:ara_x_preferred":[
        "\u0639\u0648\u0631\u0629"
    ],
    "name:und_x_variant":[
        "\u2018Awrah",
        "Aaoura"
    ],
    "wof:name":"Aaoura",
    "wof:placetype":"locality"
},
  "geometry": {"coordinates":[35.80315,34.23595],"type":"Point"}
}