{
  "type": "Feature",
  "properties": {
    "gn:admin1_code":"11.0",
    "gn:asciiname":"Mrah Beit Aassaf",
    "gn:country_code":"LB",
    "gn:dem":1384,
    "gn:feature_class":"P",
    "gn:feature_code":"PPL",
    "gn:name":"Mr\u00e2h Be\u00eft Aass\u00e2f",
    "gn:population":0,
    "gn:timezone":"Asia/Beirut",
    "iso:country":"LB",
    "name:und_x_variant":[
        "Mar\u0101\u1e29 Bayt \u2018Ass\u0101f",
        "Mr\u00e2h Be\u00eft Aass\u00e2f"
    ],
    "wof:name":"Mrah Beit Aassaf",
    "wof:placetype":"locality"
},
  "geometry": {"coordinates":[36.02028,34.06361],"type":"Point"}
}