{
  "type": "Feature",
  "properties": {
    "gn:admin1_code":"11.0",
    "gn:asciiname":"Beit Chama",
    "gn:country_code":"LB",
    "gn:dem":1054,
    "gn:feature_class":"P",
    "gn:feature_code":"PPL",
    "gn:name":"Be\u00eft Ch\u00e2ma",
    "gn:population":0,
    "gn:timezone":"Asia/Beirut",
    "iso:country":"LB",
    "name:und_x_variant":[
        "Beit Shama",
        "Bayt Sh\u0101m\u0101",
        "Be\u00eft Ch\u00e2ma"
    ],
    "wof:name":"Beit Chama",
    "wof:placetype":"locality"
},
  "geometry": {"coordinates":[36.02306,33.92583],"type":"Point"}
}