{
  "type": "Feature",
  "properties": {
    "gn:admin1_code":"11.0",
    "gn:asciiname":"El Kharayeb",
    "gn:country_code":"LB",
    "gn:dem":949,
    "gn:feature_class":"P",
    "gn:feature_code":"PPL",
    "gn:name":"El Khar\u00e2yeb",
    "gn:population":0,
    "gn:timezone":"Asia/Beirut",
    "iso:country":"LB",
    "name:und_x_variant":[
        "Al Khar\u0101\u2019ib",
        "El Khar\u00e2yeb"
    ],
    "wof:name":"El Kharayeb",
    "wof:placetype":"locality"
},
  "geometry": {"coordinates":[36.30194,34.24056],"type":"Point"}
}