{
  "type": "Feature",
  "properties": {
    "gn:admin1_code":"5.0",
    "gn:asciiname":"Er Ramout",
    "gn:country_code":"LB",
    "gn:dem":545,
    "gn:feature_class":"P",
    "gn:feature_code":"PPL",
    "gn:name":"Er R\u00e2mo\u00fbt",
    "gn:population":0,
    "gn:timezone":"Asia/Beirut",
    "iso:country":"LB",
    "name:ara_x_preferred":[
        "\u0627\u0644\u0631\u0627\u0645\u0648\u0637"
    ],
    "name:und_x_variant":[
        "Er Fr\u00e2mo\u00fbte",
        "Ar R\u0101m\u016b\u0163",
        "Er R\u00e2mo\u00fbt"
    ],
    "wof:name":"Er Ramout",
    "wof:placetype":"locality"
},
  "geometry": {"coordinates":[35.71194000000001,34.16722],"type":"Point"}
}