{
  "type": "Feature",
  "properties": {
    "gn:admin1_code":"7.0",
    "gn:asciiname":"El Birke",
    "gn:country_code":"LB",
    "gn:dem":719,
    "gn:feature_class":"P",
    "gn:feature_code":"PPL",
    "gn:name":"El Birk\u00e9",
    "gn:population":0,
    "gn:timezone":"Asia/Beirut",
    "iso:country":"LB",
    "name:ara_x_preferred":[
        "\u0627\u0644\u0628\u0631\u0643\u0629"
    ],
    "name:und_x_variant":[
        "Al Birkah",
        "El Birk\u00e9"
    ],
    "wof:name":"El Birke",
    "wof:placetype":"locality"
},
  "geometry": {"coordinates":[35.43167000000001,33.11583],"type":"Point"}
}