{
  "type": "Feature",
  "properties": {
    "gn:admin1_code":"8.0",
    "gn:asciiname":"Hammara",
    "gn:country_code":"LB",
    "gn:dem":1173,
    "gn:feature_class":"P",
    "gn:feature_code":"PPL",
    "gn:name":"Hamm\u00e2ra",
    "gn:population":0,
    "gn:timezone":"Asia/Beirut",
    "iso:country":"LB",
    "name:ara_x_preferred":[
        "\u062d\u0645\u0651\u0627\u0631\u0629"
    ],
    "name:und_x_variant":[
        "\u1e28amm\u0101rah",
        "Hamm\u00e2ra"
    ],
    "wof:name":"Hammara",
    "wof:placetype":"locality"
},
  "geometry": {"coordinates":[35.88639000000001,33.64861],"type":"Point"}
}