{
  "type": "Feature",
  "properties": {
    "gn:admin1_code":"5.0",
    "gn:asciiname":"Ghbale",
    "gn:country_code":"LB",
    "gn:dem":871,
    "gn:feature_class":"P",
    "gn:feature_code":"PPL",
    "gn:name":"Ghb\u00e2l\u00e9",
    "gn:population":0,
    "gn:timezone":"Asia/Beirut",
    "iso:country":"LB",
    "name:ara_x_preferred":[
        "\u063a\u0628\u0627\u0644\u0629"
    ],
    "name:und_x_variant":[
        "Ghebale",
        "Ghbalah",
        "Ghib\u0101lah",
        "Ghb\u00e2l\u00e9"
    ],
    "wof:name":"Ghbale",
    "wof:placetype":"locality"
},
  "geometry": {"coordinates":[35.72056,34.05389],"type":"Point"}
}