{
  "type": "Feature",
  "properties": {
    "gn:admin1_code":"5.0",
    "gn:asciiname":"El Mghaissel",
    "gn:country_code":"LB",
    "gn:dem":1329,
    "gn:feature_class":"P",
    "gn:feature_code":"PPL",
    "gn:name":"El Mgha\u00efssel",
    "gn:population":0,
    "gn:timezone":"Asia/Beirut",
    "iso:country":"LB",
    "name:und_x_variant":[
        "Al Mughaysil",
        "El Mgha\u00efssel"
    ],
    "wof:name":"El Mghaissel",
    "wof:placetype":"locality"
},
  "geometry": {"coordinates":[35.76,34.02417],"type":"Point"}
}