{
  "type": "Feature",
  "properties": {
    "gn:admin1_code":"6.0",
    "gn:asciiname":"Saddiqine",
    "gn:country_code":"LB",
    "gn:dem":386,
    "gn:feature_class":"P",
    "gn:feature_code":"PPL",
    "gn:name":"Sadd\u00eeq\u00eene",
    "gn:population":0,
    "gn:timezone":"Asia/Beirut",
    "iso:country":"LB",
    "name:ara_x_preferred":[
        "\u0635\u062f\u064a\u0642\u064a\u0646"
    ],
    "name:und_x_variant":[
        "A\u015f \u015eidd\u012bq\u012bn",
        "Sadd\u00eeq\u00eene",
        "\u015eidd\u012bqayn",
        "\u015eidd\u012bq\u012bn"
    ],
    "wof:name":"Saddiqine",
    "wof:placetype":"locality"
},
  "geometry": {"coordinates":[35.31055999999999,33.19056],"type":"Point"}
}