{
  "type": "Feature",
  "properties": {
    "gn:admin1_code":"5.0",
    "gn:asciiname":"Hosn Aar",
    "gn:country_code":"LB",
    "gn:dem":892,
    "gn:feature_class":"P",
    "gn:feature_code":"PPL",
    "gn:name":"Hosn A\u00e2r",
    "gn:population":0,
    "gn:timezone":"Asia/Beirut",
    "iso:country":"LB",
    "name:ara_x_preferred":[
        "\u062d\u0635\u0646 \u0639\u0627\u0631"
    ],
    "name:und_x_variant":[
        "\u1e28i\u015fn \u2018\u0100r",
        "Hosn A\u00e2r"
    ],
    "wof:name":"Hosn Aar",
    "wof:placetype":"locality"
},
  "geometry": {"coordinates":[35.72952,34.14477],"type":"Point"}
}