{
  "type": "Feature",
  "properties": {
    "gn:admin1_code":"10.0",
    "gn:asciiname":"Dahr el Houssein",
    "gn:country_code":"LB",
    "gn:dem":126,
    "gn:feature_class":"P",
    "gn:feature_code":"PPL",
    "gn:name":"Dahr el Housse\u00efn",
    "gn:population":0,
    "gn:timezone":"Asia/Beirut",
    "iso:country":"LB",
    "name:ara_x_preferred":[
        "\u0636\u0647\u0631 \u0627\u0644\u062d\u0633\u064a\u0646"
    ],
    "name:und_x_variant":[
        "Dahr el Housse\u00efn",
        "\u1e10ahr al \u1e28usayn"
    ],
    "wof:name":"Dahr el Houssein",
    "wof:placetype":"locality"
},
  "geometry": {"coordinates":[35.99133,34.45385],"type":"Point"}
}