{
  "type": "Feature",
  "properties": {
    "gn:admin1_code":"5.0",
    "gn:asciiname":"El Maaniye",
    "gn:country_code":"LB",
    "gn:dem":387,
    "gn:feature_class":"P",
    "gn:feature_code":"PPL",
    "gn:name":"El Maan\u00eey\u00e9",
    "gn:population":0,
    "gn:timezone":"Asia/Beirut",
    "iso:country":"LB",
    "name:ara_x_preferred":[
        "\u0645\u0639\u0646\u064a\u0629"
    ],
    "name:und_x_variant":[
        "Al Ma\u2018n\u012byah",
        "El Maan\u00eey\u00e9",
        "Ma\u2018n\u012byah"
    ],
    "wof:name":"El Maaniye",
    "wof:placetype":"locality"
},
  "geometry": {"coordinates":[35.44827,33.63087],"type":"Point"}
}