{
  "type": "Feature",
  "properties": {
    "gn:admin1_code":"5.0",
    "gn:asciiname":"Hriq el Kfour",
    "gn:country_code":"LB",
    "gn:dem":815,
    "gn:feature_class":"P",
    "gn:feature_code":"PPL",
    "gn:name":"Hr\u00eeq el Kfo\u00fbr",
    "gn:population":0,
    "gn:timezone":"Asia/Beirut",
    "iso:country":"LB",
    "name:ara_x_preferred":[
        "\u062d\u0631\u064a\u0642 \u0627\u0644\u0643\u0641\u0648\u0631"
    ],
    "name:ara_x_variant":[
        "Al Kuf\u016br",
        "\u0627\u0644\u0643\u0641\u0648\u0631"
    ],
    "name:und_x_variant":[
        "\u1e28ar\u012bq al Kuf\u016br",
        "Hr\u00eeq el Kfo\u00fbr"
    ],
    "wof:name":"Hriq el Kfour",
    "wof:placetype":"locality"
},
  "geometry": {"coordinates":[35.69556,34.03361],"type":"Point"}
}