{
  "type": "Feature",
  "properties": {
    "gn:admin1_code":"10.0",
    "gn:asciiname":"Bezbina",
    "gn:country_code":"LB",
    "gn:dem":680,
    "gn:feature_class":"P",
    "gn:feature_code":"PPL",
    "gn:name":"Bezbina",
    "gn:population":0,
    "gn:timezone":"Asia/Beirut",
    "iso:country":"LB",
    "name:und_x_variant":[
        "Bazb\u00eena",
        "Bazbeena",
        "Bizb\u012bn\u0101",
        "Bezbina"
    ],
    "wof:name":"Bezbina",
    "wof:placetype":"locality"
},
  "geometry": {"coordinates":[36.19611,34.51528],"type":"Point"}
}