{
  "type": "Feature",
  "properties": {
    "gn:admin1_code":"11.0",
    "gn:asciiname":"Ouadi el Assouad",
    "gn:country_code":"LB",
    "gn:dem":1454,
    "gn:feature_class":"P",
    "gn:feature_code":"PPL",
    "gn:name":"Ou\u00e2di el Assouad",
    "gn:population":0,
    "gn:timezone":"Asia/Beirut",
    "iso:country":"LB",
    "name:und_x_variant":[
        "W\u0101d\u012b al Aswad",
        "Ou\u00e2di el Assouad"
    ],
    "wof:name":"Ouadi el Assouad",
    "wof:placetype":"locality"
},
  "geometry": {"coordinates":[35.99805999999999,34.04],"type":"Point"}
}