{
  "type": "Feature",
  "properties": {
    "gn:admin1_code":"9.0",
    "gn:asciiname":"Kfar Aaqqa",
    "gn:country_code":"LB",
    "gn:dem":357,
    "gn:feature_class":"P",
    "gn:feature_code":"PPL",
    "gn:name":"Kfar Aaqqa",
    "gn:population":0,
    "gn:timezone":"Asia/Beirut",
    "iso:country":"LB",
    "name:und_x_variant":[
        "Kafr `Aqq\u0101"
    ],
    "wof:name":"Kfar Aaqqa",
    "wof:placetype":"locality"
},
  "geometry": {"coordinates":[35.83722,34.30306],"type":"Point"}
}