{
  "type": "Feature",
  "properties": {
    "iso:country":"LB",
    "name:ara_x_preferred":[
        "\u0627\u0644\u0645\u064a\u0646\u0627\u0621"
    ],
    "name:eng_x_preferred":[
        "Al Mina"
    ],
    "qs:gn_pop":0,
    "qs:name":"\u0627\u0644\u0645\u064a\u0646\u0627\u0621",
    "qs:name_adm0":"\u0644\u0628\u0646\u0627\u0646",
    "qs:name_adm1":"\u0627\u0644\u0634\u0645\u0627\u0644",
    "qs:photos":222,
    "qs:photos_1k":45,
    "qs:photos_9k":1,
    "qs:photos_9r":4,
    "qs:photos_all":222,
    "qs:photos_sr":4,
    "qs:placetype":"Town",
    "qs:pop_sr":"0",
    "qs:woe_adm0":23424873,
    "wof:name":"Al Mina",
    "wof:placetype":"neighbourhood"
},
  "geometry": {"coordinates":[35.824871,34.439123],"type":"Point"}
}