{
  "type": "Feature",
  "properties": {
    "gn:admin1_code":"5.0",
    "gn:asciiname":"Naameh",
    "gn:country_code":"LB",
    "gn:dem":81,
    "gn:feature_class":"P",
    "gn:feature_code":"PPL",
    "gn:name":"Naameh",
    "gn:population":0,
    "gn:timezone":"Asia/Beirut",
    "iso:country":"LB",
    "wof:name":"Naameh",
    "wof:placetype":"locality"
},
  "geometry": {"coordinates":[35.4645,33.74508],"type":"Point"}
}