{
  "type": "Feature",
  "properties": {
    "gn:admin1_code":"9.0",
    "gn:asciiname":"Aardat",
    "gn:country_code":"LB",
    "gn:dem":122,
    "gn:feature_class":"P",
    "gn:feature_code":"PPL",
    "gn:name":"Aard\u00e2t",
    "gn:population":0,
    "gn:timezone":"Asia/Beirut",
    "iso:country":"LB",
    "name:ara_x_preferred":[
        "\u0639\u0631\u062f\u0627\u062a"
    ],
    "name:ara_x_variant":[
        "\u2018Ard\u0101t"
    ],
    "name:und_x_variant":[
        "Aard\u00e2t"
    ],
    "wof:name":"Aardat",
    "wof:placetype":"locality"
},
  "geometry": {"coordinates":[35.88333,34.40861],"type":"Point"}
}