{
  "type": "Feature",
  "properties": {
    "gn:admin1_code":"5.0",
    "gn:asciiname":"El Maiyr",
    "gn:country_code":"LB",
    "gn:dem":631,
    "gn:feature_class":"P",
    "gn:feature_code":"PPL",
    "gn:name":"El Ma\u00efyr",
    "gn:population":0,
    "gn:timezone":"Asia/Beirut",
    "iso:country":"LB",
    "wof:name":"El Maiyr",
    "wof:placetype":"locality"
},
  "geometry": {"coordinates":[35.67111,33.93444],"type":"Point"}
}