{
  "type": "Feature",
  "properties": {
    "gn:admin1_code":"10.0",
    "gn:asciiname":"El Qlaiaat",
    "gn:country_code":"LB",
    "gn:dem":25,
    "gn:feature_class":"P",
    "gn:feature_code":"PPL",
    "gn:name":"El Qla\u00efa\u00e2t",
    "gn:population":0,
    "gn:timezone":"Asia/Beirut",
    "iso:country":"LB",
    "name:und_x_variant":[
        "El-Qlei\u2018at",
        "El Kulat",
        "El Haut",
        "Al Qulay\u2018\u0101t",
        "El Qla\u00efa\u00e2t"
    ],
    "wof:name":"El Qlaiaat",
    "wof:placetype":"locality"
},
  "geometry": {"coordinates":[36.01667,34.58222],"type":"Point"}
}