{
  "type": "Feature",
  "properties": {
    "gn:admin1_code":"5.0",
    "gn:asciiname":"El Qhaf",
    "gn:country_code":"LB",
    "gn:dem":1827,
    "gn:feature_class":"P",
    "gn:feature_code":"PPL",
    "gn:name":"El Qh\u00e2f",
    "gn:population":0,
    "gn:timezone":"Asia/Beirut",
    "iso:country":"LB",
    "name:und_x_variant":[
        "Al A\u1e29q\u0101f",
        "El Qh\u00e2f"
    ],
    "wof:name":"El Qhaf",
    "wof:placetype":"locality"
},
  "geometry": {"coordinates":[35.88972000000001,34.16417],"type":"Point"}
}