{
  "type": "Feature",
  "properties": {
    "gn:admin1_code":"10.0",
    "gn:asciiname":"Ilat",
    "gn:country_code":"LB",
    "gn:dem":391,
    "gn:feature_class":"P",
    "gn:feature_code":"PPL",
    "gn:name":"Il\u00e2t",
    "gn:population":0,
    "gn:timezone":"Asia/Beirut",
    "iso:country":"LB",
    "name:und_x_variant":[
        "Aay\u00e2te",
        "Eelat",
        "Il\u00e2t"
    ],
    "wof:name":"Ilat",
    "wof:placetype":"locality"
},
  "geometry": {"coordinates":[36.10972,34.51917],"type":"Point"}
}