{
  "type": "Feature",
  "properties": {
    "gn:admin1_code":"6.0",
    "gn:asciiname":"Kfar Beit",
    "gn:country_code":"LB",
    "gn:dem":417,
    "gn:feature_class":"P",
    "gn:feature_code":"PPL",
    "gn:name":"Kfar Be\u00eft",
    "gn:population":0,
    "gn:timezone":"Asia/Beirut",
    "iso:country":"LB",
    "name:ara_x_preferred":[
        "\u0643\u0641\u0631 \u0628\u064a\u062a"
    ],
    "name:und_x_variant":[
        "Kafr Bayt",
        "Kfar Be\u00eft"
    ],
    "wof:name":"Kfar Beit",
    "wof:placetype":"locality"
},
  "geometry": {"coordinates":[35.46184,33.49738],"type":"Point"}
}