{
  "type": "Feature",
  "properties": {
    "gn:admin1_code":"10.0",
    "gn:asciiname":"Dinbou",
    "gn:country_code":"LB",
    "gn:dem":599,
    "gn:feature_class":"P",
    "gn:feature_code":"PPL",
    "gn:name":"Dinbou",
    "gn:population":0,
    "gn:timezone":"Asia/Beirut",
    "iso:country":"LB",
    "name:und_x_variant":[
        "Dennbou",
        "Dinnbo",
        "Danb\u016b",
        "Dinbou"
    ],
    "wof:name":"Dinbou",
    "wof:placetype":"locality"
},
  "geometry": {"coordinates":[36.08778,34.47889],"type":"Point"}
}