{
  "type": "Feature",
  "properties": {
    "gn:admin1_code":"5.0",
    "gn:asciiname":"Baqaata",
    "gn:country_code":"LB",
    "gn:dem":922,
    "gn:feature_class":"P",
    "gn:feature_code":"PPL",
    "gn:name":"Baq\u00e2ata",
    "gn:population":0,
    "gn:timezone":"Asia/Beirut",
    "iso:country":"LB",
    "name:ara_x_preferred":[
        "\u0628\u0642\u0639\u0627\u062a\u0627"
    ],
    "name:und_x_variant":[
        "Buq\u2018\u0101t\u0101",
        "Baq\u00e2ata"
    ],
    "wof:name":"Baqaata",
    "wof:placetype":"locality"
},
  "geometry": {"coordinates":[35.59889000000001,33.67028],"type":"Point"}
}