{
  "type": "Feature",
  "properties": {
    "gn:admin1_code":"5.0",
    "gn:asciiname":"Ech Chahout",
    "gn:country_code":"LB",
    "gn:dem":721,
    "gn:feature_class":"P",
    "gn:feature_code":"PPL",
    "gn:name":"Ech Ch\u00e2ho\u00fbt",
    "gn:population":0,
    "gn:timezone":"Asia/Beirut",
    "iso:country":"LB",
    "name:und_x_variant":[
        "Ash Sh\u0101\u1e29\u016b\u0163",
        "Ech Ch\u00e2ho\u00fbt"
    ],
    "wof:name":"Ech Chahout",
    "wof:placetype":"locality"
},
  "geometry": {"coordinates":[35.69444,34.00806],"type":"Point"}
}