{
  "type": "Feature",
  "properties": {
    "gn:admin1_code":"5.0",
    "gn:asciiname":"El Aarabe",
    "gn:country_code":"LB",
    "gn:dem":1119,
    "gn:feature_class":"P",
    "gn:feature_code":"PPL",
    "gn:name":"El Aar\u00e2b\u00e9",
    "gn:population":0,
    "gn:timezone":"Asia/Beirut",
    "iso:country":"LB",
    "wof:name":"El Aarabe",
    "wof:placetype":"locality"
},
  "geometry": {"coordinates":[35.82389000000001,34.18667],"type":"Point"}
}