{
  "type": "Feature",
  "properties": {
    "gn:admin1_code":"5.0",
    "gn:asciiname":"El Bahsa",
    "gn:country_code":"LB",
    "gn:dem":4,
    "gn:feature_class":"P",
    "gn:feature_code":"PPL",
    "gn:name":"El Bahsa",
    "gn:population":0,
    "gn:timezone":"Asia/Beirut",
    "iso:country":"LB",
    "name:und_x_variant":[
        "Al Ba\u1e29\u015fah",
        "El Bahsa"
    ],
    "wof:name":"El Bahsa",
    "wof:placetype":"locality"
},
  "geometry": {"coordinates":[35.64667,34.0775],"type":"Point"}
}