{
  "type": "Feature",
  "properties": {
    "gn:admin1_code":"8.0",
    "gn:asciiname":"El Qasr",
    "gn:country_code":"LB",
    "gn:dem":984,
    "gn:feature_class":"P",
    "gn:feature_code":"PPL",
    "gn:name":"El Qasr",
    "gn:population":0,
    "gn:timezone":"Asia/Beirut",
    "iso:country":"LB",
    "name:ara_x_preferred":[
        "\u0627\u0644\u0642\u0635\u0631"
    ],
    "name:und_x_variant":[
        "Al Qa\u015fr",
        "El Qasr"
    ],
    "wof:name":"El Qasr",
    "wof:placetype":"locality"
},
  "geometry": {"coordinates":[35.76417,33.71611],"type":"Point"}
}