{
  "type": "Feature",
  "properties": {
    "gn:admin1_code":"8.0",
    "gn:asciiname":"El Qasr",
    "gn:country_code":"LB",
    "gn:dem":984,
    "gn:feature_class":"P",
    "gn:feature_code":"PPL",
    "gn:name":"El Qasr",
    "gn:population":0,
    "gn:timezone":"Asia/Beirut",
    "iso:country":"LB",
    "name:ara_x_preferred":[
        "\u0627\u0644\u0642\u0635\u0631"
    ],
    "name:ben_x_preferred":[
        "\u098f\u09b2 \u0995\u09be\u09b8\u09b0"
    ],
    "name:deu_x_preferred":[
        "El Qasr"
    ],
    "name:ell_x_preferred":[
        "\u0395\u03bb \u039a\u03b1\u03c3\u03c1"
    ],
    "name:eng_x_preferred":[
        "El Qasr"
    ],
    "name:fas_x_preferred":[
        "\u0627\u0644\u0642\u0635\u0631"
    ],
    "name:fra_x_preferred":[
        "Al Qasr"
    ],
    "name:heb_x_preferred":[
        "\u05d0\u05dc \u05e7\u05d0\u05e1\u05e8"
    ],
    "name:hin_x_preferred":[
        "\u0905\u0932 \u0915\u093e\u0938\u094d\u0930"
    ],
    "name:hun_x_preferred":[
        "El Qasr"
    ],
    "name:ind_x_preferred":[
        "El Qasr"
    ],
    "name:ita_x_preferred":[
        "El Qasr"
    ],
    "name:jpn_x_preferred":[
        "\u30a8\u30eb\u30ab\u30b9\u30eb"
    ],
    "name:kor_x_preferred":[
        "\uc5d8 \uce74\uc2a4\ub974"
    ],
    "name:nld_x_preferred":[
        "El Qasr"
    ],
    "name:pol_x_preferred":[
        "El Qasr"
    ],
    "name:por_x_preferred":[
        "Al Qasr"
    ],
    "name:rus_x_preferred":[
        "\u042d\u043b\u044c -\u041a\u0430\u0441\u0440"
    ],
    "name:spa_x_preferred":[
        "El Qasr"
    ],
    "name:swe_x_preferred":[
        "El Qasr"
    ],
    "name:tur_x_preferred":[
        "El Qasr"
    ],
    "name:ukr_x_preferred":[
        "\u0415\u043b\u044c-\u041a\u0430\u0441\u0440"
    ],
    "name:und_x_variant":[
        "Al Qa\u015fr",
        "El Qasr"
    ],
    "name:urd_x_preferred":[
        "\u0627\u06cc\u0644 \u0642\u0635\u0631"
    ],
    "name:vie_x_preferred":[
        "El Qasr"
    ],
    "name:zho_cn_x_preferred":[
        "\u57c3\u5c14\u5361\u65af\u5c14"
    ],
    "name:zho_tw_x_preferred":[
        "\u57c3\u723e\u5361\u745f"
    ],
    "wof:name":"El Qasr",
    "wof:placetype":"locality"
},
  "geometry": {"coordinates":[35.76417,33.71611],"type":"Point"}
}