{
  "type": "Feature",
  "properties": {
    "gn:admin1_code":"5.0",
    "gn:asciiname":"Haret el Qadi",
    "gn:country_code":"LB",
    "gn:dem":1153,
    "gn:feature_class":"P",
    "gn:feature_code":"PPL",
    "gn:name":"H\u00e2ret el Q\u00e2di",
    "gn:population":0,
    "gn:timezone":"Asia/Beirut",
    "iso:country":"LB",
    "name:und_x_variant":[
        "\u1e28\u0101rat al Q\u0101\u1e11\u012b",
        "H\u00e2ret el Q\u00e2di"
    ],
    "wof:name":"Haret el Qadi",
    "wof:placetype":"locality"
},
  "geometry": {"coordinates":[35.88610999999999,34.10667],"type":"Point"}
}