{
  "type": "Feature",
  "properties": {
    "gn:admin1_code":"11.0",
    "gn:asciiname":"Hortaala",
    "gn:country_code":"LB",
    "gn:dem":1144,
    "gn:feature_class":"P",
    "gn:feature_code":"PPL",
    "gn:name":"Hortaala",
    "gn:population":0,
    "gn:timezone":"Asia/Beirut",
    "iso:country":"LB",
    "name:und_x_variant":[
        "Hortal\u00e9",
        "Haour Taala",
        "Hour Taila",
        "\u1e28awr Ta\u2018l\u0101",
        "Hortaala"
    ],
    "wof:name":"Hortaala",
    "wof:placetype":"locality"
},
  "geometry": {"coordinates":[36.14139,33.91806],"type":"Point"}
}