{
  "type": "Feature",
  "properties": {
    "gn:admin1_code":"5.0",
    "gn:asciiname":"El Bouaib",
    "gn:country_code":"LB",
    "gn:dem":873,
    "gn:feature_class":"P",
    "gn:feature_code":"PPL",
    "gn:name":"El Boua\u00efb",
    "gn:population":0,
    "gn:timezone":"Asia/Beirut",
    "iso:country":"LB",
    "name:und_x_variant":[
        "Al Buwayb",
        "El Boua\u00efb"
    ],
    "wof:name":"El Bouaib",
    "wof:placetype":"locality"
},
  "geometry": {"coordinates":[35.69583,33.96639],"type":"Point"}
}