{
  "type": "Feature",
  "properties": {
    "gn:admin1_code":"10.0",
    "gn:asciiname":"Qbaiyat",
    "gn:country_code":"LB",
    "gn:dem":544,
    "gn:feature_class":"P",
    "gn:feature_code":"PPL",
    "gn:name":"Qba\u00efyat",
    "gn:population":0,
    "gn:timezone":"Asia/Beirut",
    "iso:country":"LB",
    "name:und_x_variant":[
        "Al Qbayy\u0101t",
        "Qba\u00efyat"
    ],
    "wof:name":"Qbaiyat",
    "wof:placetype":"locality"
},
  "geometry": {"coordinates":[36.28111,34.57083],"type":"Point"}
}