{
  "type": "Feature",
  "properties": {
    "gn:admin1_code":"5.0",
    "gn:asciiname":"Raachine",
    "gn:country_code":"LB",
    "gn:dem":1284,
    "gn:feature_class":"P",
    "gn:feature_code":"PPL",
    "gn:name":"Raach\u00eene",
    "gn:population":0,
    "gn:timezone":"Asia/Beirut",
    "iso:country":"LB",
    "name:ara_x_preferred":[
        "\u0631\u0639\u0634\u064a\u0646"
    ],
    "name:und_x_variant":[
        "Ra\u2018sh\u012bn",
        "Raach\u00eene"
    ],
    "wof:name":"Raachine",
    "wof:placetype":"locality"
},
  "geometry": {"coordinates":[35.72002,34.01095],"type":"Point"}
}