{
  "type": "Feature",
  "properties": {
    "gn:admin1_code":"5.0",
    "gn:asciiname":"Rouaisset Qoubbeyaa",
    "gn:country_code":"LB",
    "gn:dem":1032,
    "gn:feature_class":"P",
    "gn:feature_code":"PPL",
    "gn:name":"Roua\u00efsset Qoubbeyaa",
    "gn:population":0,
    "gn:timezone":"Asia/Beirut",
    "iso:country":"LB",
    "name:ara_x_preferred":[
        "\u0631\u0648\u064a\u0633\u0629 \u0642\u0628\u064a\u0639"
    ],
    "name:und_x_variant":[
        "Ru\u2019aysat Qibbay\u2018",
        "Roua\u00efsset Qoubbeyaa",
        "Ruwaysat Qubbay\u2018"
    ],
    "wof:name":"Rouaisset Qoubbeyaa",
    "wof:placetype":"locality"
},
  "geometry": {"coordinates":[35.68917000000001,33.81083],"type":"Point"}
}