{
  "type": "Feature",
  "properties": {
    "gn:admin1_code":"9.0",
    "gn:asciiname":"Slaiyeb Bchaale",
    "gn:country_code":"LB",
    "gn:dem":1212,
    "gn:feature_class":"P",
    "gn:feature_code":"PPL",
    "gn:name":"Sla\u00efyeb Bchaal\u00e9",
    "gn:population":0,
    "gn:timezone":"Asia/Beirut",
    "iso:country":"LB",
    "name:ara_x_preferred":[
        "\u0635\u0644\u064a\u0628 \u0628\u0634\u0639\u0644\u0629"
    ],
    "name:ara_x_variant":[
        "\u0642\u0628\u064a\u0628\u0627\u062a"
    ],
    "name:und_x_variant":[
        "El Qbeibat",
        "Ba\u00efbate",
        "\u015eulayyib Bshi\u2018lah",
        "Sla\u00efyeb Bchaal\u00e9",
        "Qubayb\u0101t",
        "\u015eulayb Bisha\u2018lah"
    ],
    "wof:name":"Slaiyeb Bchaale",
    "wof:placetype":"locality"
},
  "geometry": {"coordinates":[35.8277,34.20493],"type":"Point"}
}