{
  "type": "Feature",
  "properties": {
    "gn:admin1_code":"6.0",
    "gn:asciiname":"Biout es Sayed",
    "gn:country_code":"LB",
    "gn:dem":46,
    "gn:feature_class":"P",
    "gn:feature_code":"PPL",
    "gn:name":"Biout es Sayed",
    "gn:population":0,
    "gn:timezone":"Asia/Beirut",
    "iso:country":"LB",
    "name:ara_x_preferred":[
        "\u0645\u0632\u0631\u0639\u0629 \u0628\u064a\u0648\u062a \u0627\u0644\u0633\u064a\u0627\u062f"
    ],
    "name:ara_x_variant":[
        "\u0628\u064a\u0648\u062a \u0627\u0644\u0633\u064a\u062f"
    ],
    "name:und_x_variant":[
        "Biyud es Seid",
        "Biout es-Seiyed",
        "Buy\u016bt as Sayyid",
        "Biout es Sayed",
        "Mazra\u2018at Buy\u016bt as Say\u0101d"
    ],
    "wof:name":"Biout es Sayed",
    "wof:placetype":"locality"
},
  "geometry": {"coordinates":[35.1925,33.16806],"type":"Point"}
}