{
  "type": "Feature",
  "properties": {
    "gn:admin1_code":"5.0",
    "gn:asciiname":"El Qarqfi",
    "gn:country_code":"LB",
    "gn:dem":43,
    "gn:feature_class":"P",
    "gn:feature_code":"PPL",
    "gn:name":"El Qarqfi",
    "gn:population":0,
    "gn:timezone":"Asia/Beirut",
    "iso:country":"LB",
    "name:und_x_variant":[
        "Bechta",
        "Al Qarf\u012b",
        "El Qarqfi"
    ],
    "wof:name":"El Qarqfi",
    "wof:placetype":"locality"
},
  "geometry": {"coordinates":[35.63778,34.15722],"type":"Point"}
}