{
  "type": "Feature",
  "properties": {
    "gn:admin1_code":"7.0",
    "gn:asciiname":"Bilone",
    "gn:country_code":"LB",
    "gn:dem":625,
    "gn:feature_class":"P",
    "gn:feature_code":"PPL",
    "gn:name":"Bil\u00f4ne",
    "gn:population":0,
    "gn:timezone":"Asia/Beirut",
    "iso:country":"LB",
    "name:ara_x_preferred":[
        "\u0628\u064a\u0644\u0648\u0646"
    ],
    "name:und_x_variant":[
        "Bil\u00f4ne",
        "B\u012bl\u016bn"
    ],
    "wof:name":"Bilone",
    "wof:placetype":"locality"
},
  "geometry": {"coordinates":[35.48889000000001,33.16667],"type":"Point"}
}