{
  "type": "Feature",
  "properties": {
    "gn:admin1_code":"7.0",
    "gn:asciiname":"Jbaa",
    "gn:country_code":"LB",
    "gn:dem":787,
    "gn:feature_class":"P",
    "gn:feature_code":"PPL",
    "gn:name":"Jb\u00e2a",
    "gn:population":0,
    "gn:timezone":"Asia/Beirut",
    "iso:country":"LB",
    "name:ara_x_preferred":[
        "\u062c\u0628\u0627\u0639"
    ],
    "name:fas_x_preferred":[
        "\u062c\u0628\u0627\u0639"
    ],
    "name:nno_x_preferred":[
        "Jbaa"
    ],
    "name:und_x_variant":[
        "Djebaa",
        "Jb\u0101\u2018",
        "Jab\u0101\u2018",
        "Jb\u00e2a"
    ],
    "wof:name":"Jbaa",
    "wof:placetype":"locality"
},
  "geometry": {"coordinates":[35.51806,33.48583],"type":"Point"}
}