{
  "type": "Feature",
  "properties": {
    "gn:admin1_code":"9.0",
    "gn:asciiname":"Ed Daiaa",
    "gn:country_code":"LB",
    "gn:dem":533,
    "gn:feature_class":"P",
    "gn:feature_code":"PPL",
    "gn:name":"Ed Da\u00efaa",
    "gn:population":0,
    "gn:timezone":"Asia/Beirut",
    "iso:country":"LB",
    "name:und_x_variant":[
        "A\u1e11 \u1e10ay\u2018ah",
        "Ed Da\u00efaa"
    ],
    "wof:name":"Ed Daiaa",
    "wof:placetype":"locality"
},
  "geometry": {"coordinates":[35.77667,34.23972],"type":"Point"}
}