{
  "type": "Feature",
  "properties": {
    "gn:admin1_code":"11.0",
    "gn:asciiname":"Mrah ech Chiaair",
    "gn:country_code":"LB",
    "gn:dem":1428,
    "gn:feature_class":"P",
    "gn:feature_code":"PPL",
    "gn:name":"Mr\u00e2h ech Chiaa\u00efr",
    "gn:population":0,
    "gn:timezone":"Asia/Beirut",
    "iso:country":"LB",
    "name:und_x_variant":[
        "Mar\u0101\u1e29 ash Sha\u2018\u012br",
        "Mr\u00e2h ech Chiaa\u00efr"
    ],
    "wof:name":"Mrah ech Chiaair",
    "wof:placetype":"locality"
},
  "geometry": {"coordinates":[36.13167,34.1725],"type":"Point"}
}