{
  "type": "Feature",
  "properties": {
    "gn:admin1_code":"5.0",
    "gn:asciiname":"Nammoura",
    "gn:country_code":"LB",
    "gn:dem":789,
    "gn:feature_class":"P",
    "gn:feature_code":"PPL",
    "gn:name":"Nammo\u00fbra",
    "gn:population":0,
    "gn:timezone":"Asia/Beirut",
    "iso:country":"LB",
    "name:und_x_variant":[
        "Namm\u016brah",
        "Nammo\u00fbra"
    ],
    "wof:name":"Nammoura",
    "wof:placetype":"locality"
},
  "geometry": {"coordinates":[35.67861,33.95778],"type":"Point"}
}