{
  "type": "Feature",
  "properties": {
    "gn:admin1_code":"9.0",
    "gn:asciiname":"Qraine",
    "gn:country_code":"LB",
    "gn:dem":719,
    "gn:feature_class":"P",
    "gn:feature_code":"PPL",
    "gn:name":"Qra\u00efne",
    "gn:population":0,
    "gn:timezone":"Asia/Beirut",
    "iso:country":"LB",
    "name:und_x_variant":[
        "Al Qurayn"
    ],
    "wof:name":"Qraine",
    "wof:placetype":"locality"
},
  "geometry": {"coordinates":[36.03139,34.40028],"type":"Point"}
}