{
  "type": "Feature",
  "properties": {
    "gn:admin1_code":"10.0",
    "gn:asciiname":"Dabadeb",
    "gn:country_code":"LB",
    "gn:dem":433,
    "gn:feature_class":"P",
    "gn:feature_code":"PPL",
    "gn:name":"Dabadeb",
    "gn:population":0,
    "gn:timezone":"Asia/Beirut",
    "iso:country":"LB",
    "wof:name":"Dabadeb",
    "wof:placetype":"locality"
},
  "geometry": {"coordinates":[36.38417000000001,34.61360999999999],"type":"Point"}
}