{
  "type": "Feature",
  "properties": {
    "gn:admin1_code":"5.0",
    "gn:asciiname":"Ouata el Mrouj",
    "gn:country_code":"LB",
    "gn:dem":1181,
    "gn:feature_class":"P",
    "gn:feature_code":"PPL",
    "gn:name":"Ouata el Mro\u00fbj",
    "gn:population":0,
    "gn:timezone":"Asia/Beirut",
    "iso:country":"LB",
    "name:ara_x_preferred":[
        "\u0648\u0637\u0649 \u0627\u0644\u0645\u0631\u0648\u062c"
    ],
    "name:und_x_variant":[
        "Wa\u0163\u0101\u2019 al Mur\u016bj",
        "Ouata el Mro\u00fbj",
        "Wa\u0163\u00e1 al Mur\u016bj"
    ],
    "wof:name":"Ouata el Mrouj",
    "wof:placetype":"locality"
},
  "geometry": {"coordinates":[35.745,33.90861],"type":"Point"}
}