{
  "type": "Feature",
  "properties": {
    "gn:admin1_code":"5.0",
    "gn:asciiname":"Rakti",
    "gn:country_code":"LB",
    "gn:dem":614,
    "gn:feature_class":"P",
    "gn:feature_code":"PPL",
    "gn:name":"Rakti",
    "gn:population":0,
    "gn:timezone":"Asia/Beirut",
    "iso:country":"LB",
    "name:jpn_x_preferred":[
        "\u30e9\u30af\u30c6\u30a3"
    ],
    "wof:name":"Rakti",
    "wof:placetype":"locality"
},
  "geometry": {"coordinates":[35.68917000000001,34.07333],"type":"Point"}
}