{
  "type": "Feature",
  "properties": {
    "gn:admin1_code":"11.0",
    "gn:asciiname":"Mrah Beit el Aabd",
    "gn:country_code":"LB",
    "gn:dem":1263,
    "gn:feature_class":"P",
    "gn:feature_code":"PPL",
    "gn:name":"Mr\u00e2h Be\u00eft el Aabd",
    "gn:population":0,
    "gn:timezone":"Asia/Beirut",
    "iso:country":"LB",
    "name:und_x_variant":[
        "Mar\u0101\u1e29 Bayt al \u2018Abd",
        "Mr\u00e2h Be\u00eft el Aabd"
    ],
    "wof:name":"Mrah Beit el Aabd",
    "wof:placetype":"locality"
},
  "geometry": {"coordinates":[36.33333,34.39417],"type":"Point"}
}