{
  "type": "Feature",
  "properties": {
    "gn:admin1_code":"6.0",
    "gn:asciiname":"Bmaryamine",
    "gn:country_code":"LB",
    "gn:dem":599,
    "gn:feature_class":"P",
    "gn:feature_code":"PPL",
    "gn:name":"Bmaryamine",
    "gn:population":0,
    "gn:timezone":"Asia/Beirut",
    "iso:country":"LB",
    "name:ara_x_preferred":[
        "\u0628\u0645\u0631\u064a\u0645\u064a\u0646"
    ],
    "name:und_x_variant":[
        "Bmaryam\u012bn",
        "Bmaryamine"
    ],
    "wof:name":"Bmaryamine",
    "wof:placetype":"locality"
},
  "geometry": {"coordinates":[35.29972,33.14889],"type":"Point"}
}