{
  "type": "Feature",
  "properties": {
    "gn:admin1_code":"11.0",
    "gn:asciiname":"Ouadi et Tourkmane",
    "gn:country_code":"LB",
    "gn:dem":1406,
    "gn:feature_class":"P",
    "gn:feature_code":"PPL",
    "gn:name":"Ou\u00e2di et Tourkm\u00e2ne",
    "gn:population":0,
    "gn:timezone":"Asia/Beirut",
    "iso:country":"LB",
    "name:und_x_variant":[
        "W\u0101d\u012b at Turkum\u0101n",
        "Ou\u00e2di et Tourkm\u00e2ne"
    ],
    "wof:name":"Ouadi et Tourkmane",
    "wof:placetype":"locality"
},
  "geometry": {"coordinates":[36.31917,34.37667],"type":"Point"}
}