{
  "type": "Feature",
  "properties": {
    "gn:admin1_code":"9.0",
    "gn:asciiname":"Salaa",
    "gn:country_code":"LB",
    "gn:dem":378,
    "gn:feature_class":"P",
    "gn:feature_code":"PPL",
    "gn:name":"Salaa",
    "gn:population":0,
    "gn:timezone":"Asia/Beirut",
    "iso:country":"LB",
    "name:und_x_variant":[
        "\u015eala\u2018ah",
        "Salaa"
    ],
    "wof:name":"Salaa",
    "wof:placetype":"locality"
},
  "geometry": {"coordinates":[35.72056,34.24444],"type":"Point"}
}