{
  "type": "Feature",
  "properties": {
    "gn:admin1_code":"7.0",
    "gn:asciiname":"Touline",
    "gn:country_code":"LB",
    "gn:dem":514,
    "gn:feature_class":"P",
    "gn:feature_code":"PPL",
    "gn:name":"To\u00fbl\u00eene",
    "gn:population":0,
    "gn:timezone":"Asia/Beirut",
    "iso:country":"LB",
    "name:ara_x_preferred":[
        "\u062a\u0648\u0644\u064a\u0646"
    ],
    "name:und_x_variant":[
        "T\u016bl\u012bn",
        "To\u00fbl\u00eene"
    ],
    "wof:name":"Touline",
    "wof:placetype":"locality"
},
  "geometry": {"coordinates":[35.43694,33.25],"type":"Point"}
}