{
  "type": "Feature",
  "properties": {
    "gn:admin1_code":"8.0",
    "gn:asciiname":"Saouiri",
    "gn:country_code":"LB",
    "gn:dem":1082,
    "gn:feature_class":"P",
    "gn:feature_code":"PPL",
    "gn:name":"Saou\u00eeri",
    "gn:population":0,
    "gn:timezone":"Asia/Beirut",
    "iso:country":"LB",
    "name:ara_x_preferred":[
        "\u0635\u0648\u064a\u0631\u064a"
    ],
    "name:ara_x_variant":[
        "\u0633\u0648\u064a\u0631\u064a"
    ],
    "name:ita_x_preferred":[
        "Souairy"
    ],
    "name:nno_x_preferred":[
        "Sawiri"
    ],
    "name:und_x_variant":[
        "Es Saou\u00eer\u00e9",
        "A\u015f \u015eaw\u012brah",
        "Saou\u00eeri",
        "\u015eaw\u012br\u012b"
    ],
    "wof:name":"Saouiri",
    "wof:placetype":"locality"
},
  "geometry": {"coordinates":[35.91111,33.68583],"type":"Point"}
}