{
  "type": "Feature",
  "properties": {
    "gn:admin1_code":"9.0",
    "gn:asciiname":"Batha",
    "gn:country_code":"LB",
    "gn:dem":1095,
    "gn:feature_class":"P",
    "gn:feature_code":"PPL",
    "gn:name":"Batha",
    "gn:population":0,
    "gn:timezone":"Asia/Beirut",
    "iso:country":"LB",
    "name:ceb_x_preferred":[
        "Batha"
    ],
    "name:ces_x_preferred":[
        "Batha"
    ],
    "name:fra_x_preferred":[
        "Batha"
    ],
    "name:ita_x_preferred":[
        "Batha"
    ],
    "name:pol_x_preferred":[
        "Batha"
    ],
    "name:swe_x_preferred":[
        "Batha"
    ],
    "name:und_x_variant":[
        "Ba\u0163\u1e29ah"
    ],
    "wof:name":"Batha",
    "wof:placetype":"locality"
},
  "geometry": {"coordinates":[35.86722,34.22611],"type":"Point"}
}