{
  "type": "Feature",
  "properties": {
    "gn:admin1_code":"7.0",
    "gn:asciiname":"Ain Aarab",
    "gn:country_code":"LB",
    "gn:dem":380,
    "gn:feature_class":"P",
    "gn:feature_code":"PPL",
    "gn:name":"A\u00efn Aarab",
    "gn:population":0,
    "gn:timezone":"Asia/Beirut",
    "iso:country":"LB",
    "wof:name":"Ain Aarab",
    "wof:placetype":"locality"
},
  "geometry": {"coordinates":[35.62278,33.29667],"type":"Point"}
}