{
  "type": "Feature",
  "properties": {
    "gn:admin1_code":"5.0",
    "gn:asciiname":"Kfardebian",
    "gn:country_code":"LB",
    "gn:dem":1847,
    "gn:feature_class":"P",
    "gn:feature_code":"PPL",
    "gn:name":"Kfardebian",
    "gn:population":0,
    "gn:timezone":"Asia/Beirut",
    "iso:country":"LB",
    "name:ara_x_preferred":[
        "\u0643\u0641\u0631\u062f\u0628\u064a\u0627\u0646"
    ],
    "name:ita_x_preferred":[
        "Kfardebian"
    ],
    "wof:name":"Kfardebian",
    "wof:placetype":"locality"
},
  "geometry": {"coordinates":[35.8377,33.99173],"type":"Point"}
}