{
  "type": "Feature",
  "properties": {
    "gn:admin1_code":"8.0",
    "gn:asciiname":"Saghbine",
    "gn:country_code":"LB",
    "gn:dem":1039,
    "gn:feature_class":"P",
    "gn:feature_code":"PPL",
    "gn:name":"Saghb\u00eene",
    "gn:population":0,
    "gn:timezone":"Asia/Beirut",
    "iso:country":"LB",
    "name:ara_x_preferred":[
        "\u0635\u063a\u0628\u064a\u0646"
    ],
    "name:und_x_variant":[
        "\u015eaghb\u012bn",
        "Saghb\u00eene"
    ],
    "wof:name":"Saghbine",
    "wof:placetype":"locality"
},
  "geometry": {"coordinates":[35.69694000000001,33.61083],"type":"Point"}
}