{
  "type": "Feature",
  "properties": {
    "gn:asciiname":"Rmadiyeh",
    "gn:country_code":"LB",
    "gn:dem":274,
    "gn:feature_class":"P",
    "gn:feature_code":"PPL",
    "gn:name":"Rmadiyeh",
    "gn:population":0,
    "gn:timezone":"Asia/Beirut",
    "iso:country":"LB",
    "name:und_x_variant":[
        "RAMADIET"
    ],
    "wof:name":"Rmadiyeh",
    "wof:placetype":"locality"
},
  "geometry": {"coordinates":[35.27601,33.19866],"type":"Point"}
}