{
  "type": "Feature",
  "properties": {
    "gn:admin1_code":"9.0",
    "gn:asciiname":"Beit Moumne",
    "gn:country_code":"LB",
    "gn:dem":1144,
    "gn:feature_class":"P",
    "gn:feature_code":"PPL",
    "gn:name":"Be\u00eft Mo\u00fbmn\u00e9",
    "gn:population":0,
    "gn:timezone":"Asia/Beirut",
    "iso:country":"LB",
    "name:und_x_variant":[
        "Bayt Mu\u2019minah",
        "Be\u00eft Mo\u00fbmn\u00e9"
    ],
    "wof:name":"Beit Moumne",
    "wof:placetype":"locality"
},
  "geometry": {"coordinates":[36.04861,34.37583],"type":"Point"}
}