{
  "type": "Feature",
  "properties": {
    "gn:admin1_code":"9.0",
    "gn:asciiname":"Aaqbet Sebaail",
    "gn:country_code":"LB",
    "gn:dem":697,
    "gn:feature_class":"P",
    "gn:feature_code":"PPL",
    "gn:name":"Aaqbet Sebaail",
    "gn:population":0,
    "gn:timezone":"Asia/Beirut",
    "iso:country":"LB",
    "name:und_x_variant":[
        "\u2018Aqabat Sib\u2018il",
        "Aaqbet Sebaail"
    ],
    "wof:name":"Aaqbet Sebaail",
    "wof:placetype":"locality"
},
  "geometry": {"coordinates":[35.91972,34.31722],"type":"Point"}
}