{
  "type": "Feature",
  "properties": {
    "gn:admin1_code":"5.0",
    "gn:asciiname":"Bchille",
    "gn:country_code":"LB",
    "gn:dem":572,
    "gn:feature_class":"P",
    "gn:feature_code":"PPL",
    "gn:name":"Bchill\u00e9",
    "gn:population":0,
    "gn:timezone":"Asia/Beirut",
    "iso:country":"LB",
    "name:ara_x_preferred":[
        "\u0628\u0634\u0644\u0644\u064a"
    ],
    "name:ara_x_variant":[
        "Bishill\u012b"
    ],
    "name:und_x_variant":[
        "Bshill\u012b",
        "Bchill\u00e9"
    ],
    "wof:name":"Bchille",
    "wof:placetype":"locality"
},
  "geometry": {"coordinates":[35.71889,34.10222],"type":"Point"}
}