{
  "type": "Feature",
  "properties": {
    "gn:country":"LB",
    "gn:fcode":"PPL",
    "gn:population":98433,
    "iso:country":"LB",
    "name:ara_x_preferred":[
        "\u062d\u0628\u0648\u0634"
    ],
    "name:ceb_x_preferred":[
        "Habbo\u00fbch"
    ],
    "name:eng_x_preferred":[
        "Habbo\u00fbch"
    ],
    "name:fra_x_preferred":[
        "Habbouche"
    ],
    "name:ita_x_preferred":[
        "Habbouch"
    ],
    "name:nld_x_preferred":[
        "Habbo\u00fbch"
    ],
    "name:por_x_preferred":[
        "Habbo\u00fbch"
    ],
    "name:rus_x_preferred":[
        "\u0425\u0430\u0431\u0431\u0443\u0448\u0435"
    ],
    "name:swe_x_preferred":[
        "Habbo\u00fbch"
    ],
    "name:und_x_variant":[
        "Habboush"
    ],
    "qs:name":"Habbo\u00fbch",
    "qs:photos_9r":0,
    "qs:photos_sr":0,
    "qs:pop_sr":"8",
    "wd:wordcount":53,
    "wof:name":"Habbo\u00fbch",
    "wof:placetype":"locality",
    "wof:population":98433
},
  "geometry": {"coordinates":[35.48278,33.4075],"type":"Point"}
}