{
  "type": "Feature",
  "properties": {
    "gn:admin1_code":"9.0",
    "gn:asciiname":"Ramat",
    "gn:country_code":"LB",
    "gn:dem":429,
    "gn:feature_class":"P",
    "gn:feature_code":"PPL",
    "gn:name":"R\u00e2m\u00e2t",
    "gn:population":0,
    "gn:timezone":"Asia/Beirut",
    "iso:country":"LB",
    "wof:name":"Ramat",
    "wof:placetype":"locality"
},
  "geometry": {"coordinates":[35.71639000000001,34.21833],"type":"Point"}
}