{
  "type": "Feature",
  "properties": {
    "gn:admin1_code":"11.0",
    "gn:asciiname":"Beit Habchi",
    "gn:country_code":"LB",
    "gn:dem":1519,
    "gn:feature_class":"P",
    "gn:feature_code":"PPL",
    "gn:name":"Beit Habchi",
    "gn:population":0,
    "gn:timezone":"Asia/Beirut",
    "iso:country":"LB",
    "name:und_x_variant":[
        "El Rh\u00e2r",
        "Bayt \u1e28abash\u012b",
        "Beit Habchi"
    ],
    "wof:name":"Beit Habchi",
    "wof:placetype":"locality"
},
  "geometry": {"coordinates":[36.09861,34.15361],"type":"Point"}
}