{
  "type": "Feature",
  "properties": {
    "gn:admin1_code":"10.0",
    "gn:asciiname":"Tallet ez Zefir",
    "gn:country_code":"LB",
    "gn:dem":66,
    "gn:feature_class":"P",
    "gn:feature_code":"PPL",
    "gn:name":"Tallet ez Zef\u00eer",
    "gn:population":0,
    "gn:timezone":"Asia/Beirut",
    "iso:country":"LB",
    "name:und_x_variant":[
        "Tallat az Zaf\u012br",
        "Tallet ez Zef\u00eer"
    ],
    "wof:name":"Tallet ez Zefir",
    "wof:placetype":"locality"
},
  "geometry": {"coordinates":[36.08333,34.57556],"type":"Point"}
}