{
  "type": "Feature",
  "properties": {
    "gn:admin1_code":"8.0",
    "gn:asciiname":"Qaa er Rim",
    "gn:country_code":"LB",
    "gn:dem":1279,
    "gn:feature_class":"P",
    "gn:feature_code":"PPL",
    "gn:name":"Q\u00e2a er R\u00eem",
    "gn:population":0,
    "gn:timezone":"Asia/Beirut",
    "iso:country":"LB",
    "name:ara_x_preferred":[
        "\u0642\u0627\u0639 \u0627\u0644\u0631\u064a\u0645"
    ],
    "name:nno_x_preferred":[
        "Q\u00e2a er R\u00eem"
    ],
    "name:und_x_variant":[
        "Q\u0101\u2018ar R\u012bm"
    ],
    "wof:name":"Qaa er Rim",
    "wof:placetype":"locality"
},
  "geometry": {"coordinates":[35.87528,33.88472],"type":"Point"}
}