{
  "type": "Feature",
  "properties": {
    "gn:admin1_code":"6.0",
    "gn:asciiname":"Sejoud",
    "gn:country_code":"LB",
    "gn:dem":1033,
    "gn:feature_class":"P",
    "gn:feature_code":"PPL",
    "gn:name":"S\u00e9joud",
    "gn:population":0,
    "gn:timezone":"Asia/Beirut",
    "iso:country":"LB",
    "name:ara_x_preferred":[
        "\u0633\u062c\u062f"
    ],
    "name:und_x_variant":[
        "Sujud",
        "S\u00e9joud",
        "SOUJOUD"
    ],
    "wof:name":"Sejoud",
    "wof:placetype":"locality"
},
  "geometry": {"coordinates":[35.53361,33.43360999999999],"type":"Point"}
}