{
  "type": "Feature",
  "properties": {
    "gn:admin1_code":"9.0",
    "gn:asciiname":"Borj el Yahoudiye",
    "gn:country_code":"LB",
    "gn:dem":165,
    "gn:feature_class":"P",
    "gn:feature_code":"PPL",
    "gn:name":"Borj el Yahoud\u00eey\u00e9",
    "gn:population":0,
    "gn:timezone":"Asia/Beirut",
    "iso:country":"LB",
    "name:ara_x_preferred":[
        "\u0628\u0631\u062c \u0627\u0644\u064a\u0647\u0648\u062f\u064a\u0629"
    ],
    "name:und_x_variant":[
        "Borj el Uahoud\u00eey\u00e9",
        "Burj al Yah\u016bd\u012byah",
        "Borj el Yahoud\u00eey\u00e9"
    ],
    "wof:name":"Borj el Yahoudiye",
    "wof:placetype":"locality"
},
  "geometry": {"coordinates":[35.91183,34.45382],"type":"Point"}
}