{
  "type": "Feature",
  "properties": {
    "gn:admin1_code":"5.0",
    "gn:asciiname":"Al `Ayn",
    "gn:country_code":"LB",
    "gn:dem":92,
    "gn:feature_class":"P",
    "gn:feature_code":"PPL",
    "gn:name":"Al \u2018Ayn",
    "gn:population":0,
    "gn:timezone":"Asia/Beirut",
    "iso:country":"LB",
    "name:und_x_variant":[
        "El A\u00efn",
        "Al \u2018Ayn"
    ],
    "wof:name":"Al `Ayn",
    "wof:placetype":"locality"
},
  "geometry": {"coordinates":[35.53333,33.81667],"type":"Point"}
}