{
  "type": "Feature",
  "properties": {
    "gn:admin1_code":"5.0",
    "gn:asciiname":"Eghbe",
    "gn:country_code":"LB",
    "gn:dem":1118,
    "gn:feature_class":"P",
    "gn:feature_code":"PPL",
    "gn:name":"Eghb\u00e9",
    "gn:population":0,
    "gn:timezone":"Asia/Beirut",
    "iso:country":"LB",
    "name:und_x_variant":[
        "Aghbah",
        "Eghb\u00e9"
    ],
    "wof:name":"Eghbe",
    "wof:placetype":"locality"
},
  "geometry": {"coordinates":[35.70917,34.00944],"type":"Point"}
}