{
  "type": "Feature",
  "properties": {
    "gn:admin1_code":"11.0",
    "gn:asciiname":"Mazraat Beit el Fqih",
    "gn:country_code":"LB",
    "gn:dem":998,
    "gn:feature_class":"P",
    "gn:feature_code":"PPL",
    "gn:name":"Mazraat Be\u00eft el Fq\u00eeh",
    "gn:population":0,
    "gn:timezone":"Asia/Beirut",
    "iso:country":"LB",
    "name:und_x_variant":[
        "Mazra\u2018at Bayt al Faq\u012bh",
        "Mazraat Be\u00eft el Fq\u00eeh"
    ],
    "wof:name":"Mazraat Beit el Fqih",
    "wof:placetype":"locality"
},
  "geometry": {"coordinates":[36.34194,34.34833],"type":"Point"}
}