{
  "type": "Feature",
  "properties": {
    "gn:admin1_code":"5.0",
    "gn:asciiname":"Dahr Badris",
    "gn:country_code":"LB",
    "gn:dem":417,
    "gn:feature_class":"P",
    "gn:feature_code":"PPL",
    "gn:name":"Dahr Badr\u00ees",
    "gn:population":0,
    "gn:timezone":"Asia/Beirut",
    "iso:country":"LB",
    "wof:name":"Dahr Badris",
    "wof:placetype":"locality"
},
  "geometry": {"coordinates":[35.66389,34.0525],"type":"Point"}
}