{
  "type": "Feature",
  "properties": {
    "gn:admin1_code":"10.0",
    "gn:asciiname":"Qabaait",
    "gn:country_code":"LB",
    "gn:dem":593,
    "gn:feature_class":"P",
    "gn:feature_code":"PPL",
    "gn:name":"Qabaa\u00eft",
    "gn:population":0,
    "gn:timezone":"Asia/Beirut",
    "iso:country":"LB",
    "name:und_x_variant":[
        "Qab\u2018\u012bt",
        "Qabaa\u00eft"
    ],
    "wof:name":"Qabaait",
    "wof:placetype":"locality"
},
  "geometry": {"coordinates":[36.09694,34.44889000000001],"type":"Point"}
}