{
  "type": "Feature",
  "properties": {
    "gn:admin1_code":"5.0",
    "gn:asciiname":"Qeryaqous",
    "gn:country_code":"LB",
    "gn:dem":1104,
    "gn:feature_class":"P",
    "gn:feature_code":"PPL",
    "gn:name":"Qery\u00e2qo\u00fbs",
    "gn:population":0,
    "gn:timezone":"Asia/Beirut",
    "iso:country":"LB",
    "name:und_x_variant":[
        "Qiry\u0101q\u016bs",
        "Qery\u00e2qo\u00fbs"
    ],
    "wof:name":"Qeryaqous",
    "wof:placetype":"locality"
},
  "geometry": {"coordinates":[35.87083,34.09472],"type":"Point"}
}