{
  "type": "Feature",
  "properties": {
    "gn:admin1_code":"10.0",
    "gn:asciiname":"Rejm Beit Houssein",
    "gn:country_code":"LB",
    "gn:dem":502,
    "gn:feature_class":"P",
    "gn:feature_code":"PPL",
    "gn:name":"Rejm Be\u00eft Housse\u00efn",
    "gn:population":0,
    "gn:timezone":"Asia/Beirut",
    "iso:country":"LB",
    "wof:name":"Rejm Beit Houssein",
    "wof:placetype":"locality"
},
  "geometry": {"coordinates":[36.38361,34.60639],"type":"Point"}
}