{
  "type": "Feature",
  "properties": {
    "iso:country":"LB",
    "name:ara_x_preferred":[
        "\u0627\u0644\u062d\u062f\u062b"
    ],
    "name:eng_x_preferred":[
        "Al Hadath"
    ],
    "qs:gn_pop":0,
    "qs:name":"\u0627\u0644\u062d\u062f\u062b",
    "qs:name_adm0":"\u0644\u0628\u0646\u0627\u0646",
    "qs:name_adm1":"\u062c\u0628\u0644 \u0644\u0628\u0646\u0627\u0646",
    "qs:photos":23,
    "qs:photos_1k":5,
    "qs:photos_9k":1,
    "qs:photos_9r":1,
    "qs:photos_all":23,
    "qs:photos_sr":1,
    "qs:placetype":"Town",
    "qs:pop_sr":"0",
    "qs:woe_adm0":23424873,
    "wof:name":"Al Hadath",
    "wof:placetype":"locality"
},
  "geometry": {"coordinates":[35.527725,33.848177],"type":"Point"}
}