{
  "type": "Feature",
  "properties": {
    "gn:admin1_code":"9.0",
    "gn:asciiname":"Kfarsaroun",
    "gn:country_code":"LB",
    "gn:dem":1384,
    "gn:feature_class":"P",
    "gn:feature_code":"PPL",
    "gn:name":"Kfars\u00e2ro\u00fbn",
    "gn:population":0,
    "gn:timezone":"Asia/Beirut",
    "iso:country":"LB",
    "name:ara_x_preferred":[
        "\u0643\u0641\u0631 \u0635\u0627\u0631\u0648\u0646"
    ],
    "name:ara_x_variant":[
        "\u0643\u0641\u0631\u0635\u0627\u0631\u0648\u0646"
    ],
    "name:ita_x_preferred":[
        "Kfarsaroun"
    ],
    "name:nno_x_preferred":[
        "Kfarsaroun"
    ],
    "name:und_x_variant":[
        "Kafr \u015e\u0101r\u016bn",
        "Kfars\u00e2ro\u00fbn"
    ],
    "wof:name":"Kfarsaroun",
    "wof:placetype":"locality"
},
  "geometry": {"coordinates":[35.9625,34.24361],"type":"Point"}
}