{
  "type": "Feature",
  "properties": {
    "gn:admin1_code":"5.0",
    "gn:asciiname":"El Aammariye",
    "gn:country_code":"LB",
    "gn:dem":149,
    "gn:feature_class":"P",
    "gn:feature_code":"PPL",
    "gn:name":"El Aammariy\u00e9",
    "gn:population":0,
    "gn:timezone":"Asia/Beirut",
    "iso:country":"LB",
    "name:ara_x_preferred":[
        "\u0627\u0644\u0639\u0645\u0627\u0631\u064a\u0629"
    ],
    "name:und_x_variant":[
        "El Asmmariy\u00e9",
        "Al \u2018Am\u0101r\u012byah",
        "Aamm\u00e2r\u00eeye",
        "Al \u2018Amm\u0101r\u012byah",
        "El Aammariy\u00e9"
    ],
    "wof:name":"El Aammariye",
    "wof:placetype":"locality"
},
  "geometry": {"coordinates":[35.57917,33.88472],"type":"Point"}
}