{
  "type": "Feature",
  "properties": {
    "gn:admin1_code":"6.0",
    "gn:asciiname":"Benouate",
    "gn:country_code":"LB",
    "gn:dem":847,
    "gn:feature_class":"P",
    "gn:feature_code":"PPL",
    "gn:name":"Benou\u00e2t\u00e9",
    "gn:population":0,
    "gn:timezone":"Asia/Beirut",
    "iso:country":"LB",
    "name:ara_x_preferred":[
        "\u0628\u0646\u0648\u0627\u062a\u0629"
    ],
    "name:und_x_variant":[
        "Binw\u0101t\u012b",
        "Benou\u00e2t\u00e9",
        "Binw\u0101tah"
    ],
    "wof:name":"Benouate",
    "wof:placetype":"locality"
},
  "geometry": {"coordinates":[35.57417,33.57639],"type":"Point"}
}