{
  "type": "Feature",
  "properties": {
    "gn:admin1_code":"5.0",
    "gn:asciiname":"El Ghabiye",
    "gn:country_code":"LB",
    "gn:dem":1729,
    "gn:feature_class":"P",
    "gn:feature_code":"PPL",
    "gn:name":"El Ghab\u00eey\u00e9",
    "gn:population":0,
    "gn:timezone":"Asia/Beirut",
    "iso:country":"LB",
    "name:und_x_variant":[
        "Al Gh\u0101biyah",
        "El Ghab\u00eey\u00e9"
    ],
    "wof:name":"El Ghabiye",
    "wof:placetype":"locality"
},
  "geometry": {"coordinates":[35.89778,34.16833],"type":"Point"}
}