{
  "type": "Feature",
  "properties": {
    "gn:admin1_code":"10.0",
    "gn:asciiname":"Ez Zouarib",
    "gn:country_code":"LB",
    "gn:dem":226,
    "gn:feature_class":"P",
    "gn:feature_code":"PPL",
    "gn:name":"Ez Zou\u00e2r\u00eeb",
    "gn:population":0,
    "gn:timezone":"Asia/Beirut",
    "iso:country":"LB",
    "name:und_x_variant":[
        "Ez Zwareeb",
        "Az Zaw\u0101r\u012bb",
        "Ez Zou\u00e2r\u00eeb"
    ],
    "wof:name":"Ez Zouarib",
    "wof:placetype":"locality"
},
  "geometry": {"coordinates":[36.07,34.53111],"type":"Point"}
}