{
  "type": "Feature",
  "properties": {
    "gn:admin1_code":"11.0",
    "gn:asciiname":"Ech Chraoune",
    "gn:country_code":"LB",
    "gn:dem":1146,
    "gn:feature_class":"P",
    "gn:feature_code":"PPL",
    "gn:name":"Ech Chraoun\u00e9",
    "gn:population":0,
    "gn:timezone":"Asia/Beirut",
    "iso:country":"LB",
    "name:und_x_variant":[
        "Ash Shar\u0101winah",
        "Ech Chraoun\u00e9"
    ],
    "wof:name":"Ech Chraoune",
    "wof:placetype":"locality"
},
  "geometry": {"coordinates":[36.20694,34.0125],"type":"Point"}
}