{
  "type": "Feature",
  "properties": {
    "gn:admin1_code":"9.0",
    "gn:asciiname":"Dahr el Qatlab",
    "gn:country_code":"LB",
    "gn:dem":514,
    "gn:feature_class":"P",
    "gn:feature_code":"PPL",
    "gn:name":"Dahr el Qatlab",
    "gn:population":0,
    "gn:timezone":"Asia/Beirut",
    "iso:country":"LB",
    "name:ara_x_preferred":[
        "\u0636\u0647\u0631 \u0627\u0644\u0642\u0637\u0644\u0628"
    ],
    "name:und_x_variant":[
        "Dahr el Katlab",
        "\u1e10ahr al Qa\u0163lab",
        "Dahr el Qatlab"
    ],
    "wof:name":"Dahr el Qatlab",
    "wof:placetype":"locality"
},
  "geometry": {"coordinates":[35.73694000000001,34.21278],"type":"Point"}
}