{
  "type": "Feature",
  "properties": {
    "gn:admin1_code":"5.0",
    "gn:asciiname":"Bkhochtai",
    "gn:country_code":"LB",
    "gn:dem":790,
    "gn:feature_class":"P",
    "gn:feature_code":"PPL",
    "gn:name":"Bkhochta\u00ef",
    "gn:population":0,
    "gn:timezone":"Asia/Beirut",
    "iso:country":"LB",
    "name:ara_x_preferred":[
        "\u0628\u062e\u0634\u062a\u064a\u0629"
    ],
    "name:und_x_variant":[
        "Brichtai",
        "Bkhechtay",
        "Bkhouchta\u00ef",
        "Bkhishtay",
        "Bkhochta\u00ef",
        "Bkhushtayah"
    ],
    "wof:name":"Bkhochtai",
    "wof:placetype":"locality"
},
  "geometry": {"coordinates":[35.61833,33.79972],"type":"Point"}
}