{
  "type": "Feature",
  "properties": {
    "gn:admin1_code":"6.0",
    "gn:asciiname":"Yanouh",
    "gn:country_code":"LB",
    "gn:dem":203,
    "gn:feature_class":"P",
    "gn:feature_code":"PPL",
    "gn:name":"Y\u00e2no\u00fbh",
    "gn:population":0,
    "gn:timezone":"Asia/Beirut",
    "iso:country":"LB",
    "name:ara_x_preferred":[
        "\u064a\u0627\u0646\u0648\u062d"
    ],
    "name:ita_x_preferred":[
        "Yanouh"
    ],
    "name:und_x_variant":[
        "Y\u0101n\u016b\u1e29",
        "Y\u00e2no\u00fbh",
        "Ynouh"
    ],
    "wof:name":"Yanouh",
    "wof:placetype":"locality"
},
  "geometry": {"coordinates":[35.30259,33.26025],"type":"Point"}
}