{
  "type": "Feature",
  "properties": {
    "gn:admin1_code":"10.0",
    "gn:asciiname":"Ez Zire",
    "gn:country_code":"LB",
    "gn:dem":554,
    "gn:feature_class":"P",
    "gn:feature_code":"PPL",
    "gn:name":"Ez Zir\u00e9",
    "gn:population":0,
    "gn:timezone":"Asia/Beirut",
    "iso:country":"LB",
    "wof:name":"Ez Zire",
    "wof:placetype":"locality"
},
  "geometry": {"coordinates":[36.18861,34.54111],"type":"Point"}
}