{
  "type": "Feature",
  "properties": {
    "gn:admin1_code":"5.0",
    "gn:asciiname":"Aaoukar",
    "gn:country_code":"LB",
    "gn:dem":100,
    "gn:feature_class":"P",
    "gn:feature_code":"PPL",
    "gn:name":"Aaoukar",
    "gn:population":0,
    "gn:timezone":"Asia/Beirut",
    "iso:country":"LB",
    "name:und_x_variant":[
        "\u2018Awkar",
        "Aaoukar"
    ],
    "wof:name":"Aaoukar",
    "wof:placetype":"locality"
},
  "geometry": {"coordinates":[35.59778,33.93360999999999],"type":"Point"}
}