{
  "type": "Feature",
  "properties": {
    "gn:admin1_code":"5.0",
    "gn:asciiname":"El Aafs",
    "gn:country_code":"LB",
    "gn:dem":629,
    "gn:feature_class":"P",
    "gn:feature_code":"PPL",
    "gn:name":"El Aafs",
    "gn:population":0,
    "gn:timezone":"Asia/Beirut",
    "iso:country":"LB",
    "name:ara_x_preferred":[
        "\u0627\u0644\u0639\u0641\u0635"
    ],
    "name:und_x_variant":[
        "Al \u2018Af\u015f",
        "El Aafs"
    ],
    "wof:name":"El Aafs",
    "wof:placetype":"locality"
},
  "geometry": {"coordinates":[35.68111,34.01417],"type":"Point"}
}