{
  "type": "Feature",
  "properties": {
    "gn:admin1_code":"9.0",
    "gn:asciiname":"Bterram",
    "gn:country_code":"LB",
    "gn:dem":275,
    "gn:feature_class":"P",
    "gn:feature_code":"PPL",
    "gn:name":"Bterr\u00e2m",
    "gn:population":0,
    "gn:timezone":"Asia/Beirut",
    "iso:country":"LB",
    "name:ara_x_preferred":[
        "\u0628\u0637\u0631\u0627\u0645"
    ],
    "name:ita_x_preferred":[
        "Bterram"
    ],
    "name:nno_x_preferred":[
        "Btourram"
    ],
    "name:und_x_variant":[
        "Batarr\u0101m",
        "B\u0163urr\u0101m",
        "B\u0163arr\u0101m",
        "Bterr\u00e2m"
    ],
    "wof:name":"Bterram",
    "wof:placetype":"locality"
},
  "geometry": {"coordinates":[35.80917,34.33194],"type":"Point"}
}