{
  "type": "Feature",
  "properties": {
    "gn:admin1_code":"5.0",
    "gn:asciiname":"Deir Baba",
    "gn:country_code":"LB",
    "gn:dem":477,
    "gn:feature_class":"P",
    "gn:feature_code":"PPL",
    "gn:name":"Deir Baba",
    "gn:population":0,
    "gn:timezone":"Asia/Beirut",
    "iso:country":"LB",
    "name:ara_x_preferred":[
        "\u062f\u064a\u0631 \u0628\u0627\u0628\u0627"
    ],
    "name:und_x_variant":[
        "Deir Beba",
        "Dayr B\u0101b\u0101",
        "Deir Baba"
    ],
    "wof:name":"Deir Baba",
    "wof:placetype":"locality"
},
  "geometry": {"coordinates":[35.52556,33.69694],"type":"Point"}
}