{
  "type": "Feature",
  "properties": {
    "gn:admin1_code":"11.0",
    "gn:asciiname":"Haouch ed Dahab",
    "gn:country_code":"LB",
    "gn:dem":1011,
    "gn:feature_class":"P",
    "gn:feature_code":"PPL",
    "gn:name":"Haouch ed Dahab",
    "gn:population":0,
    "gn:timezone":"Asia/Beirut",
    "iso:country":"LB",
    "name:und_x_variant":[
        "Haouche ed Dahab",
        "Haouche Dahab",
        "\u1e28awsh adh Dhahab",
        "Haouch ed Dahab"
    ],
    "wof:name":"Haouch ed Dahab",
    "wof:placetype":"locality"
},
  "geometry": {"coordinates":[36.1225,34.02583],"type":"Point"}
}