{
  "type": "Feature",
  "properties": {
    "gn:admin1_code":"8.0",
    "gn:asciiname":"Es Safra",
    "gn:country_code":"LB",
    "gn:dem":867,
    "gn:feature_class":"P",
    "gn:feature_code":"PPL",
    "gn:name":"Es Safra",
    "gn:population":0,
    "gn:timezone":"Asia/Beirut",
    "iso:country":"LB",
    "name:ara_x_preferred":[
        "\u0627\u0644\u0635\u0641\u0631\u0629"
    ],
    "name:und_x_variant":[
        "A\u015f \u015eafrah"
    ],
    "wof:name":"Es Safra",
    "wof:placetype":"locality"
},
  "geometry": {"coordinates":[35.80194,33.75360999999999],"type":"Point"}
}