{
  "type": "Feature",
  "properties": {
    "gn:admin1_code":"9.0",
    "gn:asciiname":"Bnahrane",
    "gn:country_code":"LB",
    "gn:dem":559,
    "gn:feature_class":"P",
    "gn:feature_code":"PPL",
    "gn:name":"Bnahr\u00e2ne",
    "gn:population":0,
    "gn:timezone":"Asia/Beirut",
    "iso:country":"LB",
    "name:ara_x_preferred":[
        "\u0628\u0646\u0647\u0631\u0627\u0646"
    ],
    "name:und_x_variant":[
        "Bnahr\u0101n",
        "Bnahr\u00e2ne",
        "Binahr\u0101n"
    ],
    "wof:name":"Bnahrane",
    "wof:placetype":"locality"
},
  "geometry": {"coordinates":[35.85222,34.27444000000001],"type":"Point"}
}