{
  "type": "Feature",
  "properties": {
    "gn:admin1_code":"11.0",
    "gn:asciiname":"Beit Aallaou",
    "gn:country_code":"LB",
    "gn:dem":1732,
    "gn:feature_class":"P",
    "gn:feature_code":"PPL",
    "gn:name":"Be\u00eft Aallaou",
    "gn:population":0,
    "gn:timezone":"Asia/Beirut",
    "iso:country":"LB",
    "wof:name":"Beit Aallaou",
    "wof:placetype":"locality"
},
  "geometry": {"coordinates":[36.23278,34.37778],"type":"Point"}
}