{
  "type": "Feature",
  "properties": {
    "gn:admin1_code":"10.0",
    "gn:asciiname":"Jdaidet el Qaitaa",
    "gn:country_code":"LB",
    "gn:dem":321,
    "gn:feature_class":"P",
    "gn:feature_code":"PPL",
    "gn:name":"Jda\u00efdet el Qa\u00eftaa",
    "gn:population":0,
    "gn:timezone":"Asia/Beirut",
    "iso:country":"LB",
    "name:und_x_variant":[
        "El Jda\u00efd\u00e9",
        "Jdeidat el-Qeite\u2018",
        "Jda\u00efd\u00e9",
        "Jdaidet el Qaiteaa",
        "Judaydat al Qay\u0163i\u2018",
        "Jda\u00efdet el Qa\u00eftaa"
    ],
    "wof:name":"Jdaidet el Qaitaa",
    "wof:placetype":"locality"
},
  "geometry": {"coordinates":[36.01167,34.46583],"type":"Point"}
}