{
  "type": "Feature",
  "properties": {
    "gn:admin1_code":"7.0",
    "gn:asciiname":"El Fardis",
    "gn:country_code":"LB",
    "gn:dem":555,
    "gn:feature_class":"P",
    "gn:feature_code":"PPL",
    "gn:name":"El Fard\u00ees",
    "gn:population":0,
    "gn:timezone":"Asia/Beirut",
    "iso:country":"LB",
    "name:ara_x_preferred":[
        "\u0627\u0644\u0641\u0631\u062f\u064a\u0633"
    ],
    "name:und_x_variant":[
        "Ferdisse",
        "El-Fardees",
        "Fra\u00efdiss",
        "Al Furayd\u012bs",
        "Frayd\u012bs",
        "Al Fard\u012bs",
        "El Fard\u00ees",
        "Ferdiss"
    ],
    "wof:name":"El Fardis",
    "wof:placetype":"locality"
},
  "geometry": {"coordinates":[35.66806,33.37167],"type":"Point"}
}