{
  "type": "Feature",
  "properties": {
    "gn:admin1_code":"5.0",
    "gn:asciiname":"El Faouara",
    "gn:country_code":"LB",
    "gn:dem":685,
    "gn:feature_class":"P",
    "gn:feature_code":"PPL",
    "gn:name":"El Faou\u00e2ra",
    "gn:population":0,
    "gn:timezone":"Asia/Beirut",
    "iso:country":"LB",
    "name:ara_x_preferred":[
        "\u0627\u0644\u0641\u0648\u0651\u0627\u0631\u0629"
    ],
    "name:und_x_variant":[
        "El Fo\u00fb\u00e2ra",
        "El-Fuwwarah",
        "Al Faww\u0101rah",
        "El Faou\u00e2ra"
    ],
    "wof:name":"El Faouara",
    "wof:placetype":"locality"
},
  "geometry": {"coordinates":[35.64056,33.71194000000001],"type":"Point"}
}