{
  "type": "Feature",
  "properties": {
    "gn:admin1_code":"6.0",
    "gn:asciiname":"Oum et Tout",
    "gn:country_code":"LB",
    "gn:dem":449,
    "gn:feature_class":"P",
    "gn:feature_code":"PPL",
    "gn:name":"Oum et To\u00fbt",
    "gn:population":0,
    "gn:timezone":"Asia/Beirut",
    "iso:country":"LB",
    "name:ara_x_preferred":[
        "\u0623\u0645 \u062a\u0648\u062a\u0629"
    ],
    "name:ara_x_variant":[
        "\u0623\u0645 \u0627\u0644\u062a\u0648\u062a"
    ],
    "name:und_x_variant":[
        "Umm at T\u016bt",
        "Oum et To\u00fbt",
        "Umm T\u016btah"
    ],
    "wof:name":"Oum et Tout",
    "wof:placetype":"locality"
},
  "geometry": {"coordinates":[35.25528,33.11278],"type":"Point"}
}