{
  "type": "Feature",
  "properties": {
    "gn:admin1_code":"5.0",
    "gn:asciiname":"Hsayma",
    "gn:cc2":"LB",
    "gn:country_code":"LB",
    "gn:dem":187,
    "gn:feature_class":"P",
    "gn:feature_code":"PPL",
    "gn:name":"\u1e28saym\u0101",
    "gn:population":0,
    "gn:timezone":"Asia/Beirut",
    "iso:country":"LB",
    "name:und_x_variant":[
        "Hasa\u00efma",
        "Hsa\u00efma",
        "\u1e28saym\u0101"
    ],
    "wof:name":"Hsayma",
    "wof:placetype":"locality"
},
  "geometry": {"coordinates":[35.55,33.85],"type":"Point"}
}