{
  "type": "Feature",
  "properties": {
    "gn:admin1_code":"5.0",
    "gn:asciiname":"Ech Charbine",
    "gn:country_code":"LB",
    "gn:dem":1572,
    "gn:feature_class":"P",
    "gn:feature_code":"PPL",
    "gn:name":"Ech Charb\u00een\u00e9",
    "gn:population":0,
    "gn:timezone":"Asia/Beirut",
    "iso:country":"LB",
    "name:ara_x_preferred":[
        "\u0627\u0644\u0634\u0631\u0628\u064a\u0646\u0629"
    ],
    "name:und_x_variant":[
        "Ch\u00e2rb\u00eeni",
        "Ash Sharb\u012bnah",
        "Ech Charb\u00een\u00e9"
    ],
    "wof:name":"Ech Charbine",
    "wof:placetype":"locality"
},
  "geometry": {"coordinates":[35.85972,34.11778],"type":"Point"}
}