{
  "type": "Feature",
  "properties": {
    "gn:admin1_code":"11.0",
    "gn:asciiname":"Taraya",
    "gn:country_code":"LB",
    "gn:dem":1172,
    "gn:feature_class":"P",
    "gn:feature_code":"PPL",
    "gn:name":"T\u00e2ray\u00e2",
    "gn:population":0,
    "gn:timezone":"Asia/Beirut",
    "iso:country":"LB",
    "name:und_x_variant":[
        "\u0162\u0101rayy\u0101",
        "T\u00e2ray\u00e2"
    ],
    "wof:name":"Taraya",
    "wof:placetype":"locality"
},
  "geometry": {"coordinates":[36.02222000000001,33.98333],"type":"Point"}
}