{
  "type": "Feature",
  "properties": {
    "gn:admin1_code":"6.0",
    "gn:asciiname":"Mazraat Jall el Bahr",
    "gn:country_code":"LB",
    "gn:dem":14,
    "gn:feature_class":"P",
    "gn:feature_code":"PPL",
    "gn:name":"Mazraat Jall el Bahr",
    "gn:population":0,
    "gn:timezone":"Asia/Beirut",
    "iso:country":"LB",
    "name:ara_x_preferred":[
        "\u0645\u0632\u0631\u0639\u0629 \u062c\u0644 \u0627\u0644\u0628\u062d\u0631"
    ],
    "name:und_x_variant":[
        "Mazra\u2018at Jall al Ba\u1e29r"
    ],
    "wof:name":"Mazraat Jall el Bahr",
    "wof:placetype":"locality"
},
  "geometry": {"coordinates":[35.20160999999999,33.19313],"type":"Point"}
}