{
  "type": "Feature",
  "properties": {
    "gn:admin1_code":"5.0",
    "gn:asciiname":"Er Rsif",
    "gn:country_code":"LB",
    "gn:dem":123,
    "gn:feature_class":"P",
    "gn:feature_code":"PPL",
    "gn:name":"Er Rs\u00eef",
    "gn:population":0,
    "gn:timezone":"Asia/Beirut",
    "iso:country":"LB",
    "name:und_x_variant":[
        "Ar Ra\u015f\u012bf",
        "Er Rs\u00eef"
    ],
    "wof:name":"Er Rsif",
    "wof:placetype":"locality"
},
  "geometry": {"coordinates":[35.63639000000001,34.02111],"type":"Point"}
}