{
  "type": "Feature",
  "properties": {
    "gn:admin1_code":"11.0",
    "gn:asciiname":"Mrah Yassine",
    "gn:country_code":"LB",
    "gn:dem":1011,
    "gn:feature_class":"P",
    "gn:feature_code":"PPL",
    "gn:name":"Mr\u00e2h Y\u00e2ss\u00eene",
    "gn:population":0,
    "gn:timezone":"Asia/Beirut",
    "iso:country":"LB",
    "name:und_x_variant":[
        "Mar\u0101\u1e29 Y\u0101s\u012bn",
        "Mr\u00e2h Y\u00e2ss\u00eene"
    ],
    "wof:name":"Mrah Yassine",
    "wof:placetype":"locality"
},
  "geometry": {"coordinates":[36.335,34.33722],"type":"Point"}
}