{
  "type": "Feature",
  "properties": {
    "iso:country":"LB",
    "qs:gn_pop":0,
    "qs:name":"\u062c\u0646\u0629",
    "qs:name_adm0":"\u0644\u0628\u0646\u0627\u0646",
    "qs:name_adm1":"\u062c\u0628\u0644 \u0644\u0628\u0646\u0627\u0646",
    "qs:photos":24,
    "qs:photos_1k":5,
    "qs:photos_9k":1,
    "qs:photos_9r":1,
    "qs:photos_all":24,
    "qs:photos_sr":1,
    "qs:placetype":"Town",
    "qs:pop_sr":"0",
    "qs:woe_adm0":23424873,
    "wof:name":"\u062c\u0646\u0629",
    "wof:placetype":"locality"
},
  "geometry": {"coordinates":[35.833087,34.0950065],"type":"Point"}
}