{
  "type": "Feature",
  "properties": {
    "gn:admin1_code":"5.0",
    "gn:asciiname":"En Naaoura",
    "gn:country_code":"LB",
    "gn:dem":6,
    "gn:feature_class":"P",
    "gn:feature_code":"PPL",
    "gn:name":"En N\u00e2ao\u00fbra",
    "gn:population":0,
    "gn:timezone":"Asia/Beirut",
    "iso:country":"LB",
    "name:und_x_variant":[
        "An N\u0101\u2018\u016brah",
        "En N\u00e2ao\u00fbra"
    ],
    "wof:name":"En Naaoura",
    "wof:placetype":"locality"
},
  "geometry": {"coordinates":[35.64360999999999,34.0125],"type":"Point"}
}