{
  "type": "Feature",
  "properties": {
    "gn:admin1_code":"10.0",
    "gn:asciiname":"Ed Dabbabiye el Gharbiye",
    "gn:country_code":"LB",
    "gn:dem":261,
    "gn:feature_class":"P",
    "gn:feature_code":"PPL",
    "gn:name":"Ed Dabb\u00e2biy\u00e9 el Gharb\u00eey\u00e9",
    "gn:population":0,
    "gn:timezone":"Asia/Beirut",
    "iso:country":"LB",
    "name:und_x_variant":[
        "Ed Dibbabiyah",
        "Ed Dibbabiyah Gharbi",
        "Ad Dabb\u0101b\u012byah al Gharb\u012byah",
        "Ed Dabb\u00e2biy\u00e9 el Gharb\u00eey\u00e9"
    ],
    "wof:name":"Ed Dabbabiye el Gharbiye",
    "wof:placetype":"locality"
},
  "geometry": {"coordinates":[36.21556,34.62278],"type":"Point"}
}