{
  "type": "Feature",
  "properties": {
    "gn:admin1_code":"5.0",
    "gn:asciiname":"Aabadiye",
    "gn:country_code":"LB",
    "gn:dem":684,
    "gn:feature_class":"P",
    "gn:feature_code":"PPL",
    "gn:name":"Aabadiy\u00e9",
    "gn:population":0,
    "gn:timezone":"Asia/Beirut",
    "iso:country":"LB",
    "name:ara_x_preferred":[
        "\u0627\u0644\u0639\u0628\u0627\u062f\u064a\u0629"
    ],
    "name:und_x_variant":[
        "El Aabadiy\u00e9",
        "Abadiyeh",
        "Abady\u00e9",
        "Al \u2018Abb\u0101d\u012byah",
        "Aabadiy\u00e9",
        "Al \u2018Ab\u0101d\u012byah"
    ],
    "wof:name":"Aabadiye",
    "wof:placetype":"locality"
},
  "geometry": {"coordinates":[35.62028,33.83639],"type":"Point"}
}