{
  "type": "Feature",
  "properties": {
    "gn:admin1_code":"5.0",
    "gn:asciiname":"Ain Qara",
    "gn:country_code":"LB",
    "gn:dem":1551,
    "gn:feature_class":"P",
    "gn:feature_code":"PPL",
    "gn:name":"A\u00efn Q\u00e2ra",
    "gn:population":0,
    "gn:timezone":"Asia/Beirut",
    "iso:country":"LB",
    "name:und_x_variant":[
        "\u2018Ayn Q\u0101rah",
        "A\u00efn Q\u00e2ra"
    ],
    "wof:name":"Ain Qara",
    "wof:placetype":"locality"
},
  "geometry": {"coordinates":[35.87361,34.11861],"type":"Point"}
}