{
  "type": "Feature",
  "properties": {
    "gn:admin1_code":"5.0",
    "gn:asciiname":"El Qachaya",
    "gn:country_code":"LB",
    "gn:dem":903,
    "gn:feature_class":"P",
    "gn:feature_code":"PPL",
    "gn:name":"El Qach\u00e2ya",
    "gn:population":0,
    "gn:timezone":"Asia/Beirut",
    "iso:country":"LB",
    "name:ara_x_preferred":[
        "\u0627\u0644\u0642\u0634\u0627\u064a\u0627"
    ],
    "name:und_x_variant":[
        "El Qach\u00e2ya",
        "Al Qash\u0101y\u0101"
    ],
    "wof:name":"El Qachaya",
    "wof:placetype":"locality"
},
  "geometry": {"coordinates":[35.56389,33.675],"type":"Point"}
}