{
  "type": "Feature",
  "properties": {
    "gn:admin1_code":"5.0",
    "gn:asciiname":"Hazmiye",
    "gn:country_code":"LB",
    "gn:dem":136,
    "gn:feature_class":"P",
    "gn:feature_code":"PPL",
    "gn:name":"Hazmiy\u00e9",
    "gn:population":0,
    "gn:timezone":"Asia/Beirut",
    "iso:country":"LB",
    "name:ara_x_preferred":[
        "\u0627\u0644\u062d\u0627\u0632\u0645\u064a\u0629"
    ],
    "name:und_x_variant":[
        "El H\u00e2zm\u00eey\u00e9",
        "Hasmiyeh",
        "Hazmie",
        "Al \u1e28\u0101zim\u012byah",
        "Hazmiy\u00e9"
    ],
    "wof:name":"Hazmiye",
    "wof:placetype":"locality"
},
  "geometry": {"coordinates":[35.54139,33.85111],"type":"Point"}
}