{
  "type": "Feature",
  "properties": {
    "gn:admin1_code":"10.0",
    "gn:asciiname":"Es Sfine",
    "gn:country_code":"LB",
    "gn:dem":275,
    "gn:feature_class":"P",
    "gn:feature_code":"PPL",
    "gn:name":"Es Sfin\u00e9",
    "gn:population":0,
    "gn:timezone":"Asia/Beirut",
    "iso:country":"LB",
    "name:und_x_variant":[
        "Es Saf\u00een\u00e9",
        "As Saf\u012bnah",
        "Es Sfin\u00e9"
    ],
    "wof:name":"Es Sfine",
    "wof:placetype":"locality"
},
  "geometry": {"coordinates":[36.15806,34.57222],"type":"Point"}
}