{
  "type": "Feature",
  "properties": {
    "gn:admin1_code":"5.0",
    "gn:asciiname":"Hai ej Jamia",
    "gn:country_code":"LB",
    "gn:dem":745,
    "gn:feature_class":"P",
    "gn:feature_code":"PPL",
    "gn:name":"Ha\u00ef ej Jamia",
    "gn:population":0,
    "gn:timezone":"Asia/Beirut",
    "iso:country":"LB",
    "name:und_x_variant":[
        "\u1e28ayy al J\u0101mi\u2018",
        "Ha\u00ef ej Jamia"
    ],
    "wof:name":"Hai ej Jamia",
    "wof:placetype":"locality"
},
  "geometry": {"coordinates":[35.74167,34.09417],"type":"Point"}
}