{
  "type": "Feature",
  "properties": {
    "gn:admin1_code":"7.0",
    "gn:asciiname":"El Houe",
    "gn:country_code":"LB",
    "gn:dem":582,
    "gn:feature_class":"P",
    "gn:feature_code":"PPL",
    "gn:name":"El Ho\u00fb\u00e9",
    "gn:population":0,
    "gn:timezone":"Asia/Beirut",
    "iso:country":"LB",
    "name:ara_x_preferred":[
        "\u0627\u0644\u0647\u0648\u064a\u0651"
    ],
    "name:und_x_variant":[
        "El Ho\u00fb\u00e9",
        "Al Haw\u012by"
    ],
    "wof:name":"El Houe",
    "wof:placetype":"locality"
},
  "geometry": {"coordinates":[35.46333,33.21444],"type":"Point"}
}