{
  "type": "Feature",
  "properties": {
    "gn:admin1_code":"10.0",
    "gn:asciiname":"Beit Ayoub",
    "gn:country_code":"LB",
    "gn:dem":1047,
    "gn:feature_class":"P",
    "gn:feature_code":"PPL",
    "gn:name":"Be\u00eft Ayo\u00fbb",
    "gn:population":0,
    "gn:timezone":"Asia/Beirut",
    "iso:country":"LB",
    "name:und_x_variant":[
        "Be\u00eft Aiyo\u00fbb",
        "Bayt Ayy\u016bb",
        "Be\u00eft Ayo\u00fbb"
    ],
    "wof:name":"Beit Ayoub",
    "wof:placetype":"locality"
},
  "geometry": {"coordinates":[36.16028,34.47389],"type":"Point"}
}