{
  "type": "Feature",
  "properties": {
    "gn:admin1_code":"5.0",
    "gn:asciiname":"Haret el Aamroussiye",
    "gn:country_code":"LB",
    "gn:dem":142,
    "gn:feature_class":"P",
    "gn:feature_code":"PPL",
    "gn:name":"Haret el Aamroussiy\u00e9",
    "gn:population":0,
    "gn:timezone":"Asia/Beirut",
    "iso:country":"LB",
    "name:ara_x_preferred":[
        "\u062d\u0627\u0631\u0629 \u0627\u0644\u0639\u0645\u0631\u0648\u0633\u064a\u0629"
    ],
    "name:und_x_variant":[
        "Choue\u00eff\u00e2te Amro\u00fbss\u00eey\u00e2te",
        "Al \u2018Amr\u016bs\u012byah",
        "Haret el Aamroussiy\u00e9",
        "\u1e28\u0101rat al \u2018Amr\u016bs\u012byah"
    ],
    "wof:name":"Haret el Aamroussiye",
    "wof:placetype":"locality"
},
  "geometry": {"coordinates":[35.52,33.81083],"type":"Point"}
}