{
  "type": "Feature",
  "properties": {
    "gn:admin1_code":"9.0",
    "gn:asciiname":"Beit Menzer",
    "gn:country_code":"LB",
    "gn:dem":1221,
    "gn:feature_class":"P",
    "gn:feature_code":"PPL",
    "gn:name":"Be\u00eft Menzer",
    "gn:population":0,
    "gn:timezone":"Asia/Beirut",
    "iso:country":"LB",
    "name:ara_x_preferred":[
        "\u0628\u064a\u062a \u0645\u0646\u0630\u0631"
    ],
    "name:und_x_variant":[
        "Bayt Mundhir",
        "Be\u00eft Monnzer",
        "Beit Mounzer",
        "Be\u00eft Menzer"
    ],
    "wof:name":"Beit Menzer",
    "wof:placetype":"locality"
},
  "geometry": {"coordinates":[35.9114,34.26236],"type":"Point"}
}