{
  "type": "Feature",
  "properties": {
    "gn:admin1_code":"8.0",
    "gn:asciiname":"Ez Zaroub",
    "gn:country_code":"LB",
    "gn:dem":1172,
    "gn:feature_class":"P",
    "gn:feature_code":"PPL",
    "gn:name":"Ez Z\u00e2ro\u00fbb",
    "gn:population":0,
    "gn:timezone":"Asia/Beirut",
    "iso:country":"LB",
    "name:ara_x_preferred":[
        "\u0627\u0644\u0632\u0627\u0631\u0648\u0628"
    ],
    "name:und_x_variant":[
        "Az Z\u0101r\u016bb",
        "Ez Z\u00e2ro\u00fbb"
    ],
    "wof:name":"Ez Zaroub",
    "wof:placetype":"locality"
},
  "geometry": {"coordinates":[35.81444000000001,33.57556],"type":"Point"}
}