{
  "type": "Feature",
  "properties": {
    "iso:country":"LB",
    "name:ara_x_colloquial":[
        "Ra's an Naban"
    ],
    "name:ara_x_preferred":[
        "Ra's An Nab\u2019an"
    ],
    "qs:gn_adm0_cc":"LB",
    "qs:gn_local":276781,
    "qs:local_max":1709,
    "qs:local_sum":10240,
    "qs:localhoods":30,
    "qs:name":"Ra's An Nab\u2019an",
    "qs:name_adm0":"\u0644\u0628\u0646\u0627\u0646",
    "qs:name_adm1":"\u062c\u0628\u0644 \u0644\u0628\u0646\u0627\u0646",
    "qs:name_adm2":"\u0628\u0639\u0628\u062f\u0627",
    "qs:name_lau":"\u0627\u0644\u0634\u064a\u0627\u062d",
    "qs:name_local":"\u0628\u064a\u0631\u0648\u062a",
    "qs:photo_max":28,
    "qs:photo_sum":29,
    "qs:placetype":"Suburb",
    "qs:quad_count":2,
    "qs:woe_adm0":23424873,
    "qs:woe_adm1":2346017,
    "qs:woe_adm2":56049615,
    "qs:woe_lau":56411760,
    "qs:woe_local":1960307,
    "qs:woe_ver":"7.10.0",
    "wof:lang":[
        "ara"
    ],
    "wof:name":"Ra's An Nab\u2019an",
    "wof:placetype":"neighbourhood"
},
  "geometry": {"coordinates":[35.4982,33.864638],"type":"Point"}
}