{
  "type": "Feature",
  "properties": {
    "gn:admin1_code":"11.0",
    "gn:asciiname":"Mrah Beit Slim",
    "gn:country_code":"LB",
    "gn:dem":1151,
    "gn:feature_class":"P",
    "gn:feature_code":"PPL",
    "gn:name":"Mr\u00e2h Be\u00eft Sl\u00eem",
    "gn:population":0,
    "gn:timezone":"Asia/Beirut",
    "iso:country":"LB",
    "name:und_x_variant":[
        "Mar\u0101\u1e29 Bayt Sal\u012bm",
        "Mr\u00e2h Be\u00eft Sl\u00eem"
    ],
    "wof:name":"Mrah Beit Slim",
    "wof:placetype":"locality"
},
  "geometry": {"coordinates":[36.04083,34.05778],"type":"Point"}
}