{
  "type": "Feature",
  "properties": {
    "gn:admin1_code":"9.0",
    "gn:asciiname":"Afqa",
    "gn:country_code":"LB",
    "gn:dem":1342,
    "gn:feature_class":"P",
    "gn:feature_code":"PPL",
    "gn:name":"Afqa",
    "gn:population":0,
    "gn:timezone":"Asia/Beirut",
    "iso:country":"LB",
    "name:ara_x_preferred":[
        "\u0623\u0641\u0642\u0627"
    ],
    "name:ara_x_variant":[
        "Afq\u0101"
    ],
    "name:deu_x_preferred":[
        "Afqa-Grotte"
    ],
    "name:fra_x_preferred":[
        "Grotte d'Afqa"
    ],
    "name:ita_x_preferred":[
        "Grotte d'Afqa"
    ],
    "name:nno_x_preferred":[
        "Afqa"
    ],
    "wof:name":"Afqa",
    "wof:placetype":"locality"
},
  "geometry": {"coordinates":[35.98618,34.32464],"type":"Point"}
}