{
  "type": "Feature",
  "properties": {
    "gn:admin1_code":"5.0",
    "gn:asciiname":"Ftaihat el Qarqouf",
    "gn:country_code":"LB",
    "gn:dem":759,
    "gn:feature_class":"P",
    "gn:feature_code":"PPL",
    "gn:name":"Fta\u00efh\u00e2t el Qarqo\u00fbf",
    "gn:population":0,
    "gn:timezone":"Asia/Beirut",
    "iso:country":"LB",
    "name:und_x_variant":[
        "Futay\u1e29\u0101t al Qarq\u016bf",
        "Fta\u00efh\u00e2t el Qarqo\u00fbf"
    ],
    "wof:name":"Ftaihat el Qarqouf",
    "wof:placetype":"locality"
},
  "geometry": {"coordinates":[35.66639,33.98611],"type":"Point"}
}