{
  "type": "Feature",
  "properties": {
    "gn:admin1_code":"8.0",
    "gn:asciiname":"Deir el Ghazaal",
    "gn:country_code":"LB",
    "gn:dem":1105,
    "gn:feature_class":"P",
    "gn:feature_code":"PPL",
    "gn:name":"De\u00efr el Ghazaal",
    "gn:population":0,
    "gn:timezone":"Asia/Beirut",
    "iso:country":"LB",
    "name:ara_x_preferred":[
        "\u062f\u064a\u0631 \u0627\u0644\u063a\u0632\u0627\u0644"
    ],
    "name:und_x_variant":[
        "De\u00efr el Rhazal",
        "De\u00efr er Razel",
        "Deir el Ghazal",
        "Dayr al Ghaz\u0101l",
        "De\u00efr el Ghazaal"
    ],
    "wof:name":"Deir el Ghazaal",
    "wof:placetype":"locality"
},
  "geometry": {"coordinates":[36.03389,33.82444],"type":"Point"}
}