{
  "type": "Feature",
  "properties": {
    "gn:admin1_code":"5.0",
    "gn:asciiname":"El Ouadi",
    "gn:country_code":"LB",
    "gn:dem":1327,
    "gn:feature_class":"P",
    "gn:feature_code":"PPL",
    "gn:name":"El Ou\u00e2di",
    "gn:population":0,
    "gn:timezone":"Asia/Beirut",
    "iso:country":"LB",
    "name:und_x_variant":[
        "Al W\u0101d\u012b",
        "El Ou\u00e2di"
    ],
    "wof:name":"El Ouadi",
    "wof:placetype":"locality"
},
  "geometry": {"coordinates":[35.80028,34.02222],"type":"Point"}
}