{
  "type": "Feature",
  "properties": {
    "iso:country":"LB",
    "qs:gn_pop":0,
    "qs:name":"\u0632\u063a\u0631\u062a\u0627",
    "qs:name_adm0":"\u0644\u0628\u0646\u0627\u0646",
    "qs:name_adm1":"\u0627\u0644\u0634\u0645\u0627\u0644",
    "qs:photos":9,
    "qs:photos_1k":2,
    "qs:photos_9k":1,
    "qs:photos_9r":1,
    "qs:photos_all":9,
    "qs:photos_sr":1,
    "qs:placetype":"Town",
    "qs:pop_sr":"0",
    "qs:woe_adm0":23424873,
    "wof:name":"\u0632\u063a\u0631\u062a\u0627",
    "wof:placetype":"locality"
},
  "geometry": {"coordinates":[35.914134,34.379145],"type":"Point"}
}