{
  "type": "Feature",
  "properties": {
    "gn:admin1_code":"5.0",
    "gn:asciiname":"Maydan az Zayr",
    "gn:country_code":"LB",
    "gn:dem":33,
    "gn:feature_class":"P",
    "gn:feature_code":"PPL",
    "gn:name":"Mayd\u0101n az Zayr",
    "gn:population":0,
    "gn:timezone":"Asia/Beirut",
    "iso:country":"LB",
    "name:ara_x_preferred":[
        "\u0645\u064a\u062f\u0627\u0646 \u0627\u0644\u0632\u064a\u0631"
    ],
    "name:und_x_variant":[
        "Mayd\u0101n az Zayr",
        "M\u012bd\u0101n az Z\u012br",
        "Mayd\u0101n az Z\u012br"
    ],
    "wof:name":"Maydan az Zayr",
    "wof:placetype":"locality"
},
  "geometry": {"coordinates":[35.45857,33.7576],"type":"Point"}
}