{
  "type": "Feature",
  "properties": {
    "gn:admin1_code":"5.0",
    "gn:asciiname":"Yatoun el Kharroube",
    "gn:country_code":"LB",
    "gn:dem":458,
    "gn:feature_class":"P",
    "gn:feature_code":"PPL",
    "gn:name":"Yatoun el Kharroub\u00e9",
    "gn:population":0,
    "gn:timezone":"Asia/Beirut",
    "iso:country":"LB",
    "name:ara_x_preferred":[
        "\u064a\u0627\u062a\u0648\u0646 \u0627\u0644\u062e\u0631\u0648\u0628\u0629"
    ],
    "name:und_x_variant":[
        "Yatoun el Kharroub\u00e9",
        "Y\u0101t\u016bn al Kharr\u016bbah"
    ],
    "wof:name":"Yatoun el Kharroube",
    "wof:placetype":"locality"
},
  "geometry": {"coordinates":[35.58944,33.86333],"type":"Point"}
}