{
  "type": "Feature",
  "properties": {
    "gn:admin1_code":"5.0",
    "gn:asciiname":"Ghommas Youssef",
    "gn:country_code":"LB",
    "gn:dem":1180,
    "gn:feature_class":"P",
    "gn:feature_code":"PPL",
    "gn:name":"Ghomm\u00e2s Yo\u00fbssef",
    "gn:population":0,
    "gn:timezone":"Asia/Beirut",
    "iso:country":"LB",
    "name:und_x_variant":[
        "Ghamm\u0101s Y\u016bsuf",
        "Ghomm\u00e2s Yo\u00fbssef"
    ],
    "wof:name":"Ghommas Youssef",
    "wof:placetype":"locality"
},
  "geometry": {"coordinates":[35.77528,34.13944],"type":"Point"}
}