{
  "type": "Feature",
  "properties": {
    "gn:admin1_code":"5.0",
    "gn:asciiname":"Haret el Mjadle",
    "gn:country_code":"LB",
    "gn:dem":34,
    "gn:feature_class":"P",
    "gn:feature_code":"PPL",
    "gn:name":"Haret el Mjadl\u00e9",
    "gn:population":0,
    "gn:timezone":"Asia/Beirut",
    "iso:country":"LB",
    "name:ara_x_preferred":[
        "\u062d\u0627\u0631\u0629 \u0627\u0644\u0645\u062c\u0627\u062f\u0644\u0629"
    ],
    "name:und_x_variant":[
        "Haret el Mjadl\u00e9",
        "\u1e28\u0101rat al Muj\u0101dalah"
    ],
    "wof:name":"Haret el Mjadle",
    "wof:placetype":"locality"
},
  "geometry": {"coordinates":[35.52778,33.86083],"type":"Point"}
}