{
  "type": "Feature",
  "properties": {
    "gn:admin1_code":"11.0",
    "gn:asciiname":"Tallet ed Deir",
    "gn:country_code":"LB",
    "gn:dem":828,
    "gn:feature_class":"P",
    "gn:feature_code":"PPL",
    "gn:name":"Tallet ed De\u00efr",
    "gn:population":0,
    "gn:timezone":"Asia/Beirut",
    "iso:country":"LB",
    "name:und_x_variant":[
        "Jabbo\u00fbl\u00e9",
        "Tallat ad Dayr",
        "Tallet ed De\u00efr"
    ],
    "wof:name":"Tallet ed Deir",
    "wof:placetype":"locality"
},
  "geometry": {"coordinates":[36.34278,34.23083],"type":"Point"}
}