{
  "type": "Feature",
  "properties": {
    "gn:admin1_code":"6.0",
    "gn:asciiname":"Maarake",
    "gn:country_code":"LB",
    "gn:dem":270,
    "gn:feature_class":"P",
    "gn:feature_code":"PPL",
    "gn:name":"Maarak\u00e9",
    "gn:population":0,
    "gn:timezone":"Asia/Beirut",
    "iso:country":"LB",
    "name:ara_x_preferred":[
        "\u0645\u0639\u0631\u0643\u0629"
    ],
    "name:und_x_variant":[
        "Ma\u2018rak\u012b",
        "Ma\u2018rakah",
        "Maarak\u00e9"
    ],
    "wof:name":"Maarake",
    "wof:placetype":"locality"
},
  "geometry": {"coordinates":[35.30860999999999,33.27306],"type":"Point"}
}