{
  "type": "Feature",
  "properties": {
    "gn:admin1_code":"9.0",
    "gn:asciiname":"Ouata Mansour",
    "gn:country_code":"LB",
    "gn:dem":548,
    "gn:feature_class":"P",
    "gn:feature_code":"PPL",
    "gn:name":"Ouata Manso\u00fbr",
    "gn:population":0,
    "gn:timezone":"Asia/Beirut",
    "iso:country":"LB",
    "name:und_x_variant":[
        "Wa\u0163\u0101\u2019 Man\u015f\u016br",
        "Ouata Manso\u00fbr"
    ],
    "wof:name":"Ouata Mansour",
    "wof:placetype":"locality"
},
  "geometry": {"coordinates":[35.71611,34.19833],"type":"Point"}
}