{
  "type": "Feature",
  "properties": {
    "gn:admin1_code":"5.0",
    "gn:asciiname":"Haret Al Naame",
    "gn:country_code":"LB",
    "gn:dem":37,
    "gn:feature_class":"P",
    "gn:feature_code":"PPL",
    "gn:name":"Haret Al Naame",
    "gn:population":0,
    "gn:timezone":"Asia/Beirut",
    "iso:country":"LB",
    "wof:name":"Haret Al Naame",
    "wof:placetype":"locality"
},
  "geometry": {"coordinates":[35.45525,33.73913],"type":"Point"}
}