{
  "type": "Feature",
  "properties": {
    "gn:admin1_code":"9.0",
    "gn:asciiname":"Aassoun",
    "gn:country_code":"LB",
    "gn:dem":943,
    "gn:feature_class":"P",
    "gn:feature_code":"PPL",
    "gn:name":"A\u00e2sso\u00fbn",
    "gn:population":0,
    "gn:timezone":"Asia/Beirut",
    "iso:country":"LB",
    "name:und_x_variant":[
        "A\u00e2ss\u00fbn",
        "Assoun",
        "A\u015fn\u016bn",
        "\u2018\u0100\u015f\u016bn",
        "A\u00e2sso\u00fbn"
    ],
    "wof:name":"Aassoun",
    "wof:placetype":"locality"
},
  "geometry": {"coordinates":[36.01278,34.38583],"type":"Point"}
}