{
  "type": "Feature",
  "properties": {
    "gn:admin1_code":"5.0",
    "gn:asciiname":"Ech Chaoualiq",
    "gn:country_code":"LB",
    "gn:dem":536,
    "gn:feature_class":"P",
    "gn:feature_code":"PPL",
    "gn:name":"Ech Chaou\u00e2l\u00eeq",
    "gn:population":0,
    "gn:timezone":"Asia/Beirut",
    "iso:country":"LB",
    "name:ara_x_preferred":[
        "\u0627\u0644\u0634\u0648\u0627\u0644\u064a\u0642"
    ],
    "name:und_x_variant":[
        "Ash Shaw\u0101l\u012bq",
        "Ech Chaou\u00e2l\u00eeq"
    ],
    "wof:name":"Ech Chaoualiq",
    "wof:placetype":"locality"
},
  "geometry": {"coordinates":[35.54194000000001,33.69028],"type":"Point"}
}