{
  "type": "Feature",
  "properties": {
    "gn:admin1_code":"5.0",
    "gn:asciiname":"Mgharet Obeid",
    "gn:country_code":"LB",
    "gn:dem":705,
    "gn:feature_class":"P",
    "gn:feature_code":"PPL",
    "gn:name":"Mgharet Obeid",
    "gn:population":0,
    "gn:timezone":"Asia/Beirut",
    "iso:country":"LB",
    "name:und_x_variant":[
        "Magh\u0101rat \u2018Ubayd",
        "Mgharet Obeid"
    ],
    "wof:name":"Mgharet Obeid",
    "wof:placetype":"locality"
},
  "geometry": {"coordinates":[35.75722000000001,34.17972],"type":"Point"}
}