{
  "type": "Feature",
  "properties": {
    "gn:admin1_code":"5.0",
    "gn:asciiname":"Bersaissa",
    "gn:country_code":"LB",
    "gn:dem":1166,
    "gn:feature_class":"P",
    "gn:feature_code":"PPL",
    "gn:name":"Bersa\u00efssa",
    "gn:population":0,
    "gn:timezone":"Asia/Beirut",
    "iso:country":"LB",
    "name:und_x_variant":[
        "Barsays\u0101",
        "Bersa\u00efssa"
    ],
    "wof:name":"Bersaissa",
    "wof:placetype":"locality"
},
  "geometry": {"coordinates":[35.78083,34.12278],"type":"Point"}
}