{
  "type": "Feature",
  "properties": {
    "gn:admin1_code":"5.0",
    "gn:asciiname":"Haql el Baida",
    "gn:country_code":"LB",
    "gn:dem":1533,
    "gn:feature_class":"P",
    "gn:feature_code":"PPL",
    "gn:name":"Haql el Ba\u00efda",
    "gn:population":0,
    "gn:timezone":"Asia/Beirut",
    "iso:country":"LB",
    "name:und_x_variant":[
        "\u1e28aql al Bay\u1e11ah",
        "Haql el Ba\u00efda"
    ],
    "wof:name":"Haql el Baida",
    "wof:placetype":"locality"
},
  "geometry": {"coordinates":[35.80778,33.89778],"type":"Point"}
}