{
  "type": "Feature",
  "properties": {
    "gn:admin1_code":"6.0",
    "gn:asciiname":"Arzai",
    "gn:country_code":"LB",
    "gn:dem":256,
    "gn:feature_class":"P",
    "gn:feature_code":"PPL",
    "gn:name":"Arza\u00ef",
    "gn:population":0,
    "gn:timezone":"Asia/Beirut",
    "iso:country":"LB",
    "name:ara_x_preferred":[
        "\u0623\u0631\u0632\u064a"
    ],
    "name:und_x_variant":[
        "Irzay",
        "Arza\u00ef",
        "Arz\u012b"
    ],
    "wof:name":"Arzai",
    "wof:placetype":"locality"
},
  "geometry": {"coordinates":[35.29861,33.33306],"type":"Point"}
}