{
  "type": "Feature",
  "properties": {
    "gn:admin1_code":"5.0",
    "gn:asciiname":"Ez Zire",
    "gn:country_code":"LB",
    "gn:dem":107,
    "gn:feature_class":"P",
    "gn:feature_code":"PPL",
    "gn:name":"Ez Zir\u00e9",
    "gn:population":0,
    "gn:timezone":"Asia/Beirut",
    "iso:country":"LB",
    "name:ara_x_preferred":[
        "\u0627\u0644\u0632\u064a\u0631\u0629"
    ],
    "name:und_x_variant":[
        "Ez Zir\u00e9",
        "Az Z\u012brah"
    ],
    "wof:name":"Ez Zire",
    "wof:placetype":"locality"
},
  "geometry": {"coordinates":[35.57472,33.84083],"type":"Point"}
}