{
  "type": "Feature",
  "properties": {
    "gn:admin1_code":"6.0",
    "gn:asciiname":"Tanbourit",
    "gn:country_code":"LB",
    "gn:dem":304,
    "gn:feature_class":"P",
    "gn:feature_code":"PPL",
    "gn:name":"Tanbour\u00eet",
    "gn:population":0,
    "gn:timezone":"Asia/Beirut",
    "iso:country":"LB",
    "name:ara_x_preferred":[
        "\u0637\u0646\u0628\u0648\u0631\u064a\u062a"
    ],
    "name:und_x_variant":[
        "\u0162anb\u016br\u012bt",
        "Tanbour\u00eet"
    ],
    "wof:name":"Tanbourit",
    "wof:placetype":"locality"
},
  "geometry": {"coordinates":[35.41528,33.51611],"type":"Point"}
}