{
  "type": "Feature",
  "properties": {
    "gn:admin1_code":"6.0",
    "gn:asciiname":"Bafliye",
    "gn:country_code":"LB",
    "gn:dem":320,
    "gn:feature_class":"P",
    "gn:feature_code":"PPL",
    "gn:name":"B\u00e2fliy\u00e9",
    "gn:population":0,
    "gn:timezone":"Asia/Beirut",
    "iso:country":"LB",
    "name:ara_x_preferred":[
        "\u0628\u0627\u0641\u0644\u064a\u0629"
    ],
    "name:und_x_variant":[
        "B\u0101fil\u012byah",
        "B\u0101fl\u012byah",
        "B\u00e2fliy\u00e9",
        "BAFLIEH"
    ],
    "wof:name":"Bafliye",
    "wof:placetype":"locality"
},
  "geometry": {"coordinates":[35.36667,33.26139000000001],"type":"Point"}
}