{
  "type": "Feature",
  "properties": {
    "gn:admin1_code":"5.0",
    "gn:asciiname":"El Ksayer",
    "gn:country_code":"LB",
    "gn:dem":656,
    "gn:feature_class":"P",
    "gn:feature_code":"PPL",
    "gn:name":"El Ks\u00e2yer",
    "gn:population":0,
    "gn:timezone":"Asia/Beirut",
    "iso:country":"LB",
    "wof:name":"El Ksayer",
    "wof:placetype":"locality"
},
  "geometry": {"coordinates":[35.695,33.94222],"type":"Point"}
}