{
  "type": "Feature",
  "properties": {
    "gn:admin1_code":"5.0",
    "gn:asciiname":"Ghalboun",
    "gn:country_code":"LB",
    "gn:dem":458,
    "gn:feature_class":"P",
    "gn:feature_code":"PPL",
    "gn:name":"Ghalbo\u00fbn",
    "gn:population":0,
    "gn:timezone":"Asia/Beirut",
    "iso:country":"LB",
    "name:ara_x_preferred":[
        "\u063a\u0644\u0628\u0648\u0646"
    ],
    "name:und_x_variant":[
        "Ghalb\u016bn",
        "Ghalbo\u00fbn"
    ],
    "wof:name":"Ghalboun",
    "wof:placetype":"locality"
},
  "geometry": {"coordinates":[35.70306,34.17472],"type":"Point"}
}