{
  "type": "Feature",
  "properties": {
    "gn:admin1_code":"11.0",
    "gn:asciiname":"Ham",
    "gn:country_code":"LB",
    "gn:dem":1465,
    "gn:feature_class":"P",
    "gn:feature_code":"PPL",
    "gn:name":"H\u00e2m",
    "gn:population":0,
    "gn:timezone":"Asia/Beirut",
    "iso:country":"LB",
    "wof:name":"Ham",
    "wof:placetype":"locality"
},
  "geometry": {"coordinates":[36.20194,33.87361],"type":"Point"}
}