{
  "type": "Feature",
  "properties": {
    "gn:admin1_code":"9.0",
    "gn:asciiname":"Sourat",
    "gn:country_code":"LB",
    "gn:dem":388,
    "gn:feature_class":"P",
    "gn:feature_code":"PPL",
    "gn:name":"Sourat",
    "gn:population":0,
    "gn:timezone":"Asia/Beirut",
    "iso:country":"LB",
    "name:ara_x_preferred":[
        "\u0635\u0648\u0631\u0627\u062a"
    ],
    "name:ara_x_variant":[
        "\u015e\u016br\u0101t"
    ],
    "wof:name":"Sourat",
    "wof:placetype":"locality"
},
  "geometry": {"coordinates":[35.68162,34.16506],"type":"Point"}
}