{
  "type": "Feature",
  "properties": {
    "gn:admin1_code":"6.0",
    "gn:asciiname":"Kfar Chellal",
    "gn:country_code":"LB",
    "gn:dem":350,
    "gn:feature_class":"P",
    "gn:feature_code":"PPL",
    "gn:name":"Kfar Chell\u00e2l",
    "gn:population":0,
    "gn:timezone":"Asia/Beirut",
    "iso:country":"LB",
    "name:ara_x_preferred":[
        "\u0643\u0641\u0631 \u0634\u0644\u0627\u0644"
    ],
    "name:und_x_variant":[
        "Kafr Shill\u0101l",
        "Kfar Chell\u00e2l",
        "Kafr Shall\u0101l"
    ],
    "wof:name":"Kfar Chellal",
    "wof:placetype":"locality"
},
  "geometry": {"coordinates":[35.46861,33.49299],"type":"Point"}
}