{
  "type": "Feature",
  "properties": {
    "gn:admin1_code":"9.0",
    "gn:asciiname":"Bchennata",
    "gn:country_code":"LB",
    "gn:dem":1352,
    "gn:feature_class":"P",
    "gn:feature_code":"PPL",
    "gn:name":"Bchenn\u00e2ta",
    "gn:population":0,
    "gn:timezone":"Asia/Beirut",
    "iso:country":"LB",
    "name:ara_x_preferred":[
        "\u0628\u0634\u0646\u0627\u062a\u0627"
    ],
    "name:ara_x_variant":[
        "Bishinn\u0101t\u0101"
    ],
    "name:und_x_variant":[
        "Bshinn\u0101t\u0101",
        "Bchenn\u00e2te",
        "Bchenn\u00e2ta"
    ],
    "wof:name":"Bchennata",
    "wof:placetype":"locality"
},
  "geometry": {"coordinates":[35.98848,34.34413],"type":"Point"}
}