{
  "type": "Feature",
  "properties": {
    "gn:admin1_code":"5.0",
    "gn:asciiname":"El Ftehat",
    "gn:country_code":"LB",
    "gn:dem":958,
    "gn:feature_class":"P",
    "gn:feature_code":"PPL",
    "gn:name":"El Ft\u00eah\u00e2t",
    "gn:population":0,
    "gn:timezone":"Asia/Beirut",
    "iso:country":"LB",
    "name:und_x_variant":[
        "Al Ft\u0101\u1e29\u0101t",
        "El Ft\u00eah\u00e2t"
    ],
    "wof:name":"El Ftehat",
    "wof:placetype":"locality"
},
  "geometry": {"coordinates":[35.71583,34.045],"type":"Point"}
}