{
  "type": "Feature",
  "properties": {
    "gn:admin1_code":"9.0",
    "gn:asciiname":"Zakroun",
    "gn:country_code":"LB",
    "gn:dem":143,
    "gn:feature_class":"P",
    "gn:feature_code":"PPL",
    "gn:name":"Zakro\u00fbn",
    "gn:population":0,
    "gn:timezone":"Asia/Beirut",
    "iso:country":"LB",
    "name:ara_x_preferred":[
        "\u0632\u0643\u0631\u0648\u0646"
    ],
    "name:nno_x_preferred":[
        "Zakroun"
    ],
    "name:und_x_variant":[
        "Zakr\u016bn",
        "Zakro\u00fbn"
    ],
    "wof:name":"Zakroun",
    "wof:placetype":"locality"
},
  "geometry": {"coordinates":[35.75472,34.35194],"type":"Point"}
}