{
  "type": "Feature",
  "properties": {
    "gn:admin1_code":"8.0",
    "gn:asciiname":"Kafraiya",
    "gn:country_code":"LB",
    "gn:dem":1042,
    "gn:feature_class":"P",
    "gn:feature_code":"PPL",
    "gn:name":"Kafraiya",
    "gn:population":0,
    "gn:timezone":"Asia/Beirut",
    "iso:country":"LB",
    "name:ara_x_preferred":[
        "\u0643\u0641\u0631\u064a\u0627"
    ],
    "name:fra_x_preferred":[
        "Kefraya"
    ],
    "name:ita_x_preferred":[
        "Kefraya"
    ],
    "name:nno_x_preferred":[
        "Kefraya"
    ],
    "name:und_x_variant":[
        "Kefraya"
    ],
    "wof:name":"Kafraiya",
    "wof:placetype":"locality"
},
  "geometry": {"coordinates":[35.73667000000001,33.67099],"type":"Point"}
}