{
  "type": "Feature",
  "properties": {
    "gn:admin1_code":"5.0",
    "gn:asciiname":"Hazmiyeh",
    "gn:country_code":"LB",
    "gn:dem":85,
    "gn:feature_class":"P",
    "gn:feature_code":"PPL",
    "gn:name":"Hazmiyeh",
    "gn:population":0,
    "gn:timezone":"Asia/Beirut",
    "iso:country":"LB",
    "name:und_x_variant":[
        "Hazmieh"
    ],
    "wof:name":"Hazmiyeh",
    "wof:placetype":"locality"
},
  "geometry": {"coordinates":[35.53589,33.85534000000001],"type":"Point"}
}