{
  "type": "Feature",
  "properties": {
    "gn:admin1_code":"5.0",
    "gn:asciiname":"Bolhos",
    "gn:country_code":"LB",
    "gn:dem":1140,
    "gn:feature_class":"P",
    "gn:feature_code":"PPL",
    "gn:name":"Bolhos",
    "gn:population":0,
    "gn:timezone":"Asia/Beirut",
    "iso:country":"LB",
    "name:ara_x_preferred":[
        "\u0628\u0644\u062d\u0635"
    ],
    "name:und_x_variant":[
        "Bolhass",
        "Balh\u00e2s",
        "Bul\u1e29u\u015f",
        "Bolhos"
    ],
    "wof:name":"Bolhos",
    "wof:placetype":"locality"
},
  "geometry": {"coordinates":[35.80843,34.0939],"type":"Point"}
}