{
  "type": "Feature",
  "properties": {
    "gn:admin1_code":"6.0",
    "gn:asciiname":"Hanaouay",
    "gn:country_code":"LB",
    "gn:dem":256,
    "gn:feature_class":"P",
    "gn:feature_code":"PPL",
    "gn:name":"Han\u00e2ou\u00e2y",
    "gn:population":0,
    "gn:timezone":"Asia/Beirut",
    "iso:country":"LB",
    "name:ara_x_preferred":[
        "\u062d\u0646\u0627\u0648\u064a\u0629"
    ],
    "name:ara_x_variant":[
        "\u062d\u0646\u0627\u0648\u064a\u0647"
    ],
    "name:ita_x_preferred":[
        "Hanawey"
    ],
    "name:und_x_variant":[
        "Han\u00e2ouiy\u00e9",
        "\u1e28an\u0101w\u012byih",
        "\u1e28ann\u0101w\u012byah",
        "Han\u00e2ou\u00e2y",
        "HANAWEH"
    ],
    "wof:name":"Hanaouay",
    "wof:placetype":"locality"
},
  "geometry": {"coordinates":[35.27722,33.22111],"type":"Point"}
}