{
  "type": "Feature",
  "properties": {
    "gn:admin1_code":"6.0",
    "gn:asciiname":"Jamjim et Tahta",
    "gn:country_code":"LB",
    "gn:dem":136,
    "gn:feature_class":"P",
    "gn:feature_code":"PPL",
    "gn:name":"Jamj\u00eem et Tahta",
    "gn:population":0,
    "gn:timezone":"Asia/Beirut",
    "iso:country":"LB",
    "name:ara_x_preferred":[
        "\u062c\u0645\u062c\u064a\u0645 \u0627\u0644\u062a\u062d\u062a\u0627"
    ],
    "name:und_x_variant":[
        "Jamj\u012bm at Ta\u1e29t\u0101",
        "Jamj\u00eem et Tahta"
    ],
    "wof:name":"Jamjim et Tahta",
    "wof:placetype":"locality"
},
  "geometry": {"coordinates":[35.27405,33.35947],"type":"Point"}
}