{
  "type": "Feature",
  "properties": {
    "gn:admin1_code":"5.0",
    "gn:asciiname":"Dahr el Ain",
    "gn:country_code":"LB",
    "gn:dem":549,
    "gn:feature_class":"P",
    "gn:feature_code":"PPL",
    "gn:name":"Dahr el A\u00efn",
    "gn:population":0,
    "gn:timezone":"Asia/Beirut",
    "iso:country":"LB",
    "name:und_x_variant":[
        "\u1e10ahr al \u2018Ayn",
        "Dahr el A\u00efn"
    ],
    "wof:name":"Dahr el Ain",
    "wof:placetype":"locality"
},
  "geometry": {"coordinates":[35.715,34.17778],"type":"Point"}
}