{
  "type": "Feature",
  "properties": {
    "gn:admin1_code":"9.0",
    "gn:asciiname":"Kfar Chakhna",
    "gn:country_code":"LB",
    "gn:dem":204,
    "gn:feature_class":"P",
    "gn:feature_code":"PPL",
    "gn:name":"Kfar Chakhna",
    "gn:population":0,
    "gn:timezone":"Asia/Beirut",
    "iso:country":"LB",
    "name:ara_x_preferred":[
        "\u0643\u0641\u0631 \u0634\u062e\u0646\u0627"
    ],
    "name:ara_x_variant":[
        "\u0643\u0641\u0631\u0634\u062e\u0646\u0627"
    ],
    "name:und_x_variant":[
        "Kafr Shikhn\u0101",
        "Kfar Chakhna"
    ],
    "wof:name":"Kfar Chakhna",
    "wof:placetype":"locality"
},
  "geometry": {"coordinates":[35.86472,34.36417],"type":"Point"}
}