{
  "type": "Feature",
  "properties": {
    "gn:admin1_code":"5.0",
    "gn:asciiname":"Sibnai",
    "gn:country_code":"LB",
    "gn:dem":213,
    "gn:feature_class":"P",
    "gn:feature_code":"PPL",
    "gn:name":"Sibna\u00ef",
    "gn:population":0,
    "gn:timezone":"Asia/Beirut",
    "iso:country":"LB",
    "name:ara_x_preferred":[
        "\u0633\u0628\u0646\u064a\u0629"
    ],
    "name:und_x_variant":[
        "Sibna\u00ef",
        "Sibnay",
        "Sibn\u012byah"
    ],
    "wof:name":"Sibnai",
    "wof:placetype":"locality"
},
  "geometry": {"coordinates":[35.53972,33.83056],"type":"Point"}
}