{
  "type": "Feature",
  "properties": {
    "gn:admin1_code":"7.0",
    "gn:asciiname":"Khirbet Selm",
    "gn:country_code":"LB",
    "gn:dem":460,
    "gn:feature_class":"P",
    "gn:feature_code":"PPL",
    "gn:name":"Khirbet Selm",
    "gn:population":0,
    "gn:timezone":"Asia/Beirut",
    "iso:country":"LB",
    "name:ara_x_preferred":[
        "\u062e\u0631\u0628\u0629 \u0633\u0644\u0645"
    ],
    "name:fas_x_preferred":[
        "\u062e\u0631\u0628\u062a \u0633\u0644\u0645"
    ],
    "name:ita_x_preferred":[
        "Khirbet Selm"
    ],
    "name:nno_x_preferred":[
        "Khirbet Selm"
    ],
    "name:und_x_variant":[
        "Khirbat Silm",
        "Khirbat Salm"
    ],
    "wof:name":"Khirbet Selm",
    "wof:placetype":"locality"
},
  "geometry": {"coordinates":[35.42407,33.22931],"type":"Point"}
}