{
  "type": "Feature",
  "properties": {
    "gn:admin1_code":"5.0",
    "gn:asciiname":"Es Salhiye",
    "gn:country_code":"LB",
    "gn:dem":509,
    "gn:feature_class":"P",
    "gn:feature_code":"PPL",
    "gn:name":"Es Salh\u00eey\u00e9",
    "gn:population":0,
    "gn:timezone":"Asia/Beirut",
    "iso:country":"LB",
    "name:ara_x_preferred":[
        "\u0627\u0644\u0635\u0627\u0644\u062d\u064a\u0629"
    ],
    "name:ara_x_variant":[
        "\u0639\u064a\u0646 \u0627\u0644\u0635\u0627\u0644\u062d\u064a\u0629"
    ],
    "name:und_x_variant":[
        "Ain Sla\u00efy\u00e9",
        "\u2018Ain es-Salhiyah",
        "Ain Sla\u00efe",
        "Ain Essalhiye",
        "\u2018Ayn a\u015f \u015e\u0101li\u1e29\u012byah",
        "Es Salh\u00eey\u00e9",
        "A\u015f \u015e\u0101li\u1e29\u012byah"
    ],
    "wof:name":"Es Salhiye",
    "wof:placetype":"locality"
},
  "geometry": {"coordinates":[35.71305,34.07605],"type":"Point"}
}