{
  "type": "Feature",
  "properties": {
    "gn:admin1_code":"5.0",
    "gn:asciiname":"El Moukhada",
    "gn:country_code":"LB",
    "gn:dem":1546,
    "gn:feature_class":"P",
    "gn:feature_code":"PPL",
    "gn:name":"El Moukh\u00e2da",
    "gn:population":0,
    "gn:timezone":"Asia/Beirut",
    "iso:country":"LB",
    "name:ara_x_preferred":[
        "\u0627\u0644\u0645\u062e\u0627\u0636\u0629"
    ],
    "name:und_x_variant":[
        "El Mikhadah",
        "El Mour\u00e2da",
        "Al Makh\u0101\u1e11ah",
        "El Moukh\u00e2da"
    ],
    "wof:name":"El Moukhada",
    "wof:placetype":"locality"
},
  "geometry": {"coordinates":[35.84472,34.13278],"type":"Point"}
}