{
  "type": "Feature",
  "properties": {
    "gn:admin1_code":"11.0",
    "gn:asciiname":"Douris",
    "gn:country_code":"LB",
    "gn:dem":1120,
    "gn:feature_class":"P",
    "gn:feature_code":"PPL",
    "gn:name":"Do\u00fbris",
    "gn:population":0,
    "gn:timezone":"Asia/Beirut",
    "iso:country":"LB",
    "name:und_x_variant":[
        "Do\u00fbriss",
        "D\u016bris",
        "Do\u00fbris"
    ],
    "wof:name":"Douris",
    "wof:placetype":"locality"
},
  "geometry": {"coordinates":[36.17917,33.98778],"type":"Point"}
}