{
  "type": "Feature",
  "properties": {
    "gn:admin1_code":"10.0",
    "gn:asciiname":"Er Raouda",
    "gn:country_code":"LB",
    "gn:dem":304,
    "gn:feature_class":"P",
    "gn:feature_code":"PPL",
    "gn:name":"Er Raouda",
    "gn:population":0,
    "gn:timezone":"Asia/Beirut",
    "iso:country":"LB",
    "name:ara_x_preferred":[
        "\u0627\u0644\u0631\u0648\u0636\u0629"
    ],
    "name:und_x_variant":[
        "Ar Raw\u1e11ah"
    ],
    "wof:name":"Er Raouda",
    "wof:placetype":"locality"
},
  "geometry": {"coordinates":[35.97942000000001,34.4473],"type":"Point"}
}