{
  "type": "Feature",
  "properties": {
    "gn:admin1_code":"5.0",
    "gn:asciiname":"Ej Jerbane",
    "gn:country_code":"LB",
    "gn:dem":253,
    "gn:feature_class":"P",
    "gn:feature_code":"PPL",
    "gn:name":"Ej Jerb\u00e2n\u00e9",
    "gn:population":0,
    "gn:timezone":"Asia/Beirut",
    "iso:country":"LB",
    "name:ara_x_preferred":[
        "\u0627\u0644\u062c\u0631\u0628\u0627\u0646\u0629"
    ],
    "name:und_x_variant":[
        "Ej Jerb\u00e2n\u00e9",
        "Al Jarb\u0101nah"
    ],
    "wof:name":"Ej Jerbane",
    "wof:placetype":"locality"
},
  "geometry": {"coordinates":[35.52833,33.70667],"type":"Point"}
}