{
  "type": "Feature",
  "properties": {
    "gn:admin1_code":"11.0",
    "gn:asciiname":"Iaat",
    "gn:country_code":"LB",
    "gn:dem":1046,
    "gn:feature_class":"P",
    "gn:feature_code":"PPL",
    "gn:name":"\u00cea\u00e2t",
    "gn:population":0,
    "gn:timezone":"Asia/Beirut",
    "iso:country":"LB",
    "name:ara_x_preferred":[
        "\u0625\u064a\u0639\u0627\u062a"
    ],
    "name:ita_x_preferred":[
        "Iaat"
    ],
    "name:nno_x_preferred":[
        "Iaat"
    ],
    "name:und_x_variant":[
        "Ay\u2018\u0101t",
        "\u012a\u2018\u0101t",
        "\u00cea\u00e2t",
        "Ya'ad"
    ],
    "wof:name":"Iaat",
    "wof:placetype":"locality"
},
  "geometry": {"coordinates":[36.17139,34.03694],"type":"Point"}
}