{
  "type": "Feature",
  "properties": {
    "gn:admin1_code":"5.0",
    "gn:asciiname":"Mihqane Salloum",
    "gn:country_code":"LB",
    "gn:dem":1338,
    "gn:feature_class":"P",
    "gn:feature_code":"PPL",
    "gn:name":"Mihq\u00e2ne Sallo\u00fbm",
    "gn:population":0,
    "gn:timezone":"Asia/Beirut",
    "iso:country":"LB",
    "name:und_x_variant":[
        "Mi\u1e29q\u0101n Sall\u016bm",
        "Mihq\u00e2ne Sallo\u00fbm"
    ],
    "wof:name":"Mihqane Salloum",
    "wof:placetype":"locality"
},
  "geometry": {"coordinates":[35.78111,34.02444000000001],"type":"Point"}
}