{
  "type": "Feature",
  "properties": {
    "gn:admin1_code":"5.0",
    "gn:asciiname":"Mechmech",
    "gn:country_code":"LB",
    "gn:dem":1177,
    "gn:feature_class":"P",
    "gn:feature_code":"PPL",
    "gn:name":"Mechmech",
    "gn:population":0,
    "gn:timezone":"Asia/Beirut",
    "iso:country":"LB",
    "name:ara_x_preferred":[
        "\u0645\u0634\u0645\u0634"
    ],
    "name:und_x_variant":[
        "Mishmish",
        "Mechmech"
    ],
    "wof:name":"Mechmech",
    "wof:placetype":"locality"
},
  "geometry": {"coordinates":[35.78028,34.14528],"type":"Point"}
}