{
  "type": "Feature",
  "properties": {
    "gn:admin1_code":"8.0",
    "gn:asciiname":"Ablah",
    "gn:country_code":"LB",
    "gn:dem":948,
    "gn:feature_class":"P",
    "gn:feature_code":"PPL",
    "gn:name":"Ablah",
    "gn:population":0,
    "gn:timezone":"Asia/Beirut",
    "iso:country":"LB",
    "name:ara_x_preferred":[
        "\u0623\u0628\u0644\u062d"
    ],
    "name:ita_x_preferred":[
        "Ablah"
    ],
    "name:und_x_variant":[
        "Abla\u1e29",
        "Ablah"
    ],
    "wof:name":"Ablah",
    "wof:placetype":"locality"
},
  "geometry": {"coordinates":[35.96805999999999,33.87083],"type":"Point"}
}