{
  "type": "Feature",
  "properties": {
    "gn:admin1_code":"11.0",
    "gn:asciiname":"Mazraat Matar",
    "gn:country_code":"LB",
    "gn:dem":1069,
    "gn:feature_class":"P",
    "gn:feature_code":"PPL",
    "gn:name":"Mazraat Matar",
    "gn:population":0,
    "gn:timezone":"Asia/Beirut",
    "iso:country":"LB",
    "name:und_x_variant":[
        "Mazra\u2018at Ma\u0163ar",
        "Mazraat Matar"
    ],
    "wof:name":"Mazraat Matar",
    "wof:placetype":"locality"
},
  "geometry": {"coordinates":[36.09167,34.09833],"type":"Point"}
}