{
  "type": "Feature",
  "properties": {
    "gn:admin1_code":"10.0",
    "gn:asciiname":"Beino",
    "gn:country_code":"LB",
    "gn:dem":511,
    "gn:feature_class":"P",
    "gn:feature_code":"PPL",
    "gn:name":"Be\u00efno",
    "gn:population":0,
    "gn:timezone":"Asia/Beirut",
    "iso:country":"LB",
    "name:und_x_variant":[
        "Bayn",
        "Bayn\u016b",
        "Be\u00efno"
    ],
    "wof:name":"Beino",
    "wof:placetype":"locality"
},
  "geometry": {"coordinates":[36.17889,34.53778],"type":"Point"}
}