{
  "type": "Feature",
  "properties": {
    "gn:admin1_code":"5.0",
    "gn:asciiname":"Khaloue",
    "gn:country_code":"LB",
    "gn:dem":811,
    "gn:feature_class":"P",
    "gn:feature_code":"PPL",
    "gn:name":"Khalou\u00e9",
    "gn:population":0,
    "gn:timezone":"Asia/Beirut",
    "iso:country":"LB",
    "name:ara_x_preferred":[
        "\u062e\u0644\u0648\u0629"
    ],
    "name:und_x_variant":[
        "Khalou\u00e9",
        "Khalwah"
    ],
    "wof:name":"Khaloue",
    "wof:placetype":"locality"
},
  "geometry": {"coordinates":[35.54861,33.76389],"type":"Point"}
}