{
  "type": "Feature",
  "properties": {
    "gn:admin1_code":"9.0",
    "gn:asciiname":"El Ouata",
    "gn:country_code":"LB",
    "gn:dem":628,
    "gn:feature_class":"P",
    "gn:feature_code":"PPL",
    "gn:name":"El Ouata",
    "gn:population":0,
    "gn:timezone":"Asia/Beirut",
    "iso:country":"LB",
    "name:und_x_variant":[
        "Al Wa\u0163\u0101\u2019",
        "El Ouata"
    ],
    "wof:name":"El Ouata",
    "wof:placetype":"locality"
},
  "geometry": {"coordinates":[35.79222,34.23167],"type":"Point"}
}