{
  "type": "Feature",
  "properties": {
    "gn:admin1_code":"5.0",
    "gn:asciiname":"Mechane",
    "gn:country_code":"LB",
    "gn:dem":916,
    "gn:feature_class":"P",
    "gn:feature_code":"PPL",
    "gn:name":"M\u00e9ch\u00e2ne",
    "gn:population":0,
    "gn:timezone":"Asia/Beirut",
    "iso:country":"LB",
    "name:ara_x_preferred":[
        "\u0645\u0634\u0627\u0646"
    ],
    "name:fra_x_preferred":[
        "M\u00e8chan\u00e8"
    ],
    "name:ita_x_preferred":[
        "Mechan\u00e8"
    ],
    "name:kor_x_preferred":[
        "\uba54\uce74\ub124"
    ],
    "name:nld_x_preferred":[
        "Mechane"
    ],
    "name:und_x_variant":[
        "Msh\u0101n",
        "M\u00e9ch\u00e2ne",
        "Mash\u0101n"
    ],
    "wof:name":"Mechane",
    "wof:placetype":"locality"
},
  "geometry": {"coordinates":[35.75644000000001,34.08376],"type":"Point"}
}