{
  "type": "Feature",
  "properties": {
    "iso:country":"LB",
    "name:ara_x_preferred":[
        "\u0628\u0631\u0627\u0645\u064a\u0629 \u0627\u0644\u062a\u062d\u062a\u0627"
    ],
    "name:eng_x_preferred":[
        "Bramiye Et Tahta"
    ],
    "qs:gn_pop":0,
    "qs:name":"\u0628\u0631\u0627\u0645\u064a\u0629 \u0627\u0644\u062a\u062d\u062a\u0627",
    "qs:name_adm0":"\u0644\u0628\u0646\u0627\u0646",
    "qs:name_adm1":"\u0627\u0644\u062c\u0646\u0648\u0628",
    "qs:photos":68,
    "qs:photos_1k":14,
    "qs:photos_9k":1,
    "qs:photos_9r":2,
    "qs:photos_all":68,
    "qs:photos_sr":2,
    "qs:placetype":"Town",
    "qs:pop_sr":"0",
    "qs:woe_adm0":23424873,
    "wof:name":"Bramiye Et Tahta",
    "wof:placetype":"locality"
},
  "geometry": {"coordinates":[35.388035,33.575297],"type":"Point"}
}