{
  "type": "Feature",
  "properties": {
    "gn:admin1_code":"6.0",
    "gn:asciiname":"Bestiyat",
    "gn:country_code":"LB",
    "gn:dem":340,
    "gn:feature_class":"P",
    "gn:feature_code":"PPL",
    "gn:name":"Bestiy\u00e2t",
    "gn:population":0,
    "gn:timezone":"Asia/Beirut",
    "iso:country":"LB",
    "name:ara_x_preferred":[
        "\u0628\u062b\u064a\u0651\u0627\u062a"
    ],
    "name:ara_x_variant":[
        "\u0628\u062b\u062a\u064a\u0627\u062a"
    ],
    "name:und_x_variant":[
        "Besti\u00e2s",
        "Bist\u0101t",
        "Bestiy\u00e2t",
        "Bathiyy\u0101t",
        "Batht\u012by\u0101t"
    ],
    "wof:name":"Bestiyat",
    "wof:placetype":"locality"
},
  "geometry": {"coordinates":[35.35823,33.28926],"type":"Point"}
}