{
  "type": "Feature",
  "properties": {
    "gn:admin1_code":"5.0",
    "gn:asciiname":"Brih",
    "gn:country_code":"LB",
    "gn:dem":35,
    "gn:feature_class":"P",
    "gn:feature_code":"PPL",
    "gn:name":"Brih",
    "gn:population":0,
    "gn:timezone":"Asia/Beirut",
    "iso:country":"LB",
    "name:ara_x_preferred":[
        "\u0628\u0631\u064a\u062d"
    ],
    "name:nno_x_preferred":[
        "Breeh"
    ],
    "name:und_x_variant":[
        "Bar\u012b\u1e29"
    ],
    "wof:name":"Brih",
    "wof:placetype":"locality"
},
  "geometry": {"coordinates":[35.65450999999999,34.09605999999999],"type":"Point"}
}