{
  "type": "Feature",
  "properties": {
    "gn:admin1_code":"5.0",
    "gn:asciiname":"El Bahhara",
    "gn:country_code":"LB",
    "gn:dem":902,
    "gn:feature_class":"P",
    "gn:feature_code":"PPL",
    "gn:name":"El Bahh\u00e2ra",
    "gn:population":0,
    "gn:timezone":"Asia/Beirut",
    "iso:country":"LB",
    "name:und_x_variant":[
        "Al Ba\u1e29\u1e29\u0101rah",
        "El Bahh\u00e2ra"
    ],
    "wof:name":"El Bahhara",
    "wof:placetype":"locality"
},
  "geometry": {"coordinates":[35.73667000000001,34.05139],"type":"Point"}
}