{
  "type": "Feature",
  "properties": {
    "gn:admin1_code":"5.0",
    "gn:asciiname":"Fsaqine",
    "gn:country_code":"LB",
    "gn:dem":616,
    "gn:feature_class":"P",
    "gn:feature_code":"PPL",
    "gn:name":"Fsaq\u00eene",
    "gn:population":0,
    "gn:timezone":"Asia/Beirut",
    "iso:country":"LB",
    "name:ara_x_preferred":[
        "\u0627\u0644\u0641\u0633\u0627\u0642\u064a\u0646"
    ],
    "name:und_x_variant":[
        "Fs\u00e9q\u00eene",
        "Fsa\u00efq\u00eene",
        "Al Fs\u0101q\u012bn",
        "Fsaq\u00eene",
        "Al Fas\u0101q\u012bn"
    ],
    "wof:name":"Fsaqine",
    "wof:placetype":"locality"
},
  "geometry": {"coordinates":[35.52972000000001,33.7575],"type":"Point"}
}