{
  "type": "Feature",
  "properties": {
    "gn:admin1_code":"9.0",
    "gn:asciiname":"Edde",
    "gn:country_code":"LB",
    "gn:dem":397,
    "gn:feature_class":"P",
    "gn:feature_code":"PPL",
    "gn:name":"Edd\u00e9",
    "gn:population":0,
    "gn:timezone":"Asia/Beirut",
    "iso:country":"LB",
    "name:ara_x_preferred":[
        "\u0625\u062f\u0629"
    ],
    "name:und_x_variant":[
        "Iddih",
        "Iddah",
        "Edd\u00e9"
    ],
    "wof:name":"Edde",
    "wof:placetype":"locality"
},
  "geometry": {"coordinates":[35.69333,34.23389],"type":"Point"}
}