{
  "type": "Feature",
  "properties": {
    "gn:admin1_code":"6.0",
    "gn:asciiname":"Marah al Qati`",
    "gn:country_code":"LB",
    "gn:dem":414,
    "gn:feature_class":"P",
    "gn:feature_code":"PPL",
    "gn:name":"Mar\u0101\u1e29 al Q\u0101\u0163i\u2018",
    "gn:population":0,
    "gn:timezone":"Asia/Beirut",
    "iso:country":"LB",
    "name:ara_x_preferred":[
        "\u0645\u0631\u0627\u062d \u0627\u0644\u0642\u0627\u0637\u0639"
    ],
    "name:und_x_variant":[
        "Mar\u0101\u1e29 al Q\u0101\u0163i\u2018"
    ],
    "wof:name":"Marah al Qati`",
    "wof:placetype":"locality"
},
  "geometry": {"coordinates":[35.48333,33.55],"type":"Point"}
}