{
  "type": "Feature",
  "properties": {
    "gn:admin1_code":"6.0",
    "gn:asciiname":"Bhannine",
    "gn:country_code":"LB",
    "gn:dem":596,
    "gn:feature_class":"P",
    "gn:feature_code":"PPL",
    "gn:name":"Bhann\u00eene",
    "gn:population":0,
    "gn:timezone":"Asia/Beirut",
    "iso:country":"LB",
    "name:ara_x_preferred":[
        "\u0628\u062d\u0646\u064a\u0646"
    ],
    "name:und_x_variant":[
        "Bahamine",
        "B\u1e29ann\u012bn",
        "Bhanneen",
        "Bhann\u00eene",
        "BHANINE"
    ],
    "wof:name":"Bhannine",
    "wof:placetype":"locality"
},
  "geometry": {"coordinates":[35.59778,33.5825],"type":"Point"}
}