{
  "type": "Feature",
  "properties": {
    "gn:admin1_code":"10.0",
    "gn:asciiname":"Qboula",
    "gn:country_code":"LB",
    "gn:dem":552,
    "gn:feature_class":"P",
    "gn:feature_code":"PPL",
    "gn:name":"Qboula",
    "gn:population":0,
    "gn:timezone":"Asia/Beirut",
    "iso:country":"LB",
    "wof:name":"Qboula",
    "wof:placetype":"locality"
},
  "geometry": {"coordinates":[36.18139,34.535],"type":"Point"}
}