{
  "type": "Feature",
  "properties": {
    "gn:admin1_code":"5.0",
    "gn:asciiname":"Chir el Bouar",
    "gn:country_code":"LB",
    "gn:dem":1133,
    "gn:feature_class":"P",
    "gn:feature_code":"PPL",
    "gn:name":"Ch\u00eer el Bou\u00e2r",
    "gn:population":0,
    "gn:timezone":"Asia/Beirut",
    "iso:country":"LB",
    "name:und_x_variant":[
        "Sh\u012br al Bw\u0101r",
        "Ch\u00eer el Bou\u00e2r"
    ],
    "wof:name":"Chir el Bouar",
    "wof:placetype":"locality"
},
  "geometry": {"coordinates":[35.86194000000001,34.07833],"type":"Point"}
}