{
  "type": "Feature",
  "properties": {
    "gn:admin1_code":"6.0",
    "gn:asciiname":"El Qatrani",
    "gn:country_code":"LB",
    "gn:dem":990,
    "gn:feature_class":"P",
    "gn:feature_code":"PPL",
    "gn:name":"El Qatr\u00e2ni",
    "gn:population":0,
    "gn:timezone":"Asia/Beirut",
    "iso:country":"LB",
    "name:ara_x_preferred":[
        "\u0627\u0644\u0642\u0637\u0631\u0627\u0646\u064a"
    ],
    "name:und_x_variant":[
        "Al Qu\u0163r\u0101n\u012b",
        "El-Qittrani",
        "El Qatr\u00e2ni",
        "Al Qa\u0163r\u0101n\u012b"
    ],
    "wof:name":"El Qatrani",
    "wof:placetype":"locality"
},
  "geometry": {"coordinates":[35.60417,33.44083],"type":"Point"}
}