{
  "type": "Feature",
  "properties": {
    "gn:admin1_code":"6.0",
    "gn:asciiname":"Mazraat el Qraiye",
    "gn:country_code":"LB",
    "gn:dem":206,
    "gn:feature_class":"P",
    "gn:feature_code":"PPL",
    "gn:name":"Mazraat el Qra\u00efy\u00e9",
    "gn:population":0,
    "gn:timezone":"Asia/Beirut",
    "iso:country":"LB",
    "name:ara_x_preferred":[
        "\u0645\u0632\u0631\u0639\u0629 \u0627\u0644\u0642\u0631\u064a\u0629"
    ],
    "name:und_x_variant":[
        "Mazra\u2018at al Qurayyah",
        "Mazraat el Qra\u00efy\u00e9",
        "Mazra\u2018at al Qaryah"
    ],
    "wof:name":"Mazraat el Qraiye",
    "wof:placetype":"locality"
},
  "geometry": {"coordinates":[35.32901,33.41866],"type":"Point"}
}