{
  "type": "Feature",
  "properties": {
    "gn:admin1_code":"5.0",
    "gn:asciiname":"Khandaq et Tahta",
    "gn:country_code":"LB",
    "gn:dem":473,
    "gn:feature_class":"P",
    "gn:feature_code":"PPL",
    "gn:name":"Khandaq et Tahta",
    "gn:population":0,
    "gn:timezone":"Asia/Beirut",
    "iso:country":"LB",
    "name:ara_x_preferred":[
        "\u062e\u0646\u062f\u0642 \u0627\u0644\u062a\u062d\u062a\u0627"
    ],
    "name:und_x_variant":[
        "Khandaq at Ta\u1e29t\u0101",
        "Khandaq et Tahta"
    ],
    "wof:name":"Khandaq et Tahta",
    "wof:placetype":"locality"
},
  "geometry": {"coordinates":[35.48444,33.6725],"type":"Point"}
}