{
  "type": "Feature",
  "properties": {
    "gn:admin1_code":"5.0",
    "gn:asciiname":"Halioune Et Tahta",
    "gn:country_code":"LB",
    "gn:dem":386,
    "gn:feature_class":"P",
    "gn:feature_code":"PPL",
    "gn:name":"Halioune Et Tahta",
    "gn:population":0,
    "gn:timezone":"Asia/Beirut",
    "iso:country":"LB",
    "wof:name":"Halioune Et Tahta",
    "wof:placetype":"locality"
},
  "geometry": {"coordinates":[35.469,33.66382],"type":"Point"}
}