{
  "type": "Feature",
  "properties": {
    "gn:admin1_code":"5.0",
    "gn:asciiname":"Ed Daaouq",
    "gn:country_code":"LB",
    "gn:dem":1680,
    "gn:feature_class":"P",
    "gn:feature_code":"PPL",
    "gn:name":"Ed D\u00e2aouq",
    "gn:population":0,
    "gn:timezone":"Asia/Beirut",
    "iso:country":"LB",
    "name:und_x_variant":[
        "Ad D\u0101\u2018\u016bq",
        "Ed D\u00e2aouq"
    ],
    "wof:name":"Ed Daaouq",
    "wof:placetype":"locality"
},
  "geometry": {"coordinates":[35.85222,34.13556],"type":"Point"}
}