{
  "type": "Feature",
  "properties": {
    "gn:admin1_code":"5.0",
    "gn:asciiname":"Haqlet es Saiyed",
    "gn:country_code":"LB",
    "gn:dem":1300,
    "gn:feature_class":"P",
    "gn:feature_code":"PPL",
    "gn:name":"Haqlet es Sa\u00efyed",
    "gn:population":0,
    "gn:timezone":"Asia/Beirut",
    "iso:country":"LB",
    "name:und_x_variant":[
        "Al Qal\u2018ah",
        "El-Qal\u2018ah",
        "\u1e28aqlat as Sayyid",
        "Haqlet es Sa\u00efyed"
    ],
    "wof:name":"Haqlet es Saiyed",
    "wof:placetype":"locality"
},
  "geometry": {"coordinates":[35.795,33.99028],"type":"Point"}
}