{
  "type": "Feature",
  "properties": {
    "gn:admin1_code":"5.0",
    "gn:asciiname":"Ain en Nasb",
    "gn:country_code":"LB",
    "gn:dem":1183,
    "gn:feature_class":"P",
    "gn:feature_code":"PPL",
    "gn:name":"A\u00efn en Nasb",
    "gn:population":0,
    "gn:timezone":"Asia/Beirut",
    "iso:country":"LB",
    "name:und_x_variant":[
        "\u2018Ayn an Na\u015fb",
        "A\u00efn en Nasb"
    ],
    "wof:name":"Ain en Nasb",
    "wof:placetype":"locality"
},
  "geometry": {"coordinates":[35.76361,33.94389],"type":"Point"}
}