{
  "type": "Feature",
  "properties": {
    "gn:admin1_code":"6.0",
    "gn:asciiname":"Majdel Zoun",
    "gn:country_code":"LB",
    "gn:dem":389,
    "gn:feature_class":"P",
    "gn:feature_code":"PPL",
    "gn:name":"Majdel Zo\u00fbn",
    "gn:population":0,
    "gn:timezone":"Asia/Beirut",
    "iso:country":"LB",
    "name:ara_x_preferred":[
        "\u0645\u062c\u062f\u0644 \u0632\u0648\u0646"
    ],
    "name:und_x_variant":[
        "Majdal Z\u016bn",
        "Majdel Zo\u00fbn"
    ],
    "wof:name":"Majdel Zoun",
    "wof:placetype":"locality"
},
  "geometry": {"coordinates":[35.22611,33.15139],"type":"Point"}
}