{
  "type": "Feature",
  "properties": {
    "gn:admin1_code":"7.0",
    "gn:asciiname":"Borj el Mlouk",
    "gn:country_code":"LB",
    "gn:dem":614,
    "gn:feature_class":"P",
    "gn:feature_code":"PPL",
    "gn:name":"Borj el Mlouk",
    "gn:population":0,
    "gn:timezone":"Asia/Beirut",
    "iso:country":"LB",
    "name:ara_x_preferred":[
        "\u0628\u0631\u062c \u0627\u0644\u0645\u0644\u0648\u0643"
    ],
    "name:und_x_variant":[
        "BOURJ EL MOULOUK",
        "Borj el Mlouk",
        "Burj al Mul\u016bk"
    ],
    "wof:name":"Borj el Mlouk",
    "wof:placetype":"locality"
},
  "geometry": {"coordinates":[35.565,33.32139],"type":"Point"}
}