{
  "type": "Feature",
  "properties": {
    "gn:admin1_code":"9.0",
    "gn:asciiname":"Daraiya",
    "gn:country_code":"LB",
    "gn:dem":328,
    "gn:feature_class":"P",
    "gn:feature_code":"PPL",
    "gn:name":"D\u00e2ra\u00efya",
    "gn:population":0,
    "gn:timezone":"Asia/Beirut",
    "iso:country":"LB",
    "name:ara_x_preferred":[
        "\u062f\u0627\u0631\u064a\u0627"
    ],
    "name:und_x_variant":[
        "D\u0101rayy\u0101",
        "D\u00e2ra\u00efya"
    ],
    "wof:name":"Daraiya",
    "wof:placetype":"locality"
},
  "geometry": {"coordinates":[35.86944000000001,34.32889],"type":"Point"}
}