{
  "type": "Feature",
  "properties": {
    "gn:admin1_code":"9.0",
    "gn:asciiname":"Rechdibbine",
    "gn:country_code":"LB",
    "gn:dem":713,
    "gn:feature_class":"P",
    "gn:feature_code":"PPL",
    "gn:name":"Rechdibb\u00eene",
    "gn:population":0,
    "gn:timezone":"Asia/Beirut",
    "iso:country":"LB",
    "name:ara_x_preferred":[
        "\u0631\u0634\u062f\u0628\u064a\u0646"
    ],
    "name:ara_x_variant":[
        "\u0631\u064a\u0634\u062f\u0628\u064a\u0646"
    ],
    "name:ita_x_preferred":[
        "Rechdebbine"
    ],
    "name:nno_x_preferred":[
        "Rachedbine"
    ],
    "name:und_x_variant":[
        "Rishdibb\u012bn",
        "Rechdibb\u00eene"
    ],
    "wof:name":"Rechdibbine",
    "wof:placetype":"locality"
},
  "geometry": {"coordinates":[35.86028,34.29139],"type":"Point"}
}