{
  "type": "Feature",
  "properties": {
    "gn:admin1_code":"5.0",
    "gn:asciiname":"Zoummar",
    "gn:country_code":"LB",
    "gn:dem":30,
    "gn:feature_class":"P",
    "gn:feature_code":"PPL",
    "gn:name":"Zoumm\u00e2r",
    "gn:population":0,
    "gn:timezone":"Asia/Beirut",
    "iso:country":"LB",
    "name:und_x_variant":[
        "Zamm\u0101r",
        "Zoumm\u00e2r"
    ],
    "wof:name":"Zoummar",
    "wof:placetype":"locality"
},
  "geometry": {"coordinates":[35.63222000000001,34.14306],"type":"Point"}
}