{
  "type": "Feature",
  "properties": {
    "gn:admin1_code":"5.0",
    "gn:asciiname":"El Mogheiri",
    "gn:country_code":"LB",
    "gn:dem":1160,
    "gn:feature_class":"P",
    "gn:feature_code":"PPL",
    "gn:name":"El Moghe\u00efri",
    "gn:population":0,
    "gn:timezone":"Asia/Beirut",
    "iso:country":"LB",
    "name:ara_x_preferred":[
        "\u0627\u0644\u0645\u063a\u064a\u0631\u064a"
    ],
    "name:ara_x_variant":[
        "\u0627\u0644\u0645\u063a\u064a\u0631\u0629"
    ],
    "name:und_x_variant":[
        "Al Mugh\u012br\u012b",
        "El Mrha\u00efri",
        "El Mnha\u00efri",
        "Al Mughayrah",
        "El Moghe\u00efri",
        "Al Mughayr\u012b"
    ],
    "wof:name":"El Mogheiri",
    "wof:placetype":"locality"
},
  "geometry": {"coordinates":[35.87417,34.09889],"type":"Point"}
}