{
  "type": "Feature",
  "properties": {
    "gn:admin1_code":"6.0",
    "gn:asciiname":"Blatet ej Jamjim",
    "gn:country_code":"LB",
    "gn:dem":35,
    "gn:feature_class":"P",
    "gn:feature_code":"PPL",
    "gn:name":"Blatet ej Jamj\u00eem",
    "gn:population":0,
    "gn:timezone":"Asia/Beirut",
    "iso:country":"LB",
    "name:ara_x_preferred":[
        "\u0628\u0644\u0627\u0637\u0629 \u062c\u0645\u062c\u064a\u0645"
    ],
    "name:ara_x_variant":[
        "\u0628\u0644\u0627\u0637\u0629 \u0627\u0644\u062c\u0645\u062c\u064a\u0645"
    ],
    "name:und_x_variant":[
        "Bal\u0101\u0163at al Jamj\u012bm",
        "Blatet ej Jamj\u00eem",
        "Bal\u0101\u0163at Jamj\u012bm"
    ],
    "wof:name":"Blatet ej Jamjim",
    "wof:placetype":"locality"
},
  "geometry": {"coordinates":[35.28245,33.36967],"type":"Point"}
}