{
  "type": "Feature",
  "properties": {
    "gn:admin1_code":"10.0",
    "gn:asciiname":"El Ghawaya",
    "gn:country_code":"LB",
    "gn:dem":589,
    "gn:feature_class":"P",
    "gn:feature_code":"PPL",
    "gn:name":"El Ghawaya",
    "gn:population":0,
    "gn:timezone":"Asia/Beirut",
    "iso:country":"LB",
    "wof:name":"El Ghawaya",
    "wof:placetype":"locality"
},
  "geometry": {"coordinates":[36.27528,34.56528],"type":"Point"}
}