{
  "type": "Feature",
  "properties": {
    "gn:admin1_code":"6.0",
    "gn:asciiname":"Sfenta",
    "gn:country_code":"LB",
    "gn:dem":483,
    "gn:feature_class":"P",
    "gn:feature_code":"PPL",
    "gn:name":"Sfenta",
    "gn:population":0,
    "gn:timezone":"Asia/Beirut",
    "iso:country":"LB",
    "name:ara_x_preferred":[
        "\u0633\u0641\u0646\u062a\u0649"
    ],
    "name:ara_x_variant":[
        "\u0633\u0641\u0646\u062a\u0627"
    ],
    "name:und_x_variant":[
        "Sfint\u0101",
        "Sfenta",
        "Safant\u00e1",
        "Safint\u0101"
    ],
    "wof:name":"Sfenta",
    "wof:placetype":"locality"
},
  "geometry": {"coordinates":[35.49442,33.50515],"type":"Point"}
}