{
  "type": "Feature",
  "properties": {
    "gn:admin1_code":"7.0",
    "gn:asciiname":"Aazze",
    "gn:country_code":"LB",
    "gn:dem":377,
    "gn:feature_class":"P",
    "gn:feature_code":"PPL",
    "gn:name":"Aazz\u00e9",
    "gn:population":0,
    "gn:timezone":"Asia/Beirut",
    "iso:country":"LB",
    "name:ara_x_preferred":[
        "\u0639\u0632\u0629"
    ],
    "name:ara_x_variant":[
        "\u0639\u0632\u0651\u0629"
    ],
    "name:und_x_variant":[
        "\u2018Izzah",
        "Aazz\u00e9",
        "\u2018Azzah"
    ],
    "wof:name":"Aazze",
    "wof:placetype":"locality"
},
  "geometry": {"coordinates":[35.43109000000001,33.45492],"type":"Point"}
}