{
  "type": "Feature",
  "properties": {
    "gn:admin1_code":"9.0",
    "gn:asciiname":"El Ouatie",
    "gn:country_code":"LB",
    "gn:dem":432,
    "gn:feature_class":"P",
    "gn:feature_code":"PPL",
    "gn:name":"El Ouati\u00e9",
    "gn:population":0,
    "gn:timezone":"Asia/Beirut",
    "iso:country":"LB",
    "name:und_x_variant":[
        "El Ou\u00e2t\u00eey\u00e9",
        "Al W\u0101\u0163i\u2019ah",
        "El Ouati\u00e9"
    ],
    "wof:name":"El Ouatie",
    "wof:placetype":"locality"
},
  "geometry": {"coordinates":[36.0075,34.43306],"type":"Point"}
}