{
  "type": "Feature",
  "properties": {
    "gn:asciiname":"Tair Filsay",
    "gn:country_code":"LB",
    "gn:dem":259,
    "gn:feature_class":"P",
    "gn:feature_code":"PPL",
    "gn:name":"Tair Filsay",
    "gn:population":0,
    "gn:timezone":"Asia/Beirut",
    "iso:country":"LB",
    "name:und_x_variant":[
        "Tayr Filsay",
        "Tair Felssieh"
    ],
    "wof:name":"Tair Filsay",
    "wof:placetype":"locality"
},
  "geometry": {"coordinates":[35.34788,33.30897],"type":"Point"}
}