{
  "type": "Feature",
  "properties": {
    "gn:admin1_code":"5.0",
    "gn:asciiname":"Chamat",
    "gn:country_code":"LB",
    "gn:dem":451,
    "gn:feature_class":"P",
    "gn:feature_code":"PPL",
    "gn:name":"Ch\u00e2m\u00e2t",
    "gn:population":0,
    "gn:timezone":"Asia/Beirut",
    "iso:country":"LB",
    "name:ara_x_preferred":[
        "\u0634\u0627\u0645\u0627\u062a"
    ],
    "name:und_x_variant":[
        "Ch\u00e2m\u00e2te",
        "Sh\u0101m\u0101t",
        "Ch\u00e2m\u00e2t"
    ],
    "wof:name":"Chamat",
    "wof:placetype":"locality"
},
  "geometry": {"coordinates":[35.69802,34.1658],"type":"Point"}
}