{
  "type": "Feature",
  "properties": {
    "iso:country":"LB",
    "name:ara_x_preferred":[
        "\u0641\u0631\u0646 \u0627\u0644\u062d\u0627\u064a\u0643"
    ],
    "name:ara_x_variant":[
        "Furn El Hayek"
    ],
    "name:fra_x_preferred":[
        "Forn el Haik"
    ],
    "name:unk_x_variant":[
        "\u0641\u0631\u0646 \u0627\u0644\u062d\u0627\u064a\u0643"
    ],
    "qs:gn_adm0_cc":"LB",
    "qs:gn_local":276781,
    "qs:local_max":1709,
    "qs:local_sum":10240,
    "qs:localhoods":30,
    "qs:name":"\u0641\u0631\u0646 \u0627\u0644\u062d\u0627\u064a\u0643",
    "qs:name_adm0":"\u0644\u0628\u0646\u0627\u0646",
    "qs:name_adm1":"\u0628\u064a\u0631\u0648\u062a",
    "qs:name_adm2":"\u0628\u064a\u0631\u0648\u062a",
    "qs:name_lau":"\u0641\u0631\u0646 \u0627\u0644\u062d\u0627\u064a\u0643",
    "qs:name_local":"\u0628\u064a\u0631\u0648\u062a",
    "qs:photo_max":100,
    "qs:photo_sum":463,
    "qs:placetype":"Suburb",
    "qs:quad_count":16,
    "qs:woe_adm0":23424873,
    "qs:woe_adm1":2346016,
    "qs:woe_adm2":56049614,
    "qs:woe_lau":56411500,
    "qs:woe_local":1960307,
    "qs:woe_ver":"7.10.0",
    "wof:lang":[
        "ara"
    ],
    "wof:name":"\u0641\u0631\u0646 \u0627\u0644\u062d\u0627\u064a\u0643",
    "wof:placetype":"neighbourhood"
},
  "geometry": {"coordinates":[35.515094,33.888229],"type":"Point"}
}