{
  "type": "Feature",
  "properties": {
    "gn:admin1_code":"7.0",
    "gn:asciiname":"Rmaysh",
    "gn:country_code":"LB",
    "gn:dem":573,
    "gn:feature_class":"P",
    "gn:feature_code":"PPL",
    "gn:name":"Rmaysh",
    "gn:population":0,
    "gn:timezone":"Asia/Beirut",
    "iso:country":"LB",
    "name:ara_x_preferred":[
        "\u0631\u0645\u064a\u0634"
    ],
    "name:fra_x_preferred":[
        "Rmeish"
    ],
    "name:heb_x_preferred":[
        "\u05e8\u05de\u05d9\u05e9"
    ],
    "name:ita_x_preferred":[
        "Rmeich"
    ],
    "name:nno_x_preferred":[
        "Rmaich"
    ],
    "name:nor_x_preferred":[
        "Rmaich"
    ],
    "name:pol_x_preferred":[
        "Rumajsz"
    ],
    "name:und_x_variant":[
        "Rumaysh",
        "Rmaich",
        "Rmaysh",
        "Rmeich"
    ],
    "wof:name":"Rmaysh",
    "wof:placetype":"locality"
},
  "geometry": {"coordinates":[35.36611,33.07833],"type":"Point"}
}