{
  "type": "Feature",
  "properties": {
    "gn:admin1_code":"5.0",
    "gn:asciiname":"Faqra",
    "gn:country_code":"LB",
    "gn:dem":1623,
    "gn:feature_class":"P",
    "gn:feature_code":"PPL",
    "gn:name":"Faqra",
    "gn:population":0,
    "gn:timezone":"Asia/Beirut",
    "iso:country":"LB",
    "wof:name":"Faqra",
    "wof:placetype":"locality"
},
  "geometry": {"coordinates":[35.82024000000001,33.99746],"type":"Point"}
}