{
  "type": "Feature",
  "properties": {
    "gn:admin1_code":"10.0",
    "gn:asciiname":"Mathanet ed Delbe",
    "gn:country_code":"LB",
    "gn:dem":66,
    "gn:feature_class":"P",
    "gn:feature_code":"PPL",
    "gn:name":"Mathanet ed Delb\u00e9",
    "gn:population":0,
    "gn:timezone":"Asia/Beirut",
    "iso:country":"LB",
    "name:und_x_variant":[
        "Aarka",
        "\u2018Arqah",
        "Aarqa",
        "Arka",
        "\u2018Arq\u0101",
        "Ma\u0163\u1e29anat ad Dulbah",
        "Mathanet ed Delb\u00e9"
    ],
    "wof:name":"Mathanet ed Delbe",
    "wof:placetype":"locality"
},
  "geometry": {"coordinates":[36.03556,34.53222],"type":"Point"}
}