{
  "type": "Feature",
  "properties": {
    "gn:admin1_code":"6.0",
    "gn:asciiname":"Haffet Bou Hajli",
    "gn:country_code":"LB",
    "gn:dem":407,
    "gn:feature_class":"P",
    "gn:feature_code":"PPL",
    "gn:name":"Haffet Bou Hajli",
    "gn:population":0,
    "gn:timezone":"Asia/Beirut",
    "iso:country":"LB",
    "name:ara_x_preferred":[
        "\u062d\u0641\u0629 \u0628\u0648 \u062d\u062c\u0644\u064a"
    ],
    "name:und_x_variant":[
        "\u2019affat B\u016b \u2019ajl\u012b",
        "Haffet Bou Hajli",
        "\u1e28affat B\u016b \u1e28ajl\u012b"
    ],
    "wof:name":"Haffet Bou Hajli",
    "wof:placetype":"locality"
},
  "geometry": {"coordinates":[35.53556,33.3825],"type":"Point"}
}