{
  "type": "Feature",
  "properties": {
    "gn:admin1_code":"11.0",
    "gn:asciiname":"Mrah Hqab en Najjar",
    "gn:country_code":"LB",
    "gn:dem":723,
    "gn:feature_class":"P",
    "gn:feature_code":"PPL",
    "gn:name":"Mr\u00e2h Hq\u00e2b en Najj\u00e2r",
    "gn:population":0,
    "gn:timezone":"Asia/Beirut",
    "iso:country":"LB",
    "name:und_x_variant":[
        "Mar\u0101\u1e29 \u1e28iq\u0101b an Najj\u0101r",
        "Mr\u00e2h Hq\u00e2b en Najj\u00e2r"
    ],
    "wof:name":"Mrah Hqab en Najjar",
    "wof:placetype":"locality"
},
  "geometry": {"coordinates":[36.36944,34.33583],"type":"Point"}
}