{
  "type": "Feature",
  "properties": {
    "gn:admin1_code":"10.0",
    "gn:asciiname":"Ar Ru'ays",
    "gn:country_code":"LB",
    "gn:dem":569,
    "gn:feature_class":"P",
    "gn:feature_code":"PPL",
    "gn:name":"Ar Ru\u2019ays",
    "gn:population":0,
    "gn:timezone":"Asia/Beirut",
    "iso:country":"LB",
    "name:ara_x_preferred":[
        "\u0627\u0644\u0631\u0648\u064a\u0633"
    ],
    "name:ceb_x_preferred":[
        "Ar Ru'ays"
    ],
    "name:fas_x_preferred":[
        "\u0627\u0644\u0631\u0648\u06cc\u0633"
    ],
    "name:gle_x_preferred":[
        "Ar Ru'ays"
    ],
    "name:lit_x_preferred":[
        "Ruajisas"
    ],
    "name:nno_x_preferred":[
        "Ar Ru'ays"
    ],
    "name:pol_x_preferred":[
        "Ar-Ruwajs"
    ],
    "name:por_x_preferred":[
        "Ar Ru'ays"
    ],
    "name:tgl_x_preferred":[
        "Ar Ru'ays"
    ],
    "name:tur_x_preferred":[
        "Er R\u00fcveys"
    ],
    "name:und_x_variant":[
        "Er Roua\u00efss",
        "Er-Rweis",
        "Ar Ru\u2019ays"
    ],
    "name:xmf_x_preferred":[
        "\u10d4\u10e0-\u10e0\u10e3\u10d4\u10d8\u10e1\u10d8"
    ],
    "wof:name":"Ar Ru'ays",
    "wof:placetype":"locality"
},
  "geometry": {"coordinates":[36.15,34.51667],"type":"Point"}
}