{
  "type": "Feature",
  "properties": {
    "gn:admin1_code":"10.0",
    "gn:asciiname":"Ar Ru'ays",
    "gn:country_code":"LB",
    "gn:dem":569,
    "gn:feature_class":"P",
    "gn:feature_code":"PPL",
    "gn:name":"Ar Ru\u2019ays",
    "gn:population":0,
    "gn:timezone":"Asia/Beirut",
    "iso:country":"LB",
    "name:und_x_variant":[
        "Er Roua\u00efss",
        "Er-Rweis",
        "Ar Ru\u2019ays"
    ],
    "wof:name":"Ar Ru'ays",
    "wof:placetype":"locality"
},
  "geometry": {"coordinates":[36.15,34.51667],"type":"Point"}
}