{
  "type": "Feature",
  "properties": {
    "gn:admin1_code":"5.0",
    "gn:asciiname":"Najd",
    "gn:country_code":"LB",
    "gn:dem":1209,
    "gn:feature_class":"P",
    "gn:feature_code":"PPL",
    "gn:name":"Najd",
    "gn:population":0,
    "gn:timezone":"Asia/Beirut",
    "iso:country":"LB",
    "wof:name":"Najd",
    "wof:placetype":"locality"
},
  "geometry": {"coordinates":[35.75278,33.97889],"type":"Point"}
}