{
  "type": "Feature",
  "properties": {
    "gn:admin1_code":"5.0",
    "gn:asciiname":"El Battal",
    "gn:country_code":"LB",
    "gn:dem":260,
    "gn:feature_class":"P",
    "gn:feature_code":"PPL",
    "gn:name":"El Batt\u00e2l",
    "gn:population":0,
    "gn:timezone":"Asia/Beirut",
    "iso:country":"LB",
    "name:ara_x_preferred":[
        "\u0627\u0644\u0628\u0637\u0627\u0644"
    ],
    "name:und_x_variant":[
        "El Batal",
        "Al Ba\u0163\u0163\u0101l",
        "El Batt\u00e2l"
    ],
    "wof:name":"El Battal",
    "wof:placetype":"locality"
},
  "geometry": {"coordinates":[35.46147,33.69662],"type":"Point"}
}