{
  "type": "Feature",
  "properties": {
    "gn:admin1_code":"5.0",
    "gn:asciiname":"Sannour",
    "gn:country_code":"LB",
    "gn:dem":493,
    "gn:feature_class":"P",
    "gn:feature_code":"PPL",
    "gn:name":"Sanno\u00fbr",
    "gn:population":0,
    "gn:timezone":"Asia/Beirut",
    "iso:country":"LB",
    "name:und_x_variant":[
        "Hma\u00efr\u00e9",
        "El-Hmeirih",
        "El Houme\u00efr\u00e9",
        "Sann\u016br",
        "Sanno\u00fbr"
    ],
    "wof:name":"Sannour",
    "wof:placetype":"locality"
},
  "geometry": {"coordinates":[35.73139000000001,34.07917],"type":"Point"}
}