{
  "type": "Feature",
  "properties": {
    "gn:admin1_code":"5.0",
    "gn:asciiname":"Rouaissat Salima",
    "gn:country_code":"LB",
    "gn:dem":820,
    "gn:feature_class":"P",
    "gn:feature_code":"PPL",
    "gn:name":"Roua\u00efss\u00e2t Sal\u00eema",
    "gn:population":0,
    "gn:timezone":"Asia/Beirut",
    "iso:country":"LB",
    "name:ara_x_preferred":[
        "\u0631\u0648\u064a\u0633\u0627\u062a \u0635\u0644\u064a\u0645\u0627"
    ],
    "name:und_x_variant":[
        "Ru\u2019ays\u0101t \u015eal\u012bm\u0101",
        "Roua\u00efss\u00e2t Sal\u00eema",
        "Ruways\u0101t \u015eal\u012bm\u0101"
    ],
    "wof:name":"Rouaissat Salima",
    "wof:placetype":"locality"
},
  "geometry": {"coordinates":[35.68306,33.87222],"type":"Point"}
}