{
  "type": "Feature",
  "properties": {
    "gn:admin1_code":"9.0",
    "gn:asciiname":"Dahr el Ghbar",
    "gn:country_code":"LB",
    "gn:dem":404,
    "gn:feature_class":"P",
    "gn:feature_code":"PPL",
    "gn:name":"Dahr el Ghb\u00e2r",
    "gn:population":0,
    "gn:timezone":"Asia/Beirut",
    "iso:country":"LB",
    "name:und_x_variant":[
        "\u1e10ahr al Ghub\u0101r",
        "Dahr el Ghb\u00e2r"
    ],
    "wof:name":"Dahr el Ghbar",
    "wof:placetype":"locality"
},
  "geometry": {"coordinates":[35.71472,34.23139],"type":"Point"}
}