{
  "type": "Feature",
  "properties": {
    "gn:admin1_code":"6.0",
    "gn:asciiname":"Mazraat Zeita",
    "gn:country_code":"LB",
    "gn:dem":182,
    "gn:feature_class":"P",
    "gn:feature_code":"PPL",
    "gn:name":"Mazraat Ze\u00efta",
    "gn:population":0,
    "gn:timezone":"Asia/Beirut",
    "iso:country":"LB",
    "name:ara_x_preferred":[
        "\u0645\u0632\u0631\u0639\u0629 \u0632\u064a\u062a\u0627"
    ],
    "name:und_x_variant":[
        "Mazra\u2018at Zayt\u0101",
        "Mazraat Ze\u00efta"
    ],
    "wof:name":"Mazraat Zeita",
    "wof:placetype":"locality"
},
  "geometry": {"coordinates":[35.3925,33.50278],"type":"Point"}
}