{
  "type": "Feature",
  "properties": {
    "gn:admin1_code":"5.0",
    "gn:asciiname":"Mazraat Kfardibiane",
    "gn:country_code":"LB",
    "gn:dem":1264,
    "gn:feature_class":"P",
    "gn:feature_code":"PPL",
    "gn:name":"Mazraat Kfardibi\u00e2ne",
    "gn:population":0,
    "gn:timezone":"Asia/Beirut",
    "iso:country":"LB",
    "name:und_x_variant":[
        "Mazra\u2018at Kafr Dhiby\u0101n",
        "Mazraat Kfardibi\u00e2ne"
    ],
    "wof:name":"Mazraat Kfardibiane",
    "wof:placetype":"locality"
},
  "geometry": {"coordinates":[35.76667,33.98417],"type":"Point"}
}