{
  "type": "Feature",
  "properties": {
    "gn:admin1_code":"5.0",
    "gn:asciiname":"Ernaya",
    "gn:country_code":"LB",
    "gn:dem":569,
    "gn:feature_class":"P",
    "gn:feature_code":"PPL",
    "gn:name":"Ernaya",
    "gn:population":0,
    "gn:timezone":"Asia/Beirut",
    "iso:country":"LB",
    "name:ara_x_preferred":[
        "\u0623\u0631\u0646\u064a\u0627"
    ],
    "name:ara_x_variant":[
        "Qurn\u0101y\u0101",
        "\u0642\u0631\u0646\u0627\u064a\u0627"
    ],
    "name:und_x_variant":[
        "Bchell\u00e9",
        "Bchelly",
        "Irnay\u0101",
        "Ernaya",
        "Urnay\u0101"
    ],
    "wof:name":"Ernaya",
    "wof:placetype":"locality"
},
  "geometry": {"coordinates":[35.70972000000001,34.10417],"type":"Point"}
}