{
  "type": "Feature",
  "properties": {
    "gn:admin1_code":"5.0",
    "gn:asciiname":"Kfar Nabrakh",
    "gn:country_code":"LB",
    "gn:dem":1010,
    "gn:feature_class":"P",
    "gn:feature_code":"PPL",
    "gn:name":"Kfar Nabrakh",
    "gn:population":0,
    "gn:timezone":"Asia/Beirut",
    "iso:country":"LB",
    "name:ara_x_preferred":[
        "\u0643\u0641\u0631 \u0646\u0628\u0631\u062e"
    ],
    "name:ara_x_variant":[
        "\u0643\u0641\u0631\u0646\u0628\u0631\u062e"
    ],
    "name:und_x_variant":[
        "Kafr Nabrakh",
        "Kfar Nabrakh"
    ],
    "wof:name":"Kfar Nabrakh",
    "wof:placetype":"locality"
},
  "geometry": {"coordinates":[35.63194,33.69889000000001],"type":"Point"}
}