{
  "type": "Feature",
  "properties": {
    "gn:admin1_code":"11.0",
    "gn:asciiname":"Et Taybeh",
    "gn:country_code":"LB",
    "gn:dem":1194,
    "gn:feature_class":"P",
    "gn:feature_code":"PPL",
    "gn:name":"Et Taybeh",
    "gn:population":0,
    "gn:timezone":"Asia/Beirut",
    "iso:country":"LB",
    "name:und_x_variant":[
        "Et Teibah",
        "Ett Ta\u00efb\u00e9",
        "A\u0163 \u0162ayyibah",
        "Et Taybeh"
    ],
    "wof:name":"Et Taybeh",
    "wof:placetype":"locality"
},
  "geometry": {"coordinates":[36.16611,33.95833],"type":"Point"}
}