{
  "type": "Feature",
  "properties": {
    "gn:asciiname":"Aaitit",
    "gn:country_code":"LB",
    "gn:dem":327,
    "gn:feature_class":"P",
    "gn:feature_code":"PPL",
    "gn:name":"Aaitit",
    "gn:population":0,
    "gn:timezone":"Asia/Beirut",
    "iso:country":"LB",
    "name:und_x_variant":[
        "Aitit",
        "Aytiit"
    ],
    "wof:name":"Aaitit",
    "wof:placetype":"locality"
},
  "geometry": {"coordinates":[35.30647000000001,33.22754],"type":"Point"}
}