{
  "type": "Feature",
  "properties": {
    "gn:admin1_code":"9.0",
    "gn:asciiname":"El Meil",
    "gn:country_code":"LB",
    "gn:dem":1788,
    "gn:feature_class":"P",
    "gn:feature_code":"PPL",
    "gn:name":"El Me\u00efl",
    "gn:population":0,
    "gn:timezone":"Asia/Beirut",
    "iso:country":"LB",
    "name:und_x_variant":[
        "Al Mayl",
        "El Me\u00efl"
    ],
    "wof:name":"El Meil",
    "wof:placetype":"locality"
},
  "geometry": {"coordinates":[35.945,34.19139000000001],"type":"Point"}
}