{
  "type": "Feature",
  "properties": {
    "gn:admin1_code":"10.0",
    "gn:asciiname":"Beit Khlaiyel",
    "gn:country_code":"LB",
    "gn:dem":775,
    "gn:feature_class":"P",
    "gn:feature_code":"PPL",
    "gn:name":"Be\u00eft Khla\u00efyel",
    "gn:population":0,
    "gn:timezone":"Asia/Beirut",
    "iso:country":"LB",
    "name:und_x_variant":[
        "Be\u00eft Khalil",
        "Bayt Khal\u012bl",
        "Be\u00eft Khla\u00efyel"
    ],
    "wof:name":"Beit Khlaiyel",
    "wof:placetype":"locality"
},
  "geometry": {"coordinates":[36.22389,34.53417],"type":"Point"}
}