{
  "type": "Feature",
  "properties": {
    "gn:admin1_code":"6.0",
    "gn:asciiname":"Khzaiz",
    "gn:country_code":"LB",
    "gn:dem":320,
    "gn:feature_class":"P",
    "gn:feature_code":"PPL",
    "gn:name":"Khza\u00efz",
    "gn:population":0,
    "gn:timezone":"Asia/Beirut",
    "iso:country":"LB",
    "name:ara_x_preferred":[
        "\u062e\u0632\u064a\u0632"
    ],
    "name:und_x_variant":[
        "Khz\u0101z",
        "Khza\u00efz",
        "Khaz\u012bz",
        "Khuzyz"
    ],
    "wof:name":"Khzaiz",
    "wof:placetype":"locality"
},
  "geometry": {"coordinates":[35.40667,33.46694],"type":"Point"}
}