{
  "type": "Feature",
  "properties": {
    "gn:admin1_code":"6.0",
    "gn:asciiname":"Ed Dhaira",
    "gn:country_code":"LB",
    "gn:dem":446,
    "gn:feature_class":"P",
    "gn:feature_code":"PPL",
    "gn:name":"Ed Dha\u00efra",
    "gn:population":0,
    "gn:timezone":"Asia/Beirut",
    "iso:country":"LB",
    "name:ara_x_preferred":[
        "\u0627\u0644\u0636\u0647\u064a\u0631\u0629"
    ],
    "name:und_x_variant":[
        "A\u1e11 \u1e10uhayrah",
        "Ed Dha\u00efra",
        "A\u1e11 \u1e10ah\u012brah"
    ],
    "wof:name":"Ed Dhaira",
    "wof:placetype":"locality"
},
  "geometry": {"coordinates":[35.2275,33.10028],"type":"Point"}
}