{
  "type": "Feature",
  "properties": {
    "gn:admin1_code":"10.0",
    "gn:asciiname":"Ech Cheikh Mohammed",
    "gn:country_code":"LB",
    "gn:dem":202,
    "gn:feature_class":"P",
    "gn:feature_code":"PPL",
    "gn:name":"Ech Che\u00efkh Mohammed",
    "gn:population":0,
    "gn:timezone":"Asia/Beirut",
    "iso:country":"LB",
    "name:ara_x_preferred":[
        "\u0627\u0644\u0634\u064a\u062e \u0645\u062d\u0645\u062f"
    ],
    "name:ita_x_preferred":[
        "Cheikh Mohammad"
    ],
    "name:nno_x_preferred":[
        "Cheikh Mohammad"
    ],
    "name:und_x_variant":[
        "Che\u00efkh Mohammad",
        "Esh-Sheikh Mohamed",
        "Ash Shaykh Mu\u1e29ammad",
        "Ech Che\u00efkh Mohammed"
    ],
    "wof:name":"Ech Cheikh Mohammed",
    "wof:placetype":"locality"
},
  "geometry": {"coordinates":[36.08417,34.54972],"type":"Point"}
}