{
  "type": "Feature",
  "properties": {
    "gn:admin1_code":"6.0",
    "gn:asciiname":"Aabra",
    "gn:country_code":"LB",
    "gn:dem":176,
    "gn:feature_class":"P",
    "gn:feature_code":"PPL",
    "gn:name":"Aabra",
    "gn:population":0,
    "gn:timezone":"Asia/Beirut",
    "iso:country":"LB",
    "name:ara_x_preferred":[
        "\u0639\u0628\u0631\u0627"
    ],
    "name:und_x_variant":[
        "Habra",
        "\u2018Abr\u0101",
        "Aabra"
    ],
    "wof:name":"Aabra",
    "wof:placetype":"locality"
},
  "geometry": {"coordinates":[35.40583,33.56667],"type":"Point"}
}