{
  "type": "Feature",
  "properties": {
    "gn:admin1_code":"10.0",
    "gn:asciiname":"Hokr el Haissa",
    "gn:country_code":"LB",
    "gn:dem":28,
    "gn:feature_class":"P",
    "gn:feature_code":"PPL",
    "gn:name":"Hokr el Ha\u00efssa",
    "gn:population":0,
    "gn:timezone":"Asia/Beirut",
    "iso:country":"LB",
    "name:und_x_variant":[
        "El Aakk\u00e2r",
        "Hikr el-Heesa",
        "\u1e28ukr al \u1e28\u012b\u015fah",
        "Hokr el Ha\u00efssa"
    ],
    "wof:name":"Hokr el Haissa",
    "wof:placetype":"locality"
},
  "geometry": {"coordinates":[36.05472,34.59639],"type":"Point"}
}