{
  "type": "Feature",
  "properties": {
    "gn:admin1_code":"9.0",
    "gn:asciiname":"Sir ed Danniye",
    "gn:country_code":"LB",
    "gn:dem":940,
    "gn:feature_class":"P",
    "gn:feature_code":"PPLA2",
    "gn:name":"S\u00eer ed Danniy\u00e9",
    "gn:population":0,
    "gn:timezone":"Asia/Beirut",
    "iso:country":"LB",
    "name:ara_x_preferred":[
        "\u0633\u064a\u0631 \u0627\u0644\u0636\u0646\u064a\u0629"
    ],
    "name:und_x_variant":[
        "S\u012br a\u1e11 \u1e10inn\u012byah",
        "S\u00eer ed Danniy\u00e9"
    ],
    "wof:name":"Sir ed Danniye",
    "wof:placetype":"locality"
},
  "geometry": {"coordinates":[36.03111,34.38528],"type":"Point"}
}