{
  "type": "Feature",
  "properties": {
    "gn:admin1_code":"5.0",
    "gn:asciiname":"Chahtoul",
    "gn:country_code":"LB",
    "gn:dem":950,
    "gn:feature_class":"P",
    "gn:feature_code":"PPL",
    "gn:name":"Chahto\u00fbl",
    "gn:population":0,
    "gn:timezone":"Asia/Beirut",
    "iso:country":"LB",
    "name:ara_x_preferred":[
        "\u0634\u062d\u062a\u0648\u0644"
    ],
    "name:und_x_variant":[
        "Chamtoul",
        "Sha\u1e29t\u016bl",
        "Chahto\u00fbl"
    ],
    "wof:name":"Chahtoul",
    "wof:placetype":"locality"
},
  "geometry": {"coordinates":[35.725,34.03444],"type":"Point"}
}