{
  "type": "Feature",
  "properties": {
    "gn:gn_country":"LB",
    "gn:gn_fcode":"PPLA2",
    "gn:gn_pop":20000,
    "gn:population":20000,
    "iso:country":"LB",
    "name:ara_x_preferred":[
        "\u0628\u0634\u0631\u064a"
    ],
    "name:arm_x_preferred":[
        "\u0532\u056b\u0577\u0561\u0580\u056b"
    ],
    "name:bul_x_preferred":[
        "\u0411\u0438\u0448\u0430\u0440\u0438"
    ],
    "name:cat_x_preferred":[
        "Bsharra"
    ],
    "name:chi_x_preferred":[
        "\u535c\u820d\u91cc"
    ],
    "name:cze_x_preferred":[
        "B\u0161arr\u00e9"
    ],
    "name:dut_x_preferred":[
        "Bsharri"
    ],
    "name:eng_x_preferred":[
        "Bsharri"
    ],
    "name:fre_x_preferred":[
        "Bcharr\u00e9"
    ],
    "name:geo_x_preferred":[
        "\u10d1\u10d8\u10e8\u10d0\u10e0\u10d8"
    ],
    "name:ger_x_preferred":[
        "Bischarri"
    ],
    "name:glg_x_preferred":[
        "Bxari"
    ],
    "name:gre_x_preferred":[
        "\u039c\u03c0\u03c3\u03b1\u03c1\u03af"
    ],
    "name:heb_x_preferred":[
        "\u05d1\u05e9\u05e8\u05d9"
    ],
    "name:ita_x_preferred":[
        "Bsharre"
    ],
    "name:lit_x_preferred":[
        "Be\u0161aris"
    ],
    "name:nno_x_preferred":[
        "Bsharri"
    ],
    "name:pam_x_preferred":[
        "Bsharri"
    ],
    "name:pol_x_preferred":[
        "Baszarri"
    ],
    "name:rus_x_preferred":[
        "\u0411\u0438\u0448\u0430\u0440\u0438"
    ],
    "name:sco_x_preferred":[
        "Bsharri"
    ],
    "name:spa_x_preferred":[
        "Bisharri"
    ],
    "name:swe_x_preferred":[
        "Bcharr\u00e9"
    ],
    "name:ukr_x_preferred":[
        "\u0411\u0456\u0448\u0430\u0440\u0456"
    ],
    "name:unk_x_variant":[
        "Bsharr\u012b"
    ],
    "qs_pg:aaroncc":"LB",
    "qs_pg:gn_country":"LB",
    "qs_pg:gn_fcode":"PPLA2",
    "qs_pg:gn_pop":20000,
    "qs_pg:name":"Bcharr\u00e9",
    "qs_pg:photos_9r":0,
    "qs_pg:photos_sr":0,
    "qs_pg:pop_sr":6,
    "qs_pg:qs_pg_placetype":"locality",
    "wof:name":"Bcharr\u00e9",
    "wof:placetype":"locality",
    "wof:population":20000
},
  "geometry": {"coordinates":[36.01056,34.25083],"type":"Point"}
}