{
  "type": "Feature",
  "properties": {
    "gn:admin1_code":"5.0",
    "gn:asciiname":"Al Hadath",
    "gn:cc2":"LB",
    "gn:country_code":"LB",
    "gn:dem":122,
    "gn:feature_class":"P",
    "gn:feature_code":"PPL",
    "gn:name":"Al \u1e28adath",
    "gn:population":0,
    "gn:timezone":"Asia/Beirut",
    "iso:country":"LB",
    "name:ara_x_preferred":[
        "\u0627\u0644\u062d\u062f\u062b"
    ],
    "name:und_x_variant":[
        "Hadeth",
        "El Hadeth",
        "Al \u1e28adath"
    ],
    "wof:name":"Al Hadath",
    "wof:placetype":"locality"
},
  "geometry": {"coordinates":[35.53333,33.83333],"type":"Point"}
}