{
  "type": "Feature",
  "properties": {
    "gn:admin1_code":"7.0",
    "gn:asciiname":"Harouf",
    "gn:country_code":"LB",
    "gn:dem":397,
    "gn:feature_class":"P",
    "gn:feature_code":"PPL",
    "gn:name":"H\u00e2ro\u00fbf",
    "gn:population":0,
    "gn:timezone":"Asia/Beirut",
    "iso:country":"LB",
    "name:ara_x_preferred":[
        "\u062d\u0627\u0631\u0648\u0641"
    ],
    "name:fra_x_preferred":[
        "Harouf"
    ],
    "name:ita_x_preferred":[
        "Harouf"
    ],
    "name:nno_x_preferred":[
        "Harouf"
    ],
    "name:und_x_variant":[
        "\u1e28\u0101r\u016bf",
        "H\u00e2ro\u00fbf"
    ],
    "wof:name":"Harouf",
    "wof:placetype":"locality"
},
  "geometry": {"coordinates":[35.44194,33.37472],"type":"Point"}
}