{
  "type": "Feature",
  "properties": {
    "gn:admin1_code":"9.0",
    "gn:asciiname":"Tannourine el Faouqa",
    "gn:country_code":"LB",
    "gn:dem":1382,
    "gn:feature_class":"P",
    "gn:feature_code":"PPL",
    "gn:name":"Tanno\u00fbr\u00eene el Faouqa",
    "gn:population":0,
    "gn:timezone":"Asia/Beirut",
    "iso:country":"LB",
    "name:ara_x_preferred":[
        "\u062a\u0646\u0648\u0631\u064a\u0646 \u0627\u0644\u0641\u0648\u0642\u0627"
    ],
    "name:und_x_variant":[
        "Tann\u016br\u012bn al Fawq\u0101",
        "Tanno\u00fbr\u00eene el Faouqa"
    ],
    "wof:name":"Tannourine el Faouqa",
    "wof:placetype":"locality"
},
  "geometry": {"coordinates":[35.90194,34.1825],"type":"Point"}
}