{
  "type": "Feature",
  "properties": {
    "gn:admin1_code":"5.0",
    "gn:asciiname":"Es Souane",
    "gn:country_code":"LB",
    "gn:dem":1190,
    "gn:feature_class":"P",
    "gn:feature_code":"PPL",
    "gn:name":"Es Sou\u00e2n\u00e9",
    "gn:population":0,
    "gn:timezone":"Asia/Beirut",
    "iso:country":"LB",
    "name:und_x_variant":[
        "A\u015f \u015eaww\u0101nah",
        "Es Sou\u00e2n\u00e9"
    ],
    "wof:name":"Es Souane",
    "wof:placetype":"locality"
},
  "geometry": {"coordinates":[35.73083,33.99167],"type":"Point"}
}