{
  "type": "Feature",
  "properties": {
    "gn:admin1_code":"9.0",
    "gn:asciiname":"Haqlet el Baida",
    "gn:country_code":"LB",
    "gn:dem":832,
    "gn:feature_class":"P",
    "gn:feature_code":"PPL",
    "gn:name":"Haqlet el Ba\u00efda",
    "gn:population":0,
    "gn:timezone":"Asia/Beirut",
    "iso:country":"LB",
    "wof:name":"Haqlet el Baida",
    "wof:placetype":"locality"
},
  "geometry": {"coordinates":[35.96472,34.3875],"type":"Point"}
}