{
  "type": "Feature",
  "properties": {
    "gn:admin1_code":"7.0",
    "gn:asciiname":"Ain Qana",
    "gn:country_code":"LB",
    "gn:dem":693,
    "gn:feature_class":"P",
    "gn:feature_code":"PPL",
    "gn:name":"A\u00efn Q\u00e2na",
    "gn:population":0,
    "gn:timezone":"Asia/Beirut",
    "iso:country":"LB",
    "name:ara_x_preferred":[
        "\u0639\u064a\u0646 \u0642\u0627\u0646\u0627"
    ],
    "name:und_x_variant":[
        "\u2018Ayn Q\u0101n\u0101",
        "A\u00efn Q\u00e2na"
    ],
    "wof:name":"Ain Qana",
    "wof:placetype":"locality"
},
  "geometry": {"coordinates":[35.51028,33.47222],"type":"Point"}
}