{
  "type": "Feature",
  "properties": {
    "gn:admin1_code":"5.0",
    "gn:asciiname":"Baqaoun el Faouqa",
    "gn:country_code":"LB",
    "gn:dem":419,
    "gn:feature_class":"P",
    "gn:feature_code":"PPL",
    "gn:name":"Baqaoun el Faouqa",
    "gn:population":0,
    "gn:timezone":"Asia/Beirut",
    "iso:country":"LB",
    "name:ara_x_preferred":[
        "\u0627\u0644\u0628\u0642\u0639\u0648\u0646"
    ],
    "name:ara_x_variant":[
        "\u0628\u0642\u0639\u0648\u0646 \u0627\u0644\u0641\u0648\u0642\u0627"
    ],
    "name:und_x_variant":[
        "Baq\u2018\u016bn al Fawq\u0101",
        "Baqaoun el Faouqa",
        "Al Baqa\u2018\u016bn"
    ],
    "wof:name":"Baqaoun el Faouqa",
    "wof:placetype":"locality"
},
  "geometry": {"coordinates":[35.47806,33.67528],"type":"Point"}
}