{
  "type": "Feature",
  "properties": {
    "gn:admin1_code":"8.0",
    "gn:asciiname":"El Qaraaoun",
    "gn:country_code":"LB",
    "gn:dem":972,
    "gn:feature_class":"P",
    "gn:feature_code":"PPL",
    "gn:name":"El Qaraaoun",
    "gn:population":0,
    "gn:timezone":"Asia/Beirut",
    "iso:country":"LB",
    "name:ara_x_preferred":[
        "\u0627\u0644\u0642\u0631\u0639\u0648\u0646"
    ],
    "name:und_x_variant":[
        "Al Qar\u2018\u016bn",
        "Qaraaoun",
        "Al Qar\u2018awn",
        "El-Qer\u2018ann",
        "Al Qir\u2018awn",
        "El Qaraoun",
        "El Qar\u2018aun",
        "El Qaraaoun"
    ],
    "wof:name":"El Qaraaoun",
    "wof:placetype":"locality"
},
  "geometry": {"coordinates":[35.72194000000001,33.56278],"type":"Point"}
}