{
  "type": "Feature",
  "properties": {
    "gn:admin1_code":"7.0",
    "gn:asciiname":"Yatar",
    "gn:country_code":"LB",
    "gn:dem":677,
    "gn:feature_class":"P",
    "gn:feature_code":"PPL",
    "gn:name":"Y\u00e2tar",
    "gn:population":0,
    "gn:timezone":"Asia/Beirut",
    "iso:country":"LB",
    "name:ara_x_preferred":[
        "\u064a\u0627\u0637\u0631"
    ],
    "name:ita_x_preferred":[
        "Yater"
    ],
    "name:nno_x_preferred":[
        "Yater"
    ],
    "name:und_x_variant":[
        "Y\u00e2tar",
        "Y\u0101tar",
        "Y\u0101\u0163ar"
    ],
    "wof:name":"Yatar",
    "wof:placetype":"locality"
},
  "geometry": {"coordinates":[35.33028,33.15417],"type":"Point"}
}