{
  "type": "Feature",
  "properties": {
    "gn:admin1_code":"10.0",
    "gn:asciiname":"Qarqaf",
    "gn:country_code":"LB",
    "gn:dem":246,
    "gn:feature_class":"P",
    "gn:feature_code":"PPL",
    "gn:name":"Qarqaf",
    "gn:population":0,
    "gn:timezone":"Asia/Beirut",
    "iso:country":"LB",
    "wof:name":"Qarqaf",
    "wof:placetype":"locality"
},
  "geometry": {"coordinates":[36.02056,34.48472],"type":"Point"}
}