{
  "type": "Feature",
  "properties": {
    "gn:admin1_code":"5.0",
    "gn:asciiname":"Ain Abael",
    "gn:country_code":"LB",
    "gn:dem":961,
    "gn:feature_class":"P",
    "gn:feature_code":"PPL",
    "gn:name":"A\u00efn Abael",
    "gn:population":0,
    "gn:timezone":"Asia/Beirut",
    "iso:country":"LB",
    "name:ara_x_preferred":[
        "\u0639\u064a\u0646 \u0627\u0628\u0639\u0644"
    ],
    "name:ara_x_variant":[
        "\u0639\u064a\u0646 \u0628\u0639\u0627\u0644"
    ],
    "name:und_x_variant":[
        "A\u00efn Abael",
        "\u2018Ayn Ba\u2018\u0101l",
        "\u2018Ayn Ab\u2018al"
    ],
    "wof:name":"Ain Abael",
    "wof:placetype":"locality"
},
  "geometry": {"coordinates":[35.71246,34.04084],"type":"Point"}
}