{
  "type": "Feature",
  "properties": {
    "gn:admin1_code":"9.0",
    "gn:asciiname":"Ed Dahr",
    "gn:country_code":"LB",
    "gn:dem":662,
    "gn:feature_class":"P",
    "gn:feature_code":"PPL",
    "gn:name":"Ed Dahr",
    "gn:population":0,
    "gn:timezone":"Asia/Beirut",
    "iso:country":"LB",
    "wof:name":"Ed Dahr",
    "wof:placetype":"locality"
},
  "geometry": {"coordinates":[35.81222,34.24722],"type":"Point"}
}