{
  "type": "Feature",
  "properties": {
    "gn:admin1_code":"5.0",
    "gn:asciiname":"Aabboud",
    "gn:country_code":"LB",
    "gn:dem":1158,
    "gn:feature_class":"P",
    "gn:feature_code":"PPL",
    "gn:name":"Aabbo\u00fbd",
    "gn:population":0,
    "gn:timezone":"Asia/Beirut",
    "iso:country":"LB",
    "name:ara_x_preferred":[
        "\u0639\u0628\u0648\u062f"
    ],
    "name:und_x_variant":[
        "\u2018Abb\u016bd",
        "Aabbo\u00fbd"
    ],
    "wof:name":"Aabboud",
    "wof:placetype":"locality"
},
  "geometry": {"coordinates":[35.8575,34.1025],"type":"Point"}
}