{
  "type": "Feature",
  "properties": {
    "gn:admin1_code":"5.0",
    "gn:asciiname":"Gharife",
    "gn:country_code":"LB",
    "gn:dem":712,
    "gn:feature_class":"P",
    "gn:feature_code":"PPL",
    "gn:name":"Ghar\u00eef\u00e9",
    "gn:population":0,
    "gn:timezone":"Asia/Beirut",
    "iso:country":"LB",
    "name:ara_x_preferred":[
        "\u063a\u0631\u064a\u0641\u0629"
    ],
    "name:und_x_variant":[
        "Ghar\u012bfah",
        "Ghar\u00eef\u00e9"
    ],
    "wof:name":"Gharife",
    "wof:placetype":"locality"
},
  "geometry": {"coordinates":[35.55806,33.63639000000001],"type":"Point"}
}