{
  "type": "Feature",
  "properties": {
    "gn:admin1_code":"5.0",
    "gn:asciiname":"Mar Mqine",
    "gn:country_code":"LB",
    "gn:dem":1163,
    "gn:feature_class":"P",
    "gn:feature_code":"PPL",
    "gn:name":"M\u00e2r Mq\u00eene",
    "gn:population":0,
    "gn:timezone":"Asia/Beirut",
    "iso:country":"LB",
    "name:und_x_variant":[
        "Ann\u00e2ya",
        "M\u0101r Mq\u012bn",
        "M\u00e2r Mq\u00eene"
    ],
    "wof:name":"Mar Mqine",
    "wof:placetype":"locality"
},
  "geometry": {"coordinates":[35.75,34.11306],"type":"Point"}
}