{
  "type": "Feature",
  "properties": {
    "gn:admin1_code":"9.0",
    "gn:asciiname":"El Biara",
    "gn:country_code":"LB",
    "gn:dem":1474,
    "gn:feature_class":"P",
    "gn:feature_code":"PPL",
    "gn:name":"El Bi\u00e2ra",
    "gn:population":0,
    "gn:timezone":"Asia/Beirut",
    "iso:country":"LB",
    "name:und_x_variant":[
        "Khar\u1e29al",
        "Karhel",
        "El Bi\u00e2ra"
    ],
    "wof:name":"El Biara",
    "wof:placetype":"locality"
},
  "geometry": {"coordinates":[35.905,34.18806],"type":"Point"}
}