{
  "type": "Feature",
  "properties": {
    "gn:admin1_code":"5.0",
    "gn:asciiname":"Bein ed Darbain",
    "gn:country_code":"LB",
    "gn:dem":398,
    "gn:feature_class":"P",
    "gn:feature_code":"PPL",
    "gn:name":"Be\u00efn ed Darba\u00efn",
    "gn:population":0,
    "gn:timezone":"Asia/Beirut",
    "iso:country":"LB",
    "wof:name":"Bein ed Darbain",
    "wof:placetype":"locality"
},
  "geometry": {"coordinates":[35.68861,34.15944],"type":"Point"}
}