{
  "type": "Feature",
  "properties": {
    "gn:admin1_code":"6.0",
    "gn:asciiname":"Tair Debbe",
    "gn:country_code":"LB",
    "gn:dem":202,
    "gn:feature_class":"P",
    "gn:feature_code":"PPL",
    "gn:name":"Ta\u00efr Debb\u00e9",
    "gn:population":0,
    "gn:timezone":"Asia/Beirut",
    "iso:country":"LB",
    "name:ara_x_preferred":[
        "\u0637\u064a\u0631 \u062f\u0650\u0628\u0627"
    ],
    "name:ara_x_variant":[
        "\u0637\u064a\u0631 \u062f\u0628\u0627"
    ],
    "name:ita_x_preferred":[
        "Tayr Dibba"
    ],
    "name:und_x_variant":[
        "\u0162ayr Dibbah",
        "Ta\u00efr Debb\u00e9",
        "\u0162ayr Dibb\u0101"
    ],
    "wof:name":"Tair Debbe",
    "wof:placetype":"locality"
},
  "geometry": {"coordinates":[35.27861,33.27444000000001],"type":"Point"}
}