{
  "type": "Feature",
  "properties": {
    "gn:admin1_code":"9.0",
    "gn:asciiname":"Karm Sadde",
    "gn:country_code":"LB",
    "gn:dem":608,
    "gn:feature_class":"P",
    "gn:feature_code":"PPL",
    "gn:name":"Karm Sadd\u00e9",
    "gn:population":0,
    "gn:timezone":"Asia/Beirut",
    "iso:country":"LB",
    "name:ara_x_preferred":[
        "\u0643\u0631\u0645 \u0633\u062f\u0629"
    ],
    "name:und_x_variant":[
        "Karm as Saddah",
        "Karm Sadd\u00e9",
        "Karm Saddah",
        "Karmsaddeh",
        "Karm Saddeh"
    ],
    "wof:name":"Karm Sadde",
    "wof:placetype":"locality"
},
  "geometry": {"coordinates":[35.89111,34.30583],"type":"Point"}
}