{
  "type": "Feature",
  "properties": {
    "gn:admin1_code":"7.0",
    "gn:asciiname":"El Mayas",
    "gn:country_code":"LB",
    "gn:dem":674,
    "gn:feature_class":"P",
    "gn:feature_code":"PPL",
    "gn:name":"El May\u00e2s",
    "gn:population":0,
    "gn:timezone":"Asia/Beirut",
    "iso:country":"LB",
    "name:ara_x_preferred":[
        "\u0627\u0644\u0645\u064a\u0627\u0633"
    ],
    "name:und_x_variant":[
        "El May\u00e2s",
        "Al Mayy\u0101s"
    ],
    "wof:name":"El Mayas",
    "wof:placetype":"locality"
},
  "geometry": {"coordinates":[35.44028,33.18333],"type":"Point"}
}