{
  "type": "Feature",
  "properties": {
    "gn:admin1_code":"8.0",
    "gn:asciiname":"Raite",
    "gn:country_code":"LB",
    "gn:dem":1066,
    "gn:feature_class":"P",
    "gn:feature_code":"PPL",
    "gn:name":"Ra\u00efte",
    "gn:population":0,
    "gn:timezone":"Asia/Beirut",
    "iso:country":"LB",
    "name:ara_x_preferred":[
        "\u0631\u0639\u064a\u062a"
    ],
    "name:und_x_variant":[
        "\u2018Aytah",
        "R\u2018\u012bt",
        "Ra\u00efte",
        "Ra\u2018\u012bt"
    ],
    "wof:name":"Raite",
    "wof:placetype":"locality"
},
  "geometry": {"coordinates":[36.04472,33.82972],"type":"Point"}
}