{
  "type": "Feature",
  "properties": {
    "gn:admin1_code":"5.0",
    "gn:asciiname":"Haret es Saide",
    "gn:country_code":"LB",
    "gn:dem":493,
    "gn:feature_class":"P",
    "gn:feature_code":"PPL",
    "gn:name":"Haret es Sa\u00efd\u00e9",
    "gn:population":0,
    "gn:timezone":"Asia/Beirut",
    "iso:country":"LB",
    "wof:name":"Haret es Saide",
    "wof:placetype":"locality"
},
  "geometry": {"coordinates":[35.58722,33.82139],"type":"Point"}
}