{
  "type": "Feature",
  "properties": {
    "gn:admin1_code":"6.0",
    "gn:asciiname":"Btaichiye",
    "gn:country_code":"LB",
    "gn:dem":397,
    "gn:feature_class":"P",
    "gn:feature_code":"PPL",
    "gn:name":"Bta\u00efch\u00eey\u00e9",
    "gn:population":0,
    "gn:timezone":"Asia/Beirut",
    "iso:country":"LB",
    "name:ara_x_preferred":[
        "\u0627\u0644\u0628\u0637\u064a\u0634\u064a\u0629"
    ],
    "name:ara_x_variant":[
        "\u0628\u0637\u064a\u0634\u064a\u0629"
    ],
    "name:und_x_variant":[
        "Bta\u00efch\u00eey\u00e9",
        "Al Bu\u0163aysh\u012byah",
        "Bu\u0163aysh\u012byah"
    ],
    "wof:name":"Btaichiye",
    "wof:placetype":"locality"
},
  "geometry": {"coordinates":[35.20917,33.10722],"type":"Point"}
}