{
  "type": "Feature",
  "properties": {
    "gn:admin1_code":"10.0",
    "gn:asciiname":"Haret en Namous",
    "gn:country_code":"LB",
    "gn:dem":1254,
    "gn:feature_class":"P",
    "gn:feature_code":"PPL",
    "gn:name":"Haret en Namous",
    "gn:population":0,
    "gn:timezone":"Asia/Beirut",
    "iso:country":"LB",
    "wof:name":"Haret en Namous",
    "wof:placetype":"locality"
},
  "geometry": {"coordinates":[36.3125,34.5175],"type":"Point"}
}