{
  "type": "Feature",
  "properties": {
    "gn:admin1_code":"5.0",
    "gn:asciiname":"Ain ed Delbe",
    "gn:country_code":"LB",
    "gn:dem":1254,
    "gn:feature_class":"P",
    "gn:feature_code":"PPL",
    "gn:name":"A\u00efn ed Delb\u00e9",
    "gn:population":0,
    "gn:timezone":"Asia/Beirut",
    "iso:country":"LB",
    "name:ara_x_preferred":[
        "\u0639\u064a\u0646 \u0627\u0644\u062f\u0644\u0628\u0629"
    ],
    "name:und_x_variant":[
        "\u2018Ayn ad Dulbah",
        "A\u00efn ed Delb\u00e9"
    ],
    "wof:name":"Ain ed Delbe",
    "wof:placetype":"locality"
},
  "geometry": {"coordinates":[35.76778,34.02944],"type":"Point"}
}