{
  "type": "Feature",
  "properties": {
    "gn:admin1_code":"9.0",
    "gn:asciiname":"Kfar Zaina",
    "gn:country_code":"LB",
    "gn:dem":184,
    "gn:feature_class":"P",
    "gn:feature_code":"PPL",
    "gn:name":"Kfar Za\u00efna",
    "gn:population":0,
    "gn:timezone":"Asia/Beirut",
    "iso:country":"LB",
    "name:ara_x_preferred":[
        "\u0643\u0641\u0631 \u0632\u064a\u0646\u0627"
    ],
    "name:und_x_variant":[
        "Kafr Zayn\u0101",
        "Kfar Za\u00efna",
        "Kfarzeina"
    ],
    "wof:name":"Kfar Zaina",
    "wof:placetype":"locality"
},
  "geometry": {"coordinates":[35.87874,34.36716],"type":"Point"}
}